Workbook

Sheet storm_data_search_results
A1: EVENT_ID | B1: CZ_NAME_STR | C1: GEONAME | D1: GeoFips | E1: BEGIN_LOCATION | F1: BEGIN_DATE | G1: BEGIN_TIME | H1: EVENT_TYPE | I1: MAGNITUDE | J1: TOR_F_SCALE | K1: DEATHS_DIRECT | L1: INJURIES_DIRECT | M1: DAMAGE_PROPERTY_NUM | N1: DAMAGE_CROPS_NUM | O1: STATE_ABBR | P1: CZ_TIMEZONE | Q1: MAGNITUDE_TYPE | R1: EPISODE_ID | S1: CZ_TYPE | T1: CZ_FIPS | U1: WFO | V1: INJURIES_INDIRECT | W1: DEATHS_INDIRECT | X1: SOURCE | Y1: FLOOD_CAUSE | Z1: TOR_LENGTH | AA1: TOR_WIDTH | AB1: BEGIN_RANGE | AC1: BEGIN_AZIMUTH | AD1: END_RANGE | AE1: END_AZIMUTH | AF1: END_LOCATION | AG1: END_DATE | AH1: END_TIME | AI1: BEGIN_LAT | AJ1: BEGIN_LON | AK1: END_LAT | AL1: END_LON | AM1: EVENT_NARRATIVE | AN1: EPISODE_NARRATIVE | AO1: ABSOLUTE_ROWNUMBER
A2: 5716192 | B2: COASTAL PALM BEACH (ZONE) | C2: =_xlfn.XLOOKUP(B2,Match!$A$2:$A$111,Match!$B$2:$B$111) -> Palm Beach, FL | D2: =_xlfn.XLOOKUP(C2,Validation!$B$2:$B$68,Validation!$A$2:$A$68) -> 12099 | F2: 36401 | G2: 2330 | H2: Hurricane (Typhoon) | K2: 1 | L2: 0 | M2: 100000 | N2: 0 | O2: FL | P2: EST | R2: 2412133 | S2: Z | T2: 68 | U2: MFL | V2: 0 | W2: 0 | X2: NEWSPAPER | AG2: 36401 | AH2: 2330 | AN2: Large swells from Hurricane Dennis, which at the time was located off the North Carolina coast, swamped six small boats, mainly at Boca Raton and Hillsboro Inlets. One person was washed overboard and drowned. The swells also caused mostly minor beach erosion along the Palm Beach and Broward county shorelines. | AO2: 85
A3: 5716202 | B3: COASTAL DADE (ZONE) | C3: =_xlfn.XLOOKUP(B3,Match!$A$2:$A$111,Match!$B$2:$B$111) -> Miami-Dade, FL | D3: =_xlfn.XLOOKUP(C3,Validation!$B$2:$B$68,Validation!$A$2:$A$68) -> 12086 | F3: 36416 | G3: 1200 | H3: Hurricane (Typhoon) | K3: 0 | L3: 0 | M3: 0 | N3: 0 | O3: FL | P3: EST | R3: 2412137 | S3: Z | T3: 74 | U3: MFL | V3: 0 | W3: 0 | X3: NEWSPAPER | AG3: 36417 | AH3: 2300 | AN3: Large and powerful hurricane Floyd, approached the southeast Florida coast on September 13 and moved north of the area by September 15. Southeast Florida remained on the weak" side of Floyd with minimal effects | AO3: mostly to marine interests. Total damage from Floyd in south Florida is estimated at $100 thousand | AP3: most of which was in Palm Beach county. This figure does not include preparation costs which were estimated to have been near $3 million in Palm Beach County alone.
A4: 5716201 | B4: COASTAL BROWARD (ZONE) | C4: =_xlfn.XLOOKUP(B4,Match!$A$2:$A$111,Match!$B$2:$B$111) -> Broward, FL | D4: =_xlfn.XLOOKUP(C4,Validation!$B$2:$B$68,Validation!$A$2:$A$68) -> 12011 | F4: 36416 | G4: 1200 | H4: Hurricane (Typhoon) | K4: 0 | L4: 0 | M4: 0 | N4: 0 | O4: FL | P4: EST | R4: 2412137 | S4: Z | T4: 72 | U4: MFL | V4: 0 | W4: 0 | X4: NEWSPAPER | AG4: 36417 | AH4: 2300 | AN4: Large and powerful hurricane Floyd, approached the southeast Florida coast on September 13 and moved north of the area by September 15. Southeast Florida remained on the weak" side of Floyd with minimal effects | AO4: mostly to marine interests. Total damage from Floyd in south Florida is estimated at $100 thousand | AP4: most of which was in Palm Beach county. This figure does not include preparation costs which were estimated to have been near $3 million in Palm Beach County alone.
A5: 5716203 | B5: COASTAL PALM BEACH (ZONE) | C5: =_xlfn.XLOOKUP(B5,Match!$A$2:$A$111,Match!$B$2:$B$111) -> Palm Beach, FL | D5: =_xlfn.XLOOKUP(C5,Validation!$B$2:$B$68,Validation!$A$2:$A$68) -> 12099 | F5: 36416 | G5: 1200 | H5: Hurricane (Typhoon) | K5: 0 | L5: 0 | M5: 100000 | N5: 0 | O5: FL | P5: EST | R5: 2412137 | S5: Z | T5: 68 | U5: MFL | V5: 0 | W5: 0 | X5: NEWSPAPER | AG5: 36417 | AH5: 2300 | AN5: Large and powerful hurricane Floyd, approached the southeast Florida coast on September 13 and moved north of the area by September 15. Southeast Florida remained on the weak" side of Floyd with minimal effects | AO5: mostly to marine interests. Total damage from Floyd in south Florida is estimated at $100 thousand | AP5: most of which was in Palm Beach county. This figure does not include preparation costs which were estimated to have been near $3 million in Palm Beach County alone.
A6: 5717086 | B6: DE SOTO (ZONE) | C6: =_xlfn.XLOOKUP(B6,Match!$A$2:$A$111,Match!$B$2:$B$111) -> DeSoto, FL | D6: =_xlfn.XLOOKUP(C6,Validation!$B$2:$B$68,Validation!$A$2:$A$68) -> 12027 | F6: 36417 | G6: 1200 | H6: Hurricane (Typhoon) | K6: 0 | L6: 0 | M6: 0 | N6: 0 | O6: FL | P6: EST | R6: 2412730 | S6: Z | T6: 61 | U6: TBW | V6: 0 | W6: 0 | X6: OFFICIAL NWS OBS. | AG6: 36417 | AH6: 1800 | AN6: The outer rainbands of hurricane Floyd moved parallel to the east coast of Florida and produced tropical storm force wind gusts primarily across interior counties within West Central Florida. A maximum wind gust of 58 mph was reported at Lakeland Linder Airport around 1700 EST on the 14th._x000D_ _x000D_ Tropical storm force wind gusts uprooted a few large trees and downed power lines in and around Lakeland in Polk County. One mobile home lost its roof from tropical storm force winds on Rock Ridge Road in Lakeland. | AO6: 89
A7: 5717083 | B7: LEE (ZONE) | C7: =_xlfn.XLOOKUP(B7,Match!$A$2:$A$111,Match!$B$2:$B$111) -> Lee, FL | D7: =_xlfn.XLOOKUP(C7,Validation!$B$2:$B$68,Validation!$A$2:$A$68) -> 12071 | F7: 36417 | G7: 1200 | H7: Hurricane (Typhoon) | K7: 0 | L7: 0 | M7: 0 | N7: 0 | O7: FL | P7: EST | R7: 2412730 | S7: Z | T7: 65 | U7: TBW | V7: 0 | W7: 0 | X7: OFFICIAL NWS OBS. | AG7: 36417 | AH7: 1800 | AN7: The outer rainbands of hurricane Floyd moved parallel to the east coast of Florida and produced tropical storm force wind gusts primarily across interior counties within West Central Florida. A maximum wind gust of 58 mph was reported at Lakeland Linder Airport around 1700 EST on the 14th._x000D_ _x000D_ Tropical storm force wind gusts uprooted a few large trees and downed power lines in and around Lakeland in Polk County. One mobile home lost its roof from tropical storm force winds on Rock Ridge Road in Lakeland. | AO7: 90
A8: 5717081 | B8: HIGHLANDS (ZONE) | C8: =_xlfn.XLOOKUP(B8,Match!$A$2:$A$111,Match!$B$2:$B$111) -> Highlands, FL | D8: =_xlfn.XLOOKUP(C8,Validation!$B$2:$B$68,Validation!$A$2:$A$68) -> 12055 | F8: 36417 | G8: 1200 | H8: Hurricane (Typhoon) | K8: 0 | L8: 0 | M8: 0 | N8: 0 | O8: FL | P8: EST | R8: 2412730 | S8: Z | T8: 57 | U8: TBW | V8: 0 | W8: 0 | X8: OFFICIAL NWS OBS. | AG8: 36417 | AH8: 1800 | AN8: The outer rainbands of hurricane Floyd moved parallel to the east coast of Florida and produced tropical storm force wind gusts primarily across interior counties within West Central Florida. A maximum wind gust of 58 mph was reported at Lakeland Linder Airport around 1700 EST on the 14th._x000D_ _x000D_ Tropical storm force wind gusts uprooted a few large trees and downed power lines in and around Lakeland in Polk County. One mobile home lost its roof from tropical storm force winds on Rock Ridge Road in Lakeland. | AO8: 91
A9: 5717080 | B9: CHARLOTTE (ZONE) | C9: =_xlfn.XLOOKUP(B9,Match!$A$2:$A$111,Match!$B$2:$B$111) -> Charlotte, FL | D9: =_xlfn.XLOOKUP(C9,Validation!$B$2:$B$68,Validation!$A$2:$A$68) -> 12015 | F9: 36417 | G9: 1200 | H9: Hurricane (Typhoon) | K9: 0 | L9: 0 | M9: 0 | N9: 0 | O9: FL | P9: EST | R9: 2412730 | S9: Z | T9: 62 | U9: TBW | V9: 0 | W9: 0 | X9: OFFICIAL NWS OBS. | AG9: 36417 | AH9: 1800 | AN9: The outer rainbands of hurricane Floyd moved parallel to the east coast of Florida and produced tropical storm force wind gusts primarily across interior counties within West Central Florida. A maximum wind gust of 58 mph was reported at Lakeland Linder Airport around 1700 EST on the 14th._x000D_ _x000D_ Tropical storm force wind gusts uprooted a few large trees and downed power lines in and around Lakeland in Polk County. One mobile home lost its roof from tropical storm force winds on Rock Ridge Road in Lakeland. | AO9: 92
A10: 5717079 | B10: POLK (ZONE) | C10: =_xlfn.XLOOKUP(B10,Match!$A$2:$A$111,Match!$B$2:$B$111) -> Polk, FL | D10: =_xlfn.XLOOKUP(C10,Validation!$B$2:$B$68,Validation!$A$2:$A$68) -> 12105 | F10: 36417 | G10: 1200 | H10: Hurricane (Typhoon) | K10: 0 | L10: 0 | M10: 20000 | N10: 0 | O10: FL | P10: EST | R10: 2412730 | S10: Z | T10: 52 | U10: TBW | V10: 0 | W10: 0 | X10: OFFICIAL NWS OBS. | AG10: 36417 | AH10: 1800 | AN10: The outer rainbands of hurricane Floyd moved parallel to the east coast of Florida and produced tropical storm force wind gusts primarily across interior counties within West Central Florida. A maximum wind gust of 58 mph was reported at Lakeland Linder Airport around 1700 EST on the 14th._x000D_ _x000D_ Tropical storm force wind gusts uprooted a few large trees and downed power lines in and around Lakeland in Polk County. One mobile home lost its roof from tropical storm force winds on Rock Ridge Road in Lakeland. | AO10: 93
A11: 5717082 | B11: HILLSBOROUGH (ZONE) | C11: =_xlfn.XLOOKUP(B11,Match!$A$2:$A$111,Match!$B$2:$B$111) -> Hillsborough, FL | D11: =_xlfn.XLOOKUP(C11,Validation!$B$2:$B$68,Validation!$A$2:$A$68) -> 12057 | F11: 36417 | G11: 1200 | H11: Hurricane (Typhoon) | K11: 0 | L11: 0 | M11: 0 | N11: 0 | O11: FL | P11: EST | R11: 2412730 | S11: Z | T11: 51 | U11: TBW | V11: 0 | W11: 0 | X11: OFFICIAL NWS OBS. | AG11: 36417 | AH11: 1800 | AN11: The outer rainbands of hurricane Floyd moved parallel to the east coast of Florida and produced tropical storm force wind gusts primarily across interior counties within West Central Florida. A maximum wind gust of 58 mph was reported at Lakeland Linder Airport around 1700 EST on the 14th._x000D_ _x000D_ Tropical storm force wind gusts uprooted a few large trees and downed power lines in and around Lakeland in Polk County. One mobile home lost its roof from tropical storm force winds on Rock Ridge Road in Lakeland. | AO11: 94
A12: 5717085 | B12: SARASOTA (ZONE) | C12: =_xlfn.XLOOKUP(B12,Match!$A$2:$A$111,Match!$B$2:$B$111) -> Sarasota, FL | D12: =_xlfn.XLOOKUP(C12,Validation!$B$2:$B$68,Validation!$A$2:$A$68) -> 12115 | F12: 36417 | G12: 1200 | H12: Hurricane (Typhoon) | K12: 0 | L12: 0 | M12: 0 | N12: 0 | O12: FL | P12: EST | R12: 2412730 | S12: Z | T12: 60 | U12: TBW | V12: 0 | W12: 0 | X12: OFFICIAL NWS OBS. | AG12: 36417 | AH12: 1800 | AN12: The outer rainbands of hurricane Floyd moved parallel to the east coast of Florida and produced tropical storm force wind gusts primarily across interior counties within West Central Florida. A maximum wind gust of 58 mph was reported at Lakeland Linder Airport around 1700 EST on the 14th._x000D_ _x000D_ Tropical storm force wind gusts uprooted a few large trees and downed power lines in and around Lakeland in Polk County. One mobile home lost its roof from tropical storm force winds on Rock Ridge Road in Lakeland. | AO12: 95
A13: 5717084 | B13: MANATEE (ZONE) | C13: =_xlfn.XLOOKUP(B13,Match!$A$2:$A$111,Match!$B$2:$B$111) -> Manatee, FL | D13: =_xlfn.XLOOKUP(C13,Validation!$B$2:$B$68,Validation!$A$2:$A$68) -> 12081 | F13: 36417 | G13: 1200 | H13: Hurricane (Typhoon) | K13: 0 | L13: 0 | M13: 0 | N13: 0 | O13: FL | P13: EST | R13: 2412730 | S13: Z | T13: 55 | U13: TBW | V13: 0 | W13: 0 | X13: OFFICIAL NWS OBS. | AG13: 36417 | AH13: 1800 | AN13: The outer rainbands of hurricane Floyd moved parallel to the east coast of Florida and produced tropical storm force wind gusts primarily across interior counties within West Central Florida. A maximum wind gust of 58 mph was reported at Lakeland Linder Airport around 1700 EST on the 14th._x000D_ _x000D_ Tropical storm force wind gusts uprooted a few large trees and downed power lines in and around Lakeland in Polk County. One mobile home lost its roof from tropical storm force winds on Rock Ridge Road in Lakeland. | AO13: 96
A14: 5717087 | B14: HARDEE (ZONE) | C14: =_xlfn.XLOOKUP(B14,Match!$A$2:$A$111,Match!$B$2:$B$111) -> Hardee, FL | D14: =_xlfn.XLOOKUP(C14,Validation!$B$2:$B$68,Validation!$A$2:$A$68) -> 12049 | F14: 36417 | G14: 1200 | H14: Hurricane (Typhoon) | K14: 0 | L14: 0 | M14: 0 | N14: 0 | O14: FL | P14: EST | R14: 2412730 | S14: Z | T14: 56 | U14: TBW | V14: 0 | W14: 0 | X14: OFFICIAL NWS OBS. | AG14: 36417 | AH14: 1800 | AN14: The outer rainbands of hurricane Floyd moved parallel to the east coast of Florida and produced tropical storm force wind gusts primarily across interior counties within West Central Florida. A maximum wind gust of 58 mph was reported at Lakeland Linder Airport around 1700 EST on the 14th._x000D_ _x000D_ Tropical storm force wind gusts uprooted a few large trees and downed power lines in and around Lakeland in Polk County. One mobile home lost its roof from tropical storm force winds on Rock Ridge Road in Lakeland. | AO14: 97
A15: 5717618 | B15: ST. LUCIE (ZONE) | C15: =_xlfn.XLOOKUP(B15,Match!$A$2:$A$111,Match!$B$2:$B$111) -> St. Lucie, FL | D15: =_xlfn.XLOOKUP(C15,Validation!$B$2:$B$68,Validation!$A$2:$A$68) -> 12111 | F15: 36417 | G15: 2000 | H15: Hurricane (Typhoon) | K15: 0 | L15: 0 | M15: 50000 | N15: 0 | O15: FL | P15: EST | R15: 2413683 | S15: Z | T15: 59 | U15: MLB | V15: 0 | W15: 0 | X15: EMERGENCY MANAGER | AG15: 36418 | AH15: 1200 | AN15: The center of Hurricane Floyd passed about 115 statute miles off the coast of east central Florida on September 15th. The areas hardest hit were coastal sections of Brevard and Volusia counties. Both counties experienced widespread wind gusts to near 70 mph. Initial damage estimates in Volusia County were near $42 Million. About ten million of that was due to beach erosion. Three hundred thirty plus homes were damaged by wind or falling trees. Thousands of people were left without power. A large section of the Main Street Pier was destroyed by heavy surf in Daytona Beach. In Brevard County damage estimates were near $10 million. About $8 million of that was due to beach erosion. A few beach front homes received major damage from surf and wind. Many highrise hotels received water damage from wind driven rain. Thousands of trees and power lines were blown down across the county._x000D_ _x000D_ Beach erosion and downed trees and power lines and damage to some homes were also reported across coastal sections of St. Lucie and Indian River counties. Inland, downed trees and power lines and minor wind damage to structures was also reported in Orange and Seminole counties. | AO15: 98
A16: 5717615 | B16: SEMINOLE (ZONE) | C16: =_xlfn.XLOOKUP(B16,Match!$A$2:$A$111,Match!$B$2:$B$111) -> Seminole, FL | D16: =_xlfn.XLOOKUP(C16,Validation!$B$2:$B$68,Validation!$A$2:$A$68) -> 12117 | F16: 36417 | G16: 2200 | H16: Hurricane (Typhoon) | K16: 0 | L16: 0 | M16: 400000 | N16: 0 | O16: FL | P16: EST | R16: 2413683 | S16: Z | T16: 46 | U16: MLB | V16: 0 | W16: 0 | X16: EMERGENCY MANAGER | AG16: 36418 | AH16: 1600 | AN16: The center of Hurricane Floyd passed about 115 statute miles off the coast of east central Florida on September 15th. The areas hardest hit were coastal sections of Brevard and Volusia counties. Both counties experienced widespread wind gusts to near 70 mph. Initial damage estimates in Volusia County were near $42 Million. About ten million of that was due to beach erosion. Three hundred thirty plus homes were damaged by wind or falling trees. Thousands of people were left without power. A large section of the Main Street Pier was destroyed by heavy surf in Daytona Beach. In Brevard County damage estimates were near $10 million. About $8 million of that was due to beach erosion. A few beach front homes received major damage from surf and wind. Many highrise hotels received water damage from wind driven rain. Thousands of trees and power lines were blown down across the county._x000D_ _x000D_ Beach erosion and downed trees and power lines and damage to some homes were also reported across coastal sections of St. Lucie and Indian River counties. Inland, downed trees and power lines and minor wind damage to structures was also reported in Orange and Seminole counties. | AO16: 99
A17: 5723962 | B17: BREVARD (ZONE) | C17: =_xlfn.XLOOKUP(B17,Match!$A$2:$A$111,Match!$B$2:$B$111) -> Brevard, FL | D17: =_xlfn.XLOOKUP(C17,Validation!$B$2:$B$68,Validation!$A$2:$A$68) -> 12009 | F17: 36417 | G17: 2200 | H17: Hurricane (Typhoon) | K17: 0 | L17: 0 | M17: 5000000 | N17: 0 | O17: FL | P17: EST | R17: 2413683 | S17: Z | T17: 47 | U17: MLB | V17: 0 | W17: 0 | X17: EMERGENCY MANAGER | AG17: 36418 | AH17: 1600 | AN17: The center of Hurricane Floyd passed about 115 statute miles off the coast of east central Florida on September 15th. The areas hardest hit were coastal sections of Brevard and Volusia counties. Both counties experienced widespread wind gusts to near 70 mph. Initial damage estimates in Volusia County were near $42 Million. About ten million of that was due to beach erosion. Three hundred thirty plus homes were damaged by wind or falling trees. Thousands of people were left without power. A large section of the Main Street Pier was destroyed by heavy surf in Daytona Beach. In Brevard County damage estimates were near $10 million. About $8 million of that was due to beach erosion. A few beach front homes received major damage from surf and wind. Many highrise hotels received water damage from wind driven rain. Thousands of trees and power lines were blown down across the county._x000D_ _x000D_ Beach erosion and downed trees and power lines and damage to some homes were also reported across coastal sections of St. Lucie and Indian River counties. Inland, downed trees and power lines and minor wind damage to structures was also reported in Orange and Seminole counties. | AO17: 100
... A27: 5716958 | B27: COASTAL PALM BEACH (ZONE) | C27: =_xlfn.XLOOKUP(B27,Match!$A$2:$A$111,Match!$B$2:$B$111) -> Palm Beach, FL | D27: =_xlfn.XLOOKUP(C27,Validation!$B$2:$B$68,Validation!$A$2:$A$68) -> 12099 | F27: 36447 | G27: 900 | H27: Hurricane (Typhoon) | K27: 0 | L27: 0 | M27: 68000000 | N27: 75000000 | O27: FL | P27: EST | R27: 2411770 | S27: Z | T27: 68 | U27: MFL | V27: 0 | W27: 0 | X27: NEWSPAPER | AG27: 36448 | AH27: 2300 | AN27: After lingering as a broad area of low pressure in the western Caribbean Sea for four days, a tropical depression formed just after midnight EDT on October 13 and became tropical storm Irene in the northwest Caribbean Sea later that morning. Irene moved north across western Cuba on October 14 and strengthened to hurricane intensity early on October 15 in the Straits of Florida. It then made its first landfall in south Florida in the lower Florida Keys around 9 AM EDT, October 15. After crossing Florida Bay the center of Irene made landfall on the peninsula near Cape Sable around 4 PM EDT, October 15 as a Category One intensity hurricane. It moved northeast across central Miami-Dade and Broward counties before exiting into the Atlantic just after midnight EDT on October 16 near Jupiter in northeast Palm Beach County._x000D_ _x000D_ Heavy rains and sustained winds of tropical storm force caused widespread flooding and power outages in the metropolitan areas of Miami-Dade, Broward and Palm Beach counties. The effects were similar, although somewhat more widespread, than those experienced in tropical storm Gordon in November 1994 and were reminiscent of the wet hurricanes in the 1930s and 1940s._x000D_ _x000D_ Rainfall totals in southeast Florida ranged from 6 to 17 inches with many areas getting 10 to 15 inches. The greatest reliable amount reported was 17.45 inches at Boynton Beach. The highest sustained wind over land was 60 mph at Miami Beach with many readings from 40 to 55 mph. Fowey Rocks Light reported sustained winds of 66 mph while the Miami NWS doppler radar estimated areas of sustained hurricane force winds in the Atlantic Ocean just off the southeast Florida coast. Among the highest recorded gusts were readings of 93 mph near Belle Glade, 85 mph at Homestead Air Reserve Base, 84 mph at Fowey Rocks Light, 74 mph at Turkey Point nuclear power plant and 70 mph at Miami International Airport. The lowest barometric pressure on the south Florida peninsula was 989.9 mb at Opa Locka Airport. Storm surge and beach erosion were minimal._x000D_ _x000D_ Four tornadoes touched down in Broward and Palm Beach counties, injuring 3 persons. Several other areas of localized wind damage were reported, especially near the southeast shore of Lake Okeechobee, and were likely attributable to convective downbursts._x000D_ _x000D_ There were no direct deaths from Irene, but eight persons died in the aftermath. Five persons were electrocuted by downed power lines, including three persons from one family. Three other persons drowned in vehicle-related accidents. Damage in southeast Florida, mainly from flooding is estimated near $600 million which includes $335 million in agricultural losses. An estimated 700,000 customers lost electricity. Flooding in a few residential areas lasted for a week displacing several hundred persons and isolating thousands more._x000D_ _x000D_ Other long-term ecological repercussions may be experienced from the flooding rains such as the effects of high water on Everglade's hammocks, and the effects of excessive fresh-water runoff on estuaries. | AO27: 110
A28: 5716844 | B28: MONROE/LOWER KEYS (ZONE) | C28: =_xlfn.XLOOKUP(B28,Match!$A$2:$A$111,Match!$B$2:$B$111) -> Monroe, FL | D28: =_xlfn.XLOOKUP(C28,Validation!$B$2:$B$68,Validation!$A$2:$A$68) -> 12087 | F28: 36447 | G28: 2100 | H28: Hurricane (Typhoon) | K28: 0 | L28: 0 | M28: 9300000 | N28: 0 | O28: FL | P28: EST | R28: 2413547 | S28: Z | T28: 78 | U28: EYW | V28: 0 | W28: 0 | X28: NWS STORM SURVEY | AG28: 36448 | AH28: 1800 | AO28: 111
A29: 5716845 | B29: MONROE/MIDDLE KEYS (ZONE) | C29: =_xlfn.XLOOKUP(B29,Match!$A$2:$A$111,Match!$B$2:$B$111) -> Monroe, FL | D29: =_xlfn.XLOOKUP(C29,Validation!$B$2:$B$68,Validation!$A$2:$A$68) -> 12087 | F29: 36447 | G29: 2200 | H29: Hurricane (Typhoon) | K29: 0 | L29: 0 | M29: 1500000 | N29: 0 | O29: FL | P29: EST | R29: 2413547 | S29: Z | T29: 77 | U29: EYW | V29: 0 | W29: 0 | X29: NWS STORM SURVEY | AG29: 36448 | AH29: 2000 | AO29: 112
A30: 5716846 | B30: MONROE/UPPER KEYS (ZONE) | C30: =_xlfn.XLOOKUP(B30,Match!$A$2:$A$111,Match!$B$2:$B$111) -> Monroe, FL | D30: =_xlfn.XLOOKUP(C30,Validation!$B$2:$B$68,Validation!$A$2:$A$68) -> 12087 | F30: 36447 | G30: 2300 | H30: Hurricane (Typhoon) | K30: 0 | L30: 0 | M30: 2670000 | N30: 0 | O30: FL | P30: EST | R30: 2413547 | S30: Z | T30: 76 | U30: EYW | V30: 0 | W30: 0 | X30: NWS STORM SURVEY | AG30: 36448 | AH30: 2100 | AO30: 113
A31: 5723286 | B31: DE SOTO (ZONE) | C31: =_xlfn.XLOOKUP(B31,Match!$A$2:$A$111,Match!$B$2:$B$111) -> DeSoto, FL | D31: =_xlfn.XLOOKUP(C31,Validation!$B$2:$B$68,Validation!$A$2:$A$68) -> 12027 | F31: 36448 | G31: 1200 | H31: Hurricane (Typhoon) | K31: 0 | L31: 0 | M31: 0 | N31: 0 | O31: FL | P31: EST | R31: 2413725 | S31: Z | T31: 61 | U31: TBW | V31: 0 | W31: 0 | X31: OFFICIAL NWS OBS. | AG31: 36449 | AH31: 1500 | AN31: The westernmost bands of Hurricane Irene produced occasional tropical storm force wind gusts across the interior counties of central Florida during the evening of October 15th and early morning of the 16th with no reported fatalities, injuries or damage._x000D_ _x000D_ Maximum wind gust observed was 42 mph from the northeast recorded at the automated surface observing site (ASOS) in Winter Haven of Polk County, Florida at 1533 EST on the 15th. Maximum 24 hour rainfall was .31 inches recorded at Page Field in Ft Myers of Lee County, Florida ending at 0800 EST on the 16th. Lowest sea-level pressure observed was 1000.0 mb at Regional Southwest Airport in Ft Myers of Lee County, Florida at 1917EST on the 15th. | AO31: 114
A32: 5723289 | B32: POLK (ZONE) | C32: =_xlfn.XLOOKUP(B32,Match!$A$2:$A$111,Match!$B$2:$B$111) -> Polk, FL | D32: =_xlfn.XLOOKUP(C32,Validation!$B$2:$B$68,Validation!$A$2:$A$68) -> 12105 | F32: 36448 | G32: 1200 | H32: Hurricane (Typhoon) | K32: 0 | L32: 0 | M32: 0 | N32: 0 | O32: FL | P32: EST | R32: 2413725 | S32: Z | T32: 52 | U32: TBW | V32: 0 | W32: 0 | X32: OFFICIAL NWS OBS. | AG32: 36449 | AH32: 1500 | AN32: The westernmost bands of Hurricane Irene produced occasional tropical storm force wind gusts across the interior counties of central Florida during the evening of October 15th and early morning of the 16th with no reported fatalities, injuries or damage._x000D_ _x000D_ Maximum wind gust observed was 42 mph from the northeast recorded at the automated surface observing site (ASOS) in Winter Haven of Polk County, Florida at 1533 EST on the 15th. Maximum 24 hour rainfall was .31 inches recorded at Page Field in Ft Myers of Lee County, Florida ending at 0800 EST on the 16th. Lowest sea-level pressure observed was 1000.0 mb at Regional Southwest Airport in Ft Myers of Lee County, Florida at 1917EST on the 15th. | AO32: 115
A33: 5723284 | B33: LEE (ZONE) | C33: =_xlfn.XLOOKUP(B33,Match!$A$2:$A$111,Match!$B$2:$B$111) -> Lee, FL | D33: =_xlfn.XLOOKUP(C33,Validation!$B$2:$B$68,Validation!$A$2:$A$68) -> 12071 | F33: 36448 | G33: 1200 | H33: Hurricane (Typhoon) | K33: 0 | L33: 0 | M33: 0 | N33: 0 | O33: FL | P33: EST | R33: 2413725 | S33: Z | T33: 65 | U33: TBW | V33: 0 | W33: 0 | X33: OFFICIAL NWS OBS. | AG33: 36449 | AH33: 1500 | AN33: The westernmost bands of Hurricane Irene produced occasional tropical storm force wind gusts across the interior counties of central Florida during the evening of October 15th and early morning of the 16th with no reported fatalities, injuries or damage._x000D_ _x000D_ Maximum wind gust observed was 42 mph from the northeast recorded at the automated surface observing site (ASOS) in Winter Haven of Polk County, Florida at 1533 EST on the 15th. Maximum 24 hour rainfall was .31 inches recorded at Page Field in Ft Myers of Lee County, Florida ending at 0800 EST on the 16th. Lowest sea-level pressure observed was 1000.0 mb at Regional Southwest Airport in Ft Myers of Lee County, Florida at 1917EST on the 15th. | AO33: 116
A34: 5723287 | B34: HARDEE (ZONE) | C34: =_xlfn.XLOOKUP(B34,Match!$A$2:$A$111,Match!$B$2:$B$111) -> Hardee, FL | D34: =_xlfn.XLOOKUP(C34,Validation!$B$2:$B$68,Validation!$A$2:$A$68) -> 12049 | F34: 36448 | G34: 1200 | H34: Hurricane (Typhoon) | K34: 0 | L34: 0 | M34: 0 | N34: 0 | O34: FL | P34: EST | R34: 2413725 | S34: Z | T34: 56 | U34: TBW | V34: 0 | W34: 0 | X34: OFFICIAL NWS OBS. | AG34: 36449 | AH34: 1500 | AN34: The westernmost bands of Hurricane Irene produced occasional tropical storm force wind gusts across the interior counties of central Florida during the evening of October 15th and early morning of the 16th with no reported fatalities, injuries or damage._x000D_ _x000D_ Maximum wind gust observed was 42 mph from the northeast recorded at the automated surface observing site (ASOS) in Winter Haven of Polk County, Florida at 1533 EST on the 15th. Maximum 24 hour rainfall was .31 inches recorded at Page Field in Ft Myers of Lee County, Florida ending at 0800 EST on the 16th. Lowest sea-level pressure observed was 1000.0 mb at Regional Southwest Airport in Ft Myers of Lee County, Florida at 1917EST on the 15th. | AO34: 117
A35: 5723285 | B35: CHARLOTTE (ZONE) | C35: =_xlfn.XLOOKUP(B35,Match!$A$2:$A$111,Match!$B$2:$B$111) -> Charlotte, FL | D35: =_xlfn.XLOOKUP(C35,Validation!$B$2:$B$68,Validation!$A$2:$A$68) -> 12015 | F35: 36448 | G35: 1200 | H35: Hurricane (Typhoon) | K35: 0 | L35: 0 | M35: 0 | N35: 0 | O35: FL | P35: EST | R35: 2413725 | S35: Z | T35: 62 | U35: TBW | V35: 0 | W35: 0 | X35: OFFICIAL NWS OBS. | AG35: 36449 | AH35: 1500 | AN35: The westernmost bands of Hurricane Irene produced occasional tropical storm force wind gusts across the interior counties of central Florida during the evening of October 15th and early morning of the 16th with no reported fatalities, injuries or damage._x000D_ _x000D_ Maximum wind gust observed was 42 mph from the northeast recorded at the automated surface observing site (ASOS) in Winter Haven of Polk County, Florida at 1533 EST on the 15th. Maximum 24 hour rainfall was .31 inches recorded at Page Field in Ft Myers of Lee County, Florida ending at 0800 EST on the 16th. Lowest sea-level pressure observed was 1000.0 mb at Regional Southwest Airport in Ft Myers of Lee County, Florida at 1917EST on the 15th. | AO35: 118
A36: 5723288 | B36: HIGHLANDS (ZONE) | C36: =_xlfn.XLOOKUP(B36,Match!$A$2:$A$111,Match!$B$2:$B$111) -> Highlands, FL | D36: =_xlfn.XLOOKUP(C36,Validation!$B$2:$B$68,Validation!$A$2:$A$68) -> 12055 | F36: 36448 | G36: 1200 | H36: Hurricane (Typhoon) | K36: 0 | L36: 0 | M36: 0 | N36: 0 | O36: FL | P36: EST | R36: 2413725 | S36: Z | T36: 57 | U36: TBW | V36: 0 | W36: 0 | X36: OFFICIAL NWS OBS. | AG36: 36449 | AH36: 1500 | AN36: The westernmost bands of Hurricane Irene produced occasional tropical storm force wind gusts across the interior counties of central Florida during the evening of October 15th and early morning of the 16th with no reported fatalities, injuries or damage._x000D_ _x000D_ Maximum wind gust observed was 42 mph from the northeast recorded at the automated surface observing site (ASOS) in Winter Haven of Polk County, Florida at 1533 EST on the 15th. Maximum 24 hour rainfall was .31 inches recorded at Page Field in Ft Myers of Lee County, Florida ending at 0800 EST on the 16th. Lowest sea-level pressure observed was 1000.0 mb at Regional Southwest Airport in Ft Myers of Lee County, Florida at 1917EST on the 15th. | AO36: 119
A37: 5717621 | B37: INDIAN RIVER (ZONE) | C37: =_xlfn.XLOOKUP(B37,Match!$A$2:$A$111,Match!$B$2:$B$111) -> Indian River, FL | D37: =_xlfn.XLOOKUP(C37,Validation!$B$2:$B$68,Validation!$A$2:$A$68) -> 12061 | F37: 36448 | G37: 2000 | H37: Hurricane (Typhoon) | K37: 0 | L37: 0 | M37: 10000000 | N37: 0 | O37: FL | P37: EST | R37: 2413684 | S37: Z | T37: 54 | U37: MLB | V37: 0 | W37: 0 | X37: EMERGENCY MANAGER | AG37: 36449 | AH37: 1200 | AN37: Minimal Hurricane Irene moved northeast from the Florida Keys across south Florida and emerged over the Atlantic near Ft. Pierce. Even though the storm was classified a category one hurricane, no sustained hurricane force winds were observed in east central Florida. Winds gusted from 60 to 70 mph over coastal locations from Ft. Pierce to Daytona Beach. _x000D_ _x000D_ In Martin and St. Lucie counties the greatest impact from the storm was flooding. From 5 to 9 inches of rain fell over the area flooding 300 homes. About 50 homes had major wind damage and thousands of trees were blown down. _x000D_ _x000D_ In Volusia, Brevard and Indian River counties hundreds of homes received minor wind damage and about 50 residences were seriously damaged. The hardest hit areas were beach front communities. Many houses and high rise hotels suffered roof damage and damage from wind driven rain. A barge broke free during high winds and damaged the causeway bridge on US Highway 528 near Cape Canaveral. Substantial beach erosion was reported along the entire coast. From 4 to 10 feet of beach front was lost in most areas with damage estimated in the millions of dollars in each county. | AO37: 120
A38: 5717622 | B38: BREVARD (ZONE) | C38: =_xlfn.XLOOKUP(B38,Match!$A$2:$A$111,Match!$B$2:$B$111) -> Brevard, FL | D38: =_xlfn.XLOOKUP(C38,Validation!$B$2:$B$68,Validation!$A$2:$A$68) -> 12009 | F38: 36448 | G38: 2000 | H38: Hurricane (Typhoon) | K38: 0 | L38: 0 | M38: 12000000 | N38: 0 | O38: FL | P38: EST | R38: 2413684 | S38: Z | T38: 47 | U38: MLB | V38: 0 | W38: 0 | X38: EMERGENCY MANAGER | AG38: 36449 | AH38: 1200 | AN38: Minimal Hurricane Irene moved northeast from the Florida Keys across south Florida and emerged over the Atlantic near Ft. Pierce. Even though the storm was classified a category one hurricane, no sustained hurricane force winds were observed in east central Florida. Winds gusted from 60 to 70 mph over coastal locations from Ft. Pierce to Daytona Beach. _x000D_ _x000D_ In Martin and St. Lucie counties the greatest impact from the storm was flooding. From 5 to 9 inches of rain fell over the area flooding 300 homes. About 50 homes had major wind damage and thousands of trees were blown down. _x000D_ _x000D_ In Volusia, Brevard and Indian River counties hundreds of homes received minor wind damage and about 50 residences were seriously damaged. The hardest hit areas were beach front communities. Many houses and high rise hotels suffered roof damage and damage from wind driven rain. A barge broke free during high winds and damaged the causeway bridge on US Highway 528 near Cape Canaveral. Substantial beach erosion was reported along the entire coast. From 4 to 10 feet of beach front was lost in most areas with damage estimated in the millions of dollars in each county. | AO38: 121
A39: 5717620 | B39: ST. LUCIE (ZONE) | C39: =_xlfn.XLOOKUP(B39,Match!$A$2:$A$111,Match!$B$2:$B$111) -> St. Lucie, FL | D39: =_xlfn.XLOOKUP(C39,Validation!$B$2:$B$68,Validation!$A$2:$A$68) -> 12111 | F39: 36448 | G39: 2000 | H39: Hurricane (Typhoon) | K39: 0 | L39: 0 | M39: 6000000 | N39: 0 | O39: FL | P39: EST | R39: 2413684 | S39: Z | T39: 59 | U39: MLB | V39: 0 | W39: 0 | X39: EMERGENCY MANAGER | AG39: 36449 | AH39: 1200 | AN39: Minimal Hurricane Irene moved northeast from the Florida Keys across south Florida and emerged over the Atlantic near Ft. Pierce. Even though the storm was classified a category one hurricane, no sustained hurricane force winds were observed in east central Florida. Winds gusted from 60 to 70 mph over coastal locations from Ft. Pierce to Daytona Beach. _x000D_ _x000D_ In Martin and St. Lucie counties the greatest impact from the storm was flooding. From 5 to 9 inches of rain fell over the area flooding 300 homes. About 50 homes had major wind damage and thousands of trees were blown down. _x000D_ _x000D_ In Volusia, Brevard and Indian River counties hundreds of homes received minor wind damage and about 50 residences were seriously damaged. The hardest hit areas were beach front communities. Many houses and high rise hotels suffered roof damage and damage from wind driven rain. A barge broke free during high winds and damaged the causeway bridge on US Highway 528 near Cape Canaveral. Substantial beach erosion was reported along the entire coast. From 4 to 10 feet of beach front was lost in most areas with damage estimated in the millions of dollars in each county. | AO39: 122
A40: 5717619 | B40: MARTIN (ZONE) | C40: =_xlfn.XLOOKUP(B40,Match!$A$2:$A$111,Match!$B$2:$B$111) -> Martin, FL | D40: =_xlfn.XLOOKUP(C40,Validation!$B$2:$B$68,Validation!$A$2:$A$68) -> 12085 | F40: 36448 | G40: 2000 | H40: Hurricane (Typhoon) | K40: 0 | L40: 0 | M40: 8000000 | N40: 0 | O40: FL | P40: EST | R40: 2413684 | S40: Z | T40: 64 | U40: MLB | V40: 0 | W40: 0 | X40: EMERGENCY MANAGER | AG40: 36449 | AH40: 1200 | AN40: Minimal Hurricane Irene moved northeast from the Florida Keys across south Florida and emerged over the Atlantic near Ft. Pierce. Even though the storm was classified a category one hurricane, no sustained hurricane force winds were observed in east central Florida. Winds gusted from 60 to 70 mph over coastal locations from Ft. Pierce to Daytona Beach. _x000D_ _x000D_ In Martin and St. Lucie counties the greatest impact from the storm was flooding. From 5 to 9 inches of rain fell over the area flooding 300 homes. About 50 homes had major wind damage and thousands of trees were blown down. _x000D_ _x000D_ In Volusia, Brevard and Indian River counties hundreds of homes received minor wind damage and about 50 residences were seriously damaged. The hardest hit areas were beach front communities. Many houses and high rise hotels suffered roof damage and damage from wind driven rain. A barge broke free during high winds and damaged the causeway bridge on US Highway 528 near Cape Canaveral. Substantial beach erosion was reported along the entire coast. From 4 to 10 feet of beach front was lost in most areas with damage estimated in the millions of dollars in each county. | AO40: 123
A41: 5717623 | B41: VOLUSIA (ZONE) | C41: =_xlfn.XLOOKUP(B41,Match!$A$2:$A$111,Match!$B$2:$B$111) -> Volusia, FL | D41: =_xlfn.XLOOKUP(C41,Validation!$B$2:$B$68,Validation!$A$2:$A$68) -> 12127 | F41: 36448 | G41: 2000 | H41: Hurricane (Typhoon) | K41: 0 | L41: 0 | M41: 15000000 | N41: 0 | O41: FL | P41: EST | R41: 2413684 | S41: Z | T41: 41 | U41: MLB | V41: 0 | W41: 0 | X41: EMERGENCY MANAGER | AG41: 36449 | AH41: 1700 | AN41: Minimal Hurricane Irene moved northeast from the Florida Keys across south Florida and emerged over the Atlantic near Ft. Pierce. Even though the storm was classified a category one hurricane, no sustained hurricane force winds were observed in east central Florida. Winds gusted from 60 to 70 mph over coastal locations from Ft. Pierce to Daytona Beach. _x000D_ _x000D_ In Martin and St. Lucie counties the greatest impact from the storm was flooding. From 5 to 9 inches of rain fell over the area flooding 300 homes. About 50 homes had major wind damage and thousands of trees were blown down. _x000D_ _x000D_ In Volusia, Brevard and Indian River counties hundreds of homes received minor wind damage and about 50 residences were seriously damaged. The hardest hit areas were beach front communities. Many houses and high rise hotels suffered roof damage and damage from wind driven rain. A barge broke free during high winds and damaged the causeway bridge on US Highway 528 near Cape Canaveral. Substantial beach erosion was reported along the entire coast. From 4 to 10 feet of beach front was lost in most areas with damage estimated in the millions of dollars in each county. | AO41: 124
A42: 5722400 | B42: FLAGLER (ZONE) | C42: =_xlfn.XLOOKUP(B42,Match!$A$2:$A$111,Match!$B$2:$B$111) -> Flagler, FL | D42: =_xlfn.XLOOKUP(C42,Validation!$B$2:$B$68,Validation!$A$2:$A$68) -> 12035 | F42: 36449 | G42: 1500 | H42: Hurricane (Typhoon) | K42: 0 | L42: 0 | M42: 600000 | N42: 0 | O42: FL | P42: EST | R42: 2414411 | S42: Z | T42: 38 | U42: JAX | V42: 0 | W42: 0 | X42: EMERGENCY MANAGER | AG42: 36450 | AH42: 400 | AN42: Hurricane Irene - Three single family homes and one multi-family structure received major damage. 167 single family homes, 6 multi-family and 18 mobile and 18 businesses with minor damage. Numerous reports of trees and power lines blown down. Minor flooding occurred in the northern portion of the county near Marineland. Minor beach erosion. A 74 mph wind gust was reported between 16/2000 and 16/2030 UTC by the Flagler Vol. Fire Department. | AO42: 125
A43: 5722401 | B43: ST. JOHNS (ZONE) | C43: =_xlfn.XLOOKUP(B43,Match!$A$2:$A$111,Match!$B$2:$B$111) -> St. Johns, FL | D43: =_xlfn.XLOOKUP(C43,Validation!$B$2:$B$68,Validation!$A$2:$A$68) -> 12109 | F43: 36449 | G43: 1700 | H43: Hurricane (Typhoon) | K43: 0 | L43: 0 | M43: 300000 | N43: 0 | O43: FL | P43: EST | R43: 2413088 | S43: Z | T43: 33 | U43: JAX | V43: 0 | W43: 0 | X43: EMERGENCY MANAGER | AG43: 36450 | AH43: 1800 | AM43: Hurricane Irene - Minor beach erosion and flooding. Numerous reports of tree and power lines blown down. Max wind gust - 77 mph, St. Augustine (SAUF1) at 170200 UTC. | AO43: 126
A44: 5722402 | B44: DUVAL (ZONE) | C44: =_xlfn.XLOOKUP(B44,Match!$A$2:$A$111,Match!$B$2:$B$111) -> Duval, FL | D44: =_xlfn.XLOOKUP(C44,Validation!$B$2:$B$68,Validation!$A$2:$A$68) -> 12031 | F44: 36449 | G44: 1800 | H44: Hurricane (Typhoon) | K44: 0 | L44: 0 | M44: 300000 | N44: 0 | O44: FL | P44: EST | R44: 2414412 | S44: Z | T44: 25 | U44: JAX | V44: 0 | W44: 0 | X44: EMERGENCY MANAGER | AG44: 36450 | AH44: 600 | AM44: Hurricane Irene - Numerous reports of trees and power lines blown down. Max wind gust - 55 mph, Mayport Navy Base at 170200 UTC. Minor beach erosion. | AO44: 127
A45: 5157574 | B45: LEE (ZONE) | C45: =_xlfn.XLOOKUP(B45,Match!$A$2:$A$111,Match!$B$2:$B$111) -> Lee, FL | D45: =_xlfn.XLOOKUP(C45,Validation!$B$2:$B$68,Validation!$A$2:$A$68) -> 12071 | F45: 36786 | G45: 330 | H45: Hurricane (Typhoon) | K45: 0 | L45: 0 | M45: 500000 | N45: 0 | O45: FL | P45: EST | R45: 1104015 | S45: Z | T45: 65 | U45: TBW | V45: 0 | W45: 0 | X45: AWOS | Y45: ASOS | Z45: MESONET | AA45: ETC | AJ45: 36786 | AK45: 1600 | AQ45: Hurricane Gordon moved northeast across the eastern Gulf of Mexico and brought mainly 30 to 40 mph sustained winds and 50 to nearly 70 mph tropical storm force wind gusts to mainly coastal areas of Southwest and West Central Florida throughout the daylight hours of the 17th. Gordon's ill-defined center made landfall near the Suwannee River around midnight of the 18th. Official, maximum sustained winds of 53 mph, with gusts as high as 68 mph, were observed at the C-MAN automated weather sensor at Cedar Key in Levy county prior to landfall near the mouth of the Suwannee River during the late evening of the 17th._x000D_ _x000D_ Hurricane Gordon produced maximum storm tides above mean sea level of 2 to 4 feet from Lee north to Manatee county, 4 to 5.5 feet along the Pinellas and Hillsborough county coastlines, and 2 to 4 feet from Pasco north to Levy county on the 17th._x000D_ _x000D_ Coastal flooding from storm surge was minimal from Lee county north to the Tampa metropolitan area. Near downtown Tampa, a foot of water covered the south and northern lanes of Bayshore Boulevard during midday on the 17th. Coastal flood waters between one and two feet covered coastal roads along Longboat Key in Manatee county and Siesta and Casey Keys in Sarasota county. In Pinellas county, nearly a foot of water covered coastal roads from St. Pete Beach to Clearwater. The Courtney Campbell Parkway, seperating Pinellas and Hillsborough counties, was closed, due to storm surge flooding, from nearly 5 to 9 pm on the 17th._x000D_ _x000D_ Beach erosion was minor from Lee north to Charlotte, moderate to severe along Sarasota and Manatee counties, minor to moderate over Manatee, Pinellas, Pasco and Hernando counties. At Bradenton Beach in Manatee county, nearly 100 feet of pristine beach, five to six feet in depth, was stripped away by wave action from Hurricane Gordon. In Sarasota county, storm surge and wave action from Gordon caused nearly 1.1 million dollars in beach erosion while in Manatee county, beach erosion was estimated at 500 thousand dollars._x000D_ _x000D_ Inland flooding from rainfall occurred over low-lying and urban areas in mainly Lee, Charlotte, Sarasota, Manatee, Hardee, DeSoto, Highlands and southern Polk counties (see flood entries)._x000D_ _x000D_ Eastern rain bands of Hurricane Gordon spawned at least five known tornadoes, two F1's and three F0's over Central and Southwest Florida (see tornado entries)._x000D_ _x000D_ Damage in Levy county was confined to roofs and toppled trees, mainly in the Cedar Key area, where a total of $100,000 dollars was estimated._x000D_ _x000D_ Damage in Citrus county was confined to a few downed trees, power lines and snapped branches from Sulphur Springs south to Ozello mounting to less than $25,000 dollars._x000D_ _x000D_ Damage in Hernando county was confined to ten homes that suffered floodwater damage along the coast along with a few toppled trees and downed power lines. Damage in Hernando county was estimated at $100,000 dollars._x000D_ _x000D_ Damage in Pasco county was confined to 15 roof damaged villas, downed trees and damaged vehicles in the New Port Colony Villas subdivsion in New Port Richey estimated at $250,000 dollars._x000D_ _x000D_ In Pinellas county, 51 single-family homes, 32 mobile homes, 27 multi-family homes and 24 businesses sustained minor wind or water damage. Estimated cost of the damage in Pinellas county was nearly $500,000 dollars._x000D_ _x000D_ In Hillsborough county, 40 homes in low lying coastal areas from Ruskin to Gibsonton to Riverview, incurred flooding from storm surge. Also, several homes were damaged from wind toppled trees and large branches throughout Hillsborough county. Estimated cost of the damage in Hillsborough county was near $500,000 dollars._x000D_ _x000D_ In Manatee county, 25 homes and businesses were flooded in Bradenton Beach and several homes incurred minor to moderate roof damage in Anna Maria. At Coquina Beach in Manatee county, 60 mph wind gusts, associated with an outer feeder band of Gordon, toppled life guard towers and destroyed an anemometer. Property damage from Hurricane Gordon was estimated at nearly $500,000 dollars in Manatee county._x000D_ _x000D_ In Sarasota county, eight foot high waves, caused nearly $600,000 in property damage to the Venice Municipal Fishing Pier. The hurricane induced waves ripped a 20 foot section and three 50 foot concrete pilings from the northern section of the pier._x000D_ _x000D_ In Lee county, tropical storm force winds caused roof, awning and lanai damage to nine homes, toppled several large trees and branches, and downed power lines across Cape Coral and Ft. Myers. Also, tornadoes, associated with outer feeder bands of Hurricane Gordon, caused significant damage on Sanibel Island of extreme western Lee county (see Lee county tornado entries)._x000D_ _x000D_ Max Wind Gust: 68 mph - Cedar Key, Levy Co. 2153 EST 09/17_x000D_ Lowest Pressure: 994.2 mb - Cedar Key, Levy Co. 2200 EST 09/17_x000D_ Max Rainfall: 6.39 in - Page Field, Ft. Myers, Lee Co. 0000-2400 EST 09/17 | AR45: 128
A46: 5157575 | B46: CHARLOTTE (ZONE) | C46: =_xlfn.XLOOKUP(B46,Match!$A$2:$A$111,Match!$B$2:$B$111) -> Charlotte, FL | D46: =_xlfn.XLOOKUP(C46,Validation!$B$2:$B$68,Validation!$A$2:$A$68) -> 12015 | F46: 36786 | G46: 400 | H46: Hurricane (Typhoon) | K46: 0 | L46: 0 | M46: 150000 | N46: 0 | O46: FL | P46: EST | R46: 1104015 | S46: Z | T46: 62 | U46: TBW | V46: 0 | W46: 0 | X46: AWOS | Y46: ASOS | Z46: MESONET | AA46: ETC | AJ46: 36786 | AK46: 1600 | AQ46: Hurricane Gordon moved northeast across the eastern Gulf of Mexico and brought mainly 30 to 40 mph sustained winds and 50 to nearly 70 mph tropical storm force wind gusts to mainly coastal areas of Southwest and West Central Florida throughout the daylight hours of the 17th. Gordon's ill-defined center made landfall near the Suwannee River around midnight of the 18th. Official, maximum sustained winds of 53 mph, with gusts as high as 68 mph, were observed at the C-MAN automated weather sensor at Cedar Key in Levy county prior to landfall near the mouth of the Suwannee River during the late evening of the 17th._x000D_ _x000D_ Hurricane Gordon produced maximum storm tides above mean sea level of 2 to 4 feet from Lee north to Manatee county, 4 to 5.5 feet along the Pinellas and Hillsborough county coastlines, and 2 to 4 feet from Pasco north to Levy county on the 17th._x000D_ _x000D_ Coastal flooding from storm surge was minimal from Lee county north to the Tampa metropolitan area. Near downtown Tampa, a foot of water covered the south and northern lanes of Bayshore Boulevard during midday on the 17th. Coastal flood waters between one and two feet covered coastal roads along Longboat Key in Manatee county and Siesta and Casey Keys in Sarasota county. In Pinellas county, nearly a foot of water covered coastal roads from St. Pete Beach to Clearwater. The Courtney Campbell Parkway, seperating Pinellas and Hillsborough counties, was closed, due to storm surge flooding, from nearly 5 to 9 pm on the 17th._x000D_ _x000D_ Beach erosion was minor from Lee north to Charlotte, moderate to severe along Sarasota and Manatee counties, minor to moderate over Manatee, Pinellas, Pasco and Hernando counties. At Bradenton Beach in Manatee county, nearly 100 feet of pristine beach, five to six feet in depth, was stripped away by wave action from Hurricane Gordon. In Sarasota county, storm surge and wave action from Gordon caused nearly 1.1 million dollars in beach erosion while in Manatee county, beach erosion was estimated at 500 thousand dollars._x000D_ _x000D_ Inland flooding from rainfall occurred over low-lying and urban areas in mainly Lee, Charlotte, Sarasota, Manatee, Hardee, DeSoto, Highlands and southern Polk counties (see flood entries)._x000D_ _x000D_ Eastern rain bands of Hurricane Gordon spawned at least five known tornadoes, two F1's and three F0's over Central and Southwest Florida (see tornado entries)._x000D_ _x000D_ Damage in Levy county was confined to roofs and toppled trees, mainly in the Cedar Key area, where a total of $100,000 dollars was estimated._x000D_ _x000D_ Damage in Citrus county was confined to a few downed trees, power lines and snapped branches from Sulphur Springs south to Ozello mounting to less than $25,000 dollars._x000D_ _x000D_ Damage in Hernando county was confined to ten homes that suffered floodwater damage along the coast along with a few toppled trees and downed power lines. Damage in Hernando county was estimated at $100,000 dollars._x000D_ _x000D_ Damage in Pasco county was confined to 15 roof damaged villas, downed trees and damaged vehicles in the New Port Colony Villas subdivsion in New Port Richey estimated at $250,000 dollars._x000D_ _x000D_ In Pinellas county, 51 single-family homes, 32 mobile homes, 27 multi-family homes and 24 businesses sustained minor wind or water damage. Estimated cost of the damage in Pinellas county was nearly $500,000 dollars._x000D_ _x000D_ In Hillsborough county, 40 homes in low lying coastal areas from Ruskin to Gibsonton to Riverview, incurred flooding from storm surge. Also, several homes were damaged from wind toppled trees and large branches throughout Hillsborough county. Estimated cost of the damage in Hillsborough county was near $500,000 dollars._x000D_ _x000D_ In Manatee county, 25 homes and businesses were flooded in Bradenton Beach and several homes incurred minor to moderate roof damage in Anna Maria. At Coquina Beach in Manatee county, 60 mph wind gusts, associated with an outer feeder band of Gordon, toppled life guard towers and destroyed an anemometer. Property damage from Hurricane Gordon was estimated at nearly $500,000 dollars in Manatee county._x000D_ _x000D_ In Sarasota county, eight foot high waves, caused nearly $600,000 in property damage to the Venice Municipal Fishing Pier. The hurricane induced waves ripped a 20 foot section and three 50 foot concrete pilings from the northern section of the pier._x000D_ _x000D_ In Lee county, tropical storm force winds caused roof, awning and lanai damage to nine homes, toppled several large trees and branches, and downed power lines across Cape Coral and Ft. Myers. Also, tornadoes, associated with outer feeder bands of Hurricane Gordon, caused significant damage on Sanibel Island of extreme western Lee county (see Lee county tornado entries)._x000D_ _x000D_ Max Wind Gust: 68 mph - Cedar Key, Levy Co. 2153 EST 09/17_x000D_ Lowest Pressure: 994.2 mb - Cedar Key, Levy Co. 2200 EST 09/17_x000D_ Max Rainfall: 6.39 in - Page Field, Ft. Myers, Lee Co. 0000-2400 EST 09/17 | AR46: 129
A47: 5157588 | B47: PINELLAS (ZONE) | C47: =_xlfn.XLOOKUP(B47,Match!$A$2:$A$111,Match!$B$2:$B$111) -> Pinellas, FL | D47: =_xlfn.XLOOKUP(C47,Validation!$B$2:$B$68,Validation!$A$2:$A$68) -> 12103 | F47: 36786 | G47: 500 | H47: Hurricane (Typhoon) | K47: 0 | L47: 0 | M47: 10000 | N47: 0 | O47: FL | P47: EST | R47: 1104015 | S47: Z | T47: 50 | U47: TBW | V47: 0 | W47: 0 | X47: AWOS | Y47: ASOS | Z47: MESONET | AA47: ETC | AJ47: 36787 | AK47: 400 | AQ47: Hurricane Gordon moved northeast across the eastern Gulf of Mexico and brought mainly 30 to 40 mph sustained winds and 50 to nearly 70 mph tropical storm force wind gusts to mainly coastal areas of Southwest and West Central Florida throughout the daylight hours of the 17th. Gordon's ill-defined center made landfall near the Suwannee River around midnight of the 18th. Official, maximum sustained winds of 53 mph, with gusts as high as 68 mph, were observed at the C-MAN automated weather sensor at Cedar Key in Levy county prior to landfall near the mouth of the Suwannee River during the late evening of the 17th._x000D_ _x000D_ Hurricane Gordon produced maximum storm tides above mean sea level of 2 to 4 feet from Lee north to Manatee county, 4 to 5.5 feet along the Pinellas and Hillsborough county coastlines, and 2 to 4 feet from Pasco north to Levy county on the 17th._x000D_ _x000D_ Coastal flooding from storm surge was minimal from Lee county north to the Tampa metropolitan area. Near downtown Tampa, a foot of water covered the south and northern lanes of Bayshore Boulevard during midday on the 17th. Coastal flood waters between one and two feet covered coastal roads along Longboat Key in Manatee county and Siesta and Casey Keys in Sarasota county. In Pinellas county, nearly a foot of water covered coastal roads from St. Pete Beach to Clearwater. The Courtney Campbell Parkway, seperating Pinellas and Hillsborough counties, was closed, due to storm surge flooding, from nearly 5 to 9 pm on the 17th._x000D_ _x000D_ Beach erosion was minor from Lee north to Charlotte, moderate to severe along Sarasota and Manatee counties, minor to moderate over Manatee, Pinellas, Pasco and Hernando counties. At Bradenton Beach in Manatee county, nearly 100 feet of pristine beach, five to six feet in depth, was stripped away by wave action from Hurricane Gordon. In Sarasota county, storm surge and wave action from Gordon caused nearly 1.1 million dollars in beach erosion while in Manatee county, beach erosion was estimated at 500 thousand dollars._x000D_ _x000D_ Inland flooding from rainfall occurred over low-lying and urban areas in mainly Lee, Charlotte, Sarasota, Manatee, Hardee, DeSoto, Highlands and southern Polk counties (see flood entries)._x000D_ _x000D_ Eastern rain bands of Hurricane Gordon spawned at least five known tornadoes, two F1's and three F0's over Central and Southwest Florida (see tornado entries)._x000D_ _x000D_ Damage in Levy county was confined to roofs and toppled trees, mainly in the Cedar Key area, where a total of $100,000 dollars was estimated._x000D_ _x000D_ Damage in Citrus county was confined to a few downed trees, power lines and snapped branches from Sulphur Springs south to Ozello mounting to less than $25,000 dollars._x000D_ _x000D_ Damage in Hernando county was confined to ten homes that suffered floodwater damage along the coast along with a few toppled trees and downed power lines. Damage in Hernando county was estimated at $100,000 dollars._x000D_ _x000D_ Damage in Pasco county was confined to 15 roof damaged villas, downed trees and damaged vehicles in the New Port Colony Villas subdivsion in New Port Richey estimated at $250,000 dollars._x000D_ _x000D_ In Pinellas county, 51 single-family homes, 32 mobile homes, 27 multi-family homes and 24 businesses sustained minor wind or water damage. Estimated cost of the damage in Pinellas county was nearly $500,000 dollars._x000D_ _x000D_ In Hillsborough county, 40 homes in low lying coastal areas from Ruskin to Gibsonton to Riverview, incurred flooding from storm surge. Also, several homes were damaged from wind toppled trees and large branches throughout Hillsborough county. Estimated cost of the damage in Hillsborough county was near $500,000 dollars._x000D_ _x000D_ In Manatee county, 25 homes and businesses were flooded in Bradenton Beach and several homes incurred minor to moderate roof damage in Anna Maria. At Coquina Beach in Manatee county, 60 mph wind gusts, associated with an outer feeder band of Gordon, toppled life guard towers and destroyed an anemometer. Property damage from Hurricane Gordon was estimated at nearly $500,000 dollars in Manatee county._x000D_ _x000D_ In Sarasota county, eight foot high waves, caused nearly $600,000 in property damage to the Venice Municipal Fishing Pier. The hurricane induced waves ripped a 20 foot section and three 50 foot concrete pilings from the northern section of the pier._x000D_ _x000D_ In Lee county, tropical storm force winds caused roof, awning and lanai damage to nine homes, toppled several large trees and branches, and downed power lines across Cape Coral and Ft. Myers. Also, tornadoes, associated with outer feeder bands of Hurricane Gordon, caused significant damage on Sanibel Island of extreme western Lee county (see Lee county tornado entries)._x000D_ _x000D_ Max Wind Gust: 68 mph - Cedar Key, Levy Co. 2153 EST 09/17_x000D_ Lowest Pressure: 994.2 mb - Cedar Key, Levy Co. 2200 EST 09/17_x000D_ Max Rainfall: 6.39 in - Page Field, Ft. Myers, Lee Co. 0000-2400 EST 09/17 | AR47: 130
A48: 5157580 | B48: HIGHLANDS (ZONE) | C48: =_xlfn.XLOOKUP(B48,Match!$A$2:$A$111,Match!$B$2:$B$111) -> Highlands, FL | D48: =_xlfn.XLOOKUP(C48,Validation!$B$2:$B$68,Validation!$A$2:$A$68) -> 12055 | F48: 36786 | G48: 500 | H48: Hurricane (Typhoon) | K48: 0 | L48: 0 | M48: 50000 | N48: 0 | O48: FL | P48: EST | R48: 1104015 | S48: Z | T48: 57 | U48: TBW | V48: 0 | W48: 0 | X48: AWOS | Y48: ASOS | Z48: MESONET | AA48: ETC | AJ48: 36786 | AK48: 1600 | AQ48: Hurricane Gordon moved northeast across the eastern Gulf of Mexico and brought mainly 30 to 40 mph sustained winds and 50 to nearly 70 mph tropical storm force wind gusts to mainly coastal areas of Southwest and West Central Florida throughout the daylight hours of the 17th. Gordon's ill-defined center made landfall near the Suwannee River around midnight of the 18th. Official, maximum sustained winds of 53 mph, with gusts as high as 68 mph, were observed at the C-MAN automated weather sensor at Cedar Key in Levy county prior to landfall near the mouth of the Suwannee River during the late evening of the 17th._x000D_ _x000D_ Hurricane Gordon produced maximum storm tides above mean sea level of 2 to 4 feet from Lee north to Manatee county, 4 to 5.5 feet along the Pinellas and Hillsborough county coastlines, and 2 to 4 feet from Pasco north to Levy county on the 17th._x000D_ _x000D_ Coastal flooding from storm surge was minimal from Lee county north to the Tampa metropolitan area. Near downtown Tampa, a foot of water covered the south and northern lanes of Bayshore Boulevard during midday on the 17th. Coastal flood waters between one and two feet covered coastal roads along Longboat Key in Manatee county and Siesta and Casey Keys in Sarasota county. In Pinellas county, nearly a foot of water covered coastal roads from St. Pete Beach to Clearwater. The Courtney Campbell Parkway, seperating Pinellas and Hillsborough counties, was closed, due to storm surge flooding, from nearly 5 to 9 pm on the 17th._x000D_ _x000D_ Beach erosion was minor from Lee north to Charlotte, moderate to severe along Sarasota and Manatee counties, minor to moderate over Manatee, Pinellas, Pasco and Hernando counties. At Bradenton Beach in Manatee county, nearly 100 feet of pristine beach, five to six feet in depth, was stripped away by wave action from Hurricane Gordon. In Sarasota county, storm surge and wave action from Gordon caused nearly 1.1 million dollars in beach erosion while in Manatee county, beach erosion was estimated at 500 thousand dollars._x000D_ _x000D_ Inland flooding from rainfall occurred over low-lying and urban areas in mainly Lee, Charlotte, Sarasota, Manatee, Hardee, DeSoto, Highlands and southern Polk counties (see flood entries)._x000D_ _x000D_ Eastern rain bands of Hurricane Gordon spawned at least five known tornadoes, two F1's and three F0's over Central and Southwest Florida (see tornado entries)._x000D_ _x000D_ Damage in Levy county was confined to roofs and toppled trees, mainly in the Cedar Key area, where a total of $100,000 dollars was estimated._x000D_ _x000D_ Damage in Citrus county was confined to a few downed trees, power lines and snapped branches from Sulphur Springs south to Ozello mounting to less than $25,000 dollars._x000D_ _x000D_ Damage in Hernando county was confined to ten homes that suffered floodwater damage along the coast along with a few toppled trees and downed power lines. Damage in Hernando county was estimated at $100,000 dollars._x000D_ _x000D_ Damage in Pasco county was confined to 15 roof damaged villas, downed trees and damaged vehicles in the New Port Colony Villas subdivsion in New Port Richey estimated at $250,000 dollars._x000D_ _x000D_ In Pinellas county, 51 single-family homes, 32 mobile homes, 27 multi-family homes and 24 businesses sustained minor wind or water damage. Estimated cost of the damage in Pinellas county was nearly $500,000 dollars._x000D_ _x000D_ In Hillsborough county, 40 homes in low lying coastal areas from Ruskin to Gibsonton to Riverview, incurred flooding from storm surge. Also, several homes were damaged from wind toppled trees and large branches throughout Hillsborough county. Estimated cost of the damage in Hillsborough county was near $500,000 dollars._x000D_ _x000D_ In Manatee county, 25 homes and businesses were flooded in Bradenton Beach and several homes incurred minor to moderate roof damage in Anna Maria. At Coquina Beach in Manatee county, 60 mph wind gusts, associated with an outer feeder band of Gordon, toppled life guard towers and destroyed an anemometer. Property damage from Hurricane Gordon was estimated at nearly $500,000 dollars in Manatee county._x000D_ _x000D_ In Sarasota county, eight foot high waves, caused nearly $600,000 in property damage to the Venice Municipal Fishing Pier. The hurricane induced waves ripped a 20 foot section and three 50 foot concrete pilings from the northern section of the pier._x000D_ _x000D_ In Lee county, tropical storm force winds caused roof, awning and lanai damage to nine homes, toppled several large trees and branches, and downed power lines across Cape Coral and Ft. Myers. Also, tornadoes, associated with outer feeder bands of Hurricane Gordon, caused significant damage on Sanibel Island of extreme western Lee county (see Lee county tornado entries)._x000D_ _x000D_ Max Wind Gust: 68 mph - Cedar Key, Levy Co. 2153 EST 09/17_x000D_ Lowest Pressure: 994.2 mb - Cedar Key, Levy Co. 2200 EST 09/17_x000D_ Max Rainfall: 6.39 in - Page Field, Ft. Myers, Lee Co. 0000-2400 EST 09/17 | AR48: 131
A49: 5157584 | B49: PASCO (ZONE) | C49: =_xlfn.XLOOKUP(B49,Match!$A$2:$A$111,Match!$B$2:$B$111) -> Pasco, FL | D49: =_xlfn.XLOOKUP(C49,Validation!$B$2:$B$68,Validation!$A$2:$A$68) -> 12101 | F49: 36786 | G49: 500 | H49: Hurricane (Typhoon) | K49: 0 | L49: 0 | M49: 250000 | N49: 0 | O49: FL | P49: EST | R49: 1104015 | S49: Z | T49: 49 | U49: TBW | V49: 0 | W49: 0 | X49: AWOS | Y49: ASOS | Z49: MESONET | AA49: ETC | AJ49: 36787 | AK49: 400 | AQ49: Hurricane Gordon moved northeast across the eastern Gulf of Mexico and brought mainly 30 to 40 mph sustained winds and 50 to nearly 70 mph tropical storm force wind gusts to mainly coastal areas of Southwest and West Central Florida throughout the daylight hours of the 17th. Gordon's ill-defined center made landfall near the Suwannee River around midnight of the 18th. Official, maximum sustained winds of 53 mph, with gusts as high as 68 mph, were observed at the C-MAN automated weather sensor at Cedar Key in Levy county prior to landfall near the mouth of the Suwannee River during the late evening of the 17th._x000D_ _x000D_ Hurricane Gordon produced maximum storm tides above mean sea level of 2 to 4 feet from Lee north to Manatee county, 4 to 5.5 feet along the Pinellas and Hillsborough county coastlines, and 2 to 4 feet from Pasco north to Levy county on the 17th._x000D_ _x000D_ Coastal flooding from storm surge was minimal from Lee county north to the Tampa metropolitan area. Near downtown Tampa, a foot of water covered the south and northern lanes of Bayshore Boulevard during midday on the 17th. Coastal flood waters between one and two feet covered coastal roads along Longboat Key in Manatee county and Siesta and Casey Keys in Sarasota county. In Pinellas county, nearly a foot of water covered coastal roads from St. Pete Beach to Clearwater. The Courtney Campbell Parkway, seperating Pinellas and Hillsborough counties, was closed, due to storm surge flooding, from nearly 5 to 9 pm on the 17th._x000D_ _x000D_ Beach erosion was minor from Lee north to Charlotte, moderate to severe along Sarasota and Manatee counties, minor to moderate over Manatee, Pinellas, Pasco and Hernando counties. At Bradenton Beach in Manatee county, nearly 100 feet of pristine beach, five to six feet in depth, was stripped away by wave action from Hurricane Gordon. In Sarasota county, storm surge and wave action from Gordon caused nearly 1.1 million dollars in beach erosion while in Manatee county, beach erosion was estimated at 500 thousand dollars._x000D_ _x000D_ Inland flooding from rainfall occurred over low-lying and urban areas in mainly Lee, Charlotte, Sarasota, Manatee, Hardee, DeSoto, Highlands and southern Polk counties (see flood entries)._x000D_ _x000D_ Eastern rain bands of Hurricane Gordon spawned at least five known tornadoes, two F1's and three F0's over Central and Southwest Florida (see tornado entries)._x000D_ _x000D_ Damage in Levy county was confined to roofs and toppled trees, mainly in the Cedar Key area, where a total of $100,000 dollars was estimated._x000D_ _x000D_ Damage in Citrus county was confined to a few downed trees, power lines and snapped branches from Sulphur Springs south to Ozello mounting to less than $25,000 dollars._x000D_ _x000D_ Damage in Hernando county was confined to ten homes that suffered floodwater damage along the coast along with a few toppled trees and downed power lines. Damage in Hernando county was estimated at $100,000 dollars._x000D_ _x000D_ Damage in Pasco county was confined to 15 roof damaged villas, downed trees and damaged vehicles in the New Port Colony Villas subdivsion in New Port Richey estimated at $250,000 dollars._x000D_ _x000D_ In Pinellas county, 51 single-family homes, 32 mobile homes, 27 multi-family homes and 24 businesses sustained minor wind or water damage. Estimated cost of the damage in Pinellas county was nearly $500,000 dollars._x000D_ _x000D_ In Hillsborough county, 40 homes in low lying coastal areas from Ruskin to Gibsonton to Riverview, incurred flooding from storm surge. Also, several homes were damaged from wind toppled trees and large branches throughout Hillsborough county. Estimated cost of the damage in Hillsborough county was near $500,000 dollars._x000D_ _x000D_ In Manatee county, 25 homes and businesses were flooded in Bradenton Beach and several homes incurred minor to moderate roof damage in Anna Maria. At Coquina Beach in Manatee county, 60 mph wind gusts, associated with an outer feeder band of Gordon, toppled life guard towers and destroyed an anemometer. Property damage from Hurricane Gordon was estimated at nearly $500,000 dollars in Manatee county._x000D_ _x000D_ In Sarasota county, eight foot high waves, caused nearly $600,000 in property damage to the Venice Municipal Fishing Pier. The hurricane induced waves ripped a 20 foot section and three 50 foot concrete pilings from the northern section of the pier._x000D_ _x000D_ In Lee county, tropical storm force winds caused roof, awning and lanai damage to nine homes, toppled several large trees and branches, and downed power lines across Cape Coral and Ft. Myers. Also, tornadoes, associated with outer feeder bands of Hurricane Gordon, caused significant damage on Sanibel Island of extreme western Lee county (see Lee county tornado entries)._x000D_ _x000D_ Max Wind Gust: 68 mph - Cedar Key, Levy Co. 2153 EST 09/17_x000D_ Lowest Pressure: 994.2 mb - Cedar Key, Levy Co. 2200 EST 09/17_x000D_ Max Rainfall: 6.39 in - Page Field, Ft. Myers, Lee Co. 0000-2400 EST 09/17 | AR49: 132
A50: 5157583 | B50: MANATEE (ZONE) | C50: =_xlfn.XLOOKUP(B50,Match!$A$2:$A$111,Match!$B$2:$B$111) -> Manatee, FL | D50: =_xlfn.XLOOKUP(C50,Validation!$B$2:$B$68,Validation!$A$2:$A$68) -> 12081 | F50: 36786 | G50: 500 | H50: Hurricane (Typhoon) | K50: 0 | L50: 0 | M50: 1000000 | N50: 0 | O50: FL | P50: EST | R50: 1104015 | S50: Z | T50: 55 | U50: TBW | V50: 0 | W50: 0 | X50: AWOS | Y50: ASOS | Z50: MESONET | AA50: ETC | AJ50: 36786 | AK50: 1600 | AQ50: Hurricane Gordon moved northeast across the eastern Gulf of Mexico and brought mainly 30 to 40 mph sustained winds and 50 to nearly 70 mph tropical storm force wind gusts to mainly coastal areas of Southwest and West Central Florida throughout the daylight hours of the 17th. Gordon's ill-defined center made landfall near the Suwannee River around midnight of the 18th. Official, maximum sustained winds of 53 mph, with gusts as high as 68 mph, were observed at the C-MAN automated weather sensor at Cedar Key in Levy county prior to landfall near the mouth of the Suwannee River during the late evening of the 17th._x000D_ _x000D_ Hurricane Gordon produced maximum storm tides above mean sea level of 2 to 4 feet from Lee north to Manatee county, 4 to 5.5 feet along the Pinellas and Hillsborough county coastlines, and 2 to 4 feet from Pasco north to Levy county on the 17th._x000D_ _x000D_ Coastal flooding from storm surge was minimal from Lee county north to the Tampa metropolitan area. Near downtown Tampa, a foot of water covered the south and northern lanes of Bayshore Boulevard during midday on the 17th. Coastal flood waters between one and two feet covered coastal roads along Longboat Key in Manatee county and Siesta and Casey Keys in Sarasota county. In Pinellas county, nearly a foot of water covered coastal roads from St. Pete Beach to Clearwater. The Courtney Campbell Parkway, seperating Pinellas and Hillsborough counties, was closed, due to storm surge flooding, from nearly 5 to 9 pm on the 17th._x000D_ _x000D_ Beach erosion was minor from Lee north to Charlotte, moderate to severe along Sarasota and Manatee counties, minor to moderate over Manatee, Pinellas, Pasco and Hernando counties. At Bradenton Beach in Manatee county, nearly 100 feet of pristine beach, five to six feet in depth, was stripped away by wave action from Hurricane Gordon. In Sarasota county, storm surge and wave action from Gordon caused nearly 1.1 million dollars in beach erosion while in Manatee county, beach erosion was estimated at 500 thousand dollars._x000D_ _x000D_ Inland flooding from rainfall occurred over low-lying and urban areas in mainly Lee, Charlotte, Sarasota, Manatee, Hardee, DeSoto, Highlands and southern Polk counties (see flood entries)._x000D_ _x000D_ Eastern rain bands of Hurricane Gordon spawned at least five known tornadoes, two F1's and three F0's over Central and Southwest Florida (see tornado entries)._x000D_ _x000D_ Damage in Levy county was confined to roofs and toppled trees, mainly in the Cedar Key area, where a total of $100,000 dollars was estimated._x000D_ _x000D_ Damage in Citrus county was confined to a few downed trees, power lines and snapped branches from Sulphur Springs south to Ozello mounting to less than $25,000 dollars._x000D_ _x000D_ Damage in Hernando county was confined to ten homes that suffered floodwater damage along the coast along with a few toppled trees and downed power lines. Damage in Hernando county was estimated at $100,000 dollars._x000D_ _x000D_ Damage in Pasco county was confined to 15 roof damaged villas, downed trees and damaged vehicles in the New Port Colony Villas subdivsion in New Port Richey estimated at $250,000 dollars._x000D_ _x000D_ In Pinellas county, 51 single-family homes, 32 mobile homes, 27 multi-family homes and 24 businesses sustained minor wind or water damage. Estimated cost of the damage in Pinellas county was nearly $500,000 dollars._x000D_ _x000D_ In Hillsborough county, 40 homes in low lying coastal areas from Ruskin to Gibsonton to Riverview, incurred flooding from storm surge. Also, several homes were damaged from wind toppled trees and large branches throughout Hillsborough county. Estimated cost of the damage in Hillsborough county was near $500,000 dollars._x000D_ _x000D_ In Manatee county, 25 homes and businesses were flooded in Bradenton Beach and several homes incurred minor to moderate roof damage in Anna Maria. At Coquina Beach in Manatee county, 60 mph wind gusts, associated with an outer feeder band of Gordon, toppled life guard towers and destroyed an anemometer. Property damage from Hurricane Gordon was estimated at nearly $500,000 dollars in Manatee county._x000D_ _x000D_ In Sarasota county, eight foot high waves, caused nearly $600,000 in property damage to the Venice Municipal Fishing Pier. The hurricane induced waves ripped a 20 foot section and three 50 foot concrete pilings from the northern section of the pier._x000D_ _x000D_ In Lee county, tropical storm force winds caused roof, awning and lanai damage to nine homes, toppled several large trees and branches, and downed power lines across Cape Coral and Ft. Myers. Also, tornadoes, associated with outer feeder bands of Hurricane Gordon, caused significant damage on Sanibel Island of extreme western Lee county (see Lee county tornado entries)._x000D_ _x000D_ Max Wind Gust: 68 mph - Cedar Key, Levy Co. 2153 EST 09/17_x000D_ Lowest Pressure: 994.2 mb - Cedar Key, Levy Co. 2200 EST 09/17_x000D_ Max Rainfall: 6.39 in - Page Field, Ft. Myers, Lee Co. 0000-2400 EST 09/17 | AR50: 133
A51: 5157582 | B51: LEVY (ZONE) | C51: =_xlfn.XLOOKUP(B51,Match!$A$2:$A$111,Match!$B$2:$B$111) -> Levy, FL | D51: =_xlfn.XLOOKUP(C51,Validation!$B$2:$B$68,Validation!$A$2:$A$68) -> 12075 | F51: 36786 | G51: 500 | H51: Hurricane (Typhoon) | K51: 0 | L51: 0 | M51: 100000 | N51: 0 | O51: FL | P51: EST | R51: 1104015 | S51: Z | T51: 39 | U51: TBW | V51: 0 | W51: 0 | X51: AWOS | Y51: ASOS | Z51: MESONET | AA51: ETC | AJ51: 36787 | AK51: 400 | AQ51: Hurricane Gordon moved northeast across the eastern Gulf of Mexico and brought mainly 30 to 40 mph sustained winds and 50 to nearly 70 mph tropical storm force wind gusts to mainly coastal areas of Southwest and West Central Florida throughout the daylight hours of the 17th. Gordon's ill-defined center made landfall near the Suwannee River around midnight of the 18th. Official, maximum sustained winds of 53 mph, with gusts as high as 68 mph, were observed at the C-MAN automated weather sensor at Cedar Key in Levy county prior to landfall near the mouth of the Suwannee River during the late evening of the 17th._x000D_ _x000D_ Hurricane Gordon produced maximum storm tides above mean sea level of 2 to 4 feet from Lee north to Manatee county, 4 to 5.5 feet along the Pinellas and Hillsborough county coastlines, and 2 to 4 feet from Pasco north to Levy county on the 17th._x000D_ _x000D_ Coastal flooding from storm surge was minimal from Lee county north to the Tampa metropolitan area. Near downtown Tampa, a foot of water covered the south and northern lanes of Bayshore Boulevard during midday on the 17th. Coastal flood waters between one and two feet covered coastal roads along Longboat Key in Manatee county and Siesta and Casey Keys in Sarasota county. In Pinellas county, nearly a foot of water covered coastal roads from St. Pete Beach to Clearwater. The Courtney Campbell Parkway, seperating Pinellas and Hillsborough counties, was closed, due to storm surge flooding, from nearly 5 to 9 pm on the 17th._x000D_ _x000D_ Beach erosion was minor from Lee north to Charlotte, moderate to severe along Sarasota and Manatee counties, minor to moderate over Manatee, Pinellas, Pasco and Hernando counties. At Bradenton Beach in Manatee county, nearly 100 feet of pristine beach, five to six feet in depth, was stripped away by wave action from Hurricane Gordon. In Sarasota county, storm surge and wave action from Gordon caused nearly 1.1 million dollars in beach erosion while in Manatee county, beach erosion was estimated at 500 thousand dollars._x000D_ _x000D_ Inland flooding from rainfall occurred over low-lying and urban areas in mainly Lee, Charlotte, Sarasota, Manatee, Hardee, DeSoto, Highlands and southern Polk counties (see flood entries)._x000D_ _x000D_ Eastern rain bands of Hurricane Gordon spawned at least five known tornadoes, two F1's and three F0's over Central and Southwest Florida (see tornado entries)._x000D_ _x000D_ Damage in Levy county was confined to roofs and toppled trees, mainly in the Cedar Key area, where a total of $100,000 dollars was estimated._x000D_ _x000D_ Damage in Citrus county was confined to a few downed trees, power lines and snapped branches from Sulphur Springs south to Ozello mounting to less than $25,000 dollars._x000D_ _x000D_ Damage in Hernando county was confined to ten homes that suffered floodwater damage along the coast along with a few toppled trees and downed power lines. Damage in Hernando county was estimated at $100,000 dollars._x000D_ _x000D_ Damage in Pasco county was confined to 15 roof damaged villas, downed trees and damaged vehicles in the New Port Colony Villas subdivsion in New Port Richey estimated at $250,000 dollars._x000D_ _x000D_ In Pinellas county, 51 single-family homes, 32 mobile homes, 27 multi-family homes and 24 businesses sustained minor wind or water damage. Estimated cost of the damage in Pinellas county was nearly $500,000 dollars._x000D_ _x000D_ In Hillsborough county, 40 homes in low lying coastal areas from Ruskin to Gibsonton to Riverview, incurred flooding from storm surge. Also, several homes were damaged from wind toppled trees and large branches throughout Hillsborough county. Estimated cost of the damage in Hillsborough county was near $500,000 dollars._x000D_ _x000D_ In Manatee county, 25 homes and businesses were flooded in Bradenton Beach and several homes incurred minor to moderate roof damage in Anna Maria. At Coquina Beach in Manatee county, 60 mph wind gusts, associated with an outer feeder band of Gordon, toppled life guard towers and destroyed an anemometer. Property damage from Hurricane Gordon was estimated at nearly $500,000 dollars in Manatee county._x000D_ _x000D_ In Sarasota county, eight foot high waves, caused nearly $600,000 in property damage to the Venice Municipal Fishing Pier. The hurricane induced waves ripped a 20 foot section and three 50 foot concrete pilings from the northern section of the pier._x000D_ _x000D_ In Lee county, tropical storm force winds caused roof, awning and lanai damage to nine homes, toppled several large trees and branches, and downed power lines across Cape Coral and Ft. Myers. Also, tornadoes, associated with outer feeder bands of Hurricane Gordon, caused significant damage on Sanibel Island of extreme western Lee county (see Lee county tornado entries)._x000D_ _x000D_ Max Wind Gust: 68 mph - Cedar Key, Levy Co. 2153 EST 09/17_x000D_ Lowest Pressure: 994.2 mb - Cedar Key, Levy Co. 2200 EST 09/17_x000D_ Max Rainfall: 6.39 in - Page Field, Ft. Myers, Lee Co. 0000-2400 EST 09/17 | AR51: 134
A52: 5157581 | B52: HILLSBOROUGH (ZONE) | C52: =_xlfn.XLOOKUP(B52,Match!$A$2:$A$111,Match!$B$2:$B$111) -> Hillsborough, FL | D52: =_xlfn.XLOOKUP(C52,Validation!$B$2:$B$68,Validation!$A$2:$A$68) -> 12057 | F52: 36786 | G52: 500 | H52: Hurricane (Typhoon) | K52: 0 | L52: 0 | M52: 500000 | N52: 0 | O52: FL | P52: EST | R52: 1104015 | S52: Z | T52: 51 | U52: TBW | V52: 0 | W52: 0 | X52: AWOS | Y52: ASOS | Z52: MESONET | AA52: ETC | AJ52: 36786 | AK52: 2200 | AQ52: Hurricane Gordon moved northeast across the eastern Gulf of Mexico and brought mainly 30 to 40 mph sustained winds and 50 to nearly 70 mph tropical storm force wind gusts to mainly coastal areas of Southwest and West Central Florida throughout the daylight hours of the 17th. Gordon's ill-defined center made landfall near the Suwannee River around midnight of the 18th. Official, maximum sustained winds of 53 mph, with gusts as high as 68 mph, were observed at the C-MAN automated weather sensor at Cedar Key in Levy county prior to landfall near the mouth of the Suwannee River during the late evening of the 17th._x000D_ _x000D_ Hurricane Gordon produced maximum storm tides above mean sea level of 2 to 4 feet from Lee north to Manatee county, 4 to 5.5 feet along the Pinellas and Hillsborough county coastlines, and 2 to 4 feet from Pasco north to Levy county on the 17th._x000D_ _x000D_ Coastal flooding from storm surge was minimal from Lee county north to the Tampa metropolitan area. Near downtown Tampa, a foot of water covered the south and northern lanes of Bayshore Boulevard during midday on the 17th. Coastal flood waters between one and two feet covered coastal roads along Longboat Key in Manatee county and Siesta and Casey Keys in Sarasota county. In Pinellas county, nearly a foot of water covered coastal roads from St. Pete Beach to Clearwater. The Courtney Campbell Parkway, seperating Pinellas and Hillsborough counties, was closed, due to storm surge flooding, from nearly 5 to 9 pm on the 17th._x000D_ _x000D_ Beach erosion was minor from Lee north to Charlotte, moderate to severe along Sarasota and Manatee counties, minor to moderate over Manatee, Pinellas, Pasco and Hernando counties. At Bradenton Beach in Manatee county, nearly 100 feet of pristine beach, five to six feet in depth, was stripped away by wave action from Hurricane Gordon. In Sarasota county, storm surge and wave action from Gordon caused nearly 1.1 million dollars in beach erosion while in Manatee county, beach erosion was estimated at 500 thousand dollars._x000D_ _x000D_ Inland flooding from rainfall occurred over low-lying and urban areas in mainly Lee, Charlotte, Sarasota, Manatee, Hardee, DeSoto, Highlands and southern Polk counties (see flood entries)._x000D_ _x000D_ Eastern rain bands of Hurricane Gordon spawned at least five known tornadoes, two F1's and three F0's over Central and Southwest Florida (see tornado entries)._x000D_ _x000D_ Damage in Levy county was confined to roofs and toppled trees, mainly in the Cedar Key area, where a total of $100,000 dollars was estimated._x000D_ _x000D_ Damage in Citrus county was confined to a few downed trees, power lines and snapped branches from Sulphur Springs south to Ozello mounting to less than $25,000 dollars._x000D_ _x000D_ Damage in Hernando county was confined to ten homes that suffered floodwater damage along the coast along with a few toppled trees and downed power lines. Damage in Hernando county was estimated at $100,000 dollars._x000D_ _x000D_ Damage in Pasco county was confined to 15 roof damaged villas, downed trees and damaged vehicles in the New Port Colony Villas subdivsion in New Port Richey estimated at $250,000 dollars._x000D_ _x000D_ In Pinellas county, 51 single-family homes, 32 mobile homes, 27 multi-family homes and 24 businesses sustained minor wind or water damage. Estimated cost of the damage in Pinellas county was nearly $500,000 dollars._x000D_ _x000D_ In Hillsborough county, 40 homes in low lying coastal areas from Ruskin to Gibsonton to Riverview, incurred flooding from storm surge. Also, several homes were damaged from wind toppled trees and large branches throughout Hillsborough county. Estimated cost of the damage in Hillsborough county was near $500,000 dollars._x000D_ _x000D_ In Manatee county, 25 homes and businesses were flooded in Bradenton Beach and several homes incurred minor to moderate roof damage in Anna Maria. At Coquina Beach in Manatee county, 60 mph wind gusts, associated with an outer feeder band of Gordon, toppled life guard towers and destroyed an anemometer. Property damage from Hurricane Gordon was estimated at nearly $500,000 dollars in Manatee county._x000D_ _x000D_ In Sarasota county, eight foot high waves, caused nearly $600,000 in property damage to the Venice Municipal Fishing Pier. The hurricane induced waves ripped a 20 foot section and three 50 foot concrete pilings from the northern section of the pier._x000D_ _x000D_ In Lee county, tropical storm force winds caused roof, awning and lanai damage to nine homes, toppled several large trees and branches, and downed power lines across Cape Coral and Ft. Myers. Also, tornadoes, associated with outer feeder bands of Hurricane Gordon, caused significant damage on Sanibel Island of extreme western Lee county (see Lee county tornado entries)._x000D_ _x000D_ Max Wind Gust: 68 mph - Cedar Key, Levy Co. 2153 EST 09/17_x000D_ Lowest Pressure: 994.2 mb - Cedar Key, Levy Co. 2200 EST 09/17_x000D_ Max Rainfall: 6.39 in - Page Field, Ft. Myers, Lee Co. 0000-2400 EST 09/17 | AR52: 135
A53: 5157579 | B53: HERNANDO (ZONE) | C53: =_xlfn.XLOOKUP(B53,Match!$A$2:$A$111,Match!$B$2:$B$111) -> Hernando, FL | D53: =_xlfn.XLOOKUP(C53,Validation!$B$2:$B$68,Validation!$A$2:$A$68) -> 12053 | F53: 36786 | G53: 500 | H53: Hurricane (Typhoon) | K53: 0 | L53: 0 | M53: 100000 | N53: 0 | O53: FL | P53: EST | R53: 1104015 | S53: Z | T53: 48 | U53: TBW | V53: 0 | W53: 0 | X53: AWOS | Y53: ASOS | Z53: MESONET | AA53: ETC | AJ53: 36787 | AK53: 400 | AQ53: Hurricane Gordon moved northeast across the eastern Gulf of Mexico and brought mainly 30 to 40 mph sustained winds and 50 to nearly 70 mph tropical storm force wind gusts to mainly coastal areas of Southwest and West Central Florida throughout the daylight hours of the 17th. Gordon's ill-defined center made landfall near the Suwannee River around midnight of the 18th. Official, maximum sustained winds of 53 mph, with gusts as high as 68 mph, were observed at the C-MAN automated weather sensor at Cedar Key in Levy county prior to landfall near the mouth of the Suwannee River during the late evening of the 17th._x000D_ _x000D_ Hurricane Gordon produced maximum storm tides above mean sea level of 2 to 4 feet from Lee north to Manatee county, 4 to 5.5 feet along the Pinellas and Hillsborough county coastlines, and 2 to 4 feet from Pasco north to Levy county on the 17th._x000D_ _x000D_ Coastal flooding from storm surge was minimal from Lee county north to the Tampa metropolitan area. Near downtown Tampa, a foot of water covered the south and northern lanes of Bayshore Boulevard during midday on the 17th. Coastal flood waters between one and two feet covered coastal roads along Longboat Key in Manatee county and Siesta and Casey Keys in Sarasota county. In Pinellas county, nearly a foot of water covered coastal roads from St. Pete Beach to Clearwater. The Courtney Campbell Parkway, seperating Pinellas and Hillsborough counties, was closed, due to storm surge flooding, from nearly 5 to 9 pm on the 17th._x000D_ _x000D_ Beach erosion was minor from Lee north to Charlotte, moderate to severe along Sarasota and Manatee counties, minor to moderate over Manatee, Pinellas, Pasco and Hernando counties. At Bradenton Beach in Manatee county, nearly 100 feet of pristine beach, five to six feet in depth, was stripped away by wave action from Hurricane Gordon. In Sarasota county, storm surge and wave action from Gordon caused nearly 1.1 million dollars in beach erosion while in Manatee county, beach erosion was estimated at 500 thousand dollars._x000D_ _x000D_ Inland flooding from rainfall occurred over low-lying and urban areas in mainly Lee, Charlotte, Sarasota, Manatee, Hardee, DeSoto, Highlands and southern Polk counties (see flood entries)._x000D_ _x000D_ Eastern rain bands of Hurricane Gordon spawned at least five known tornadoes, two F1's and three F0's over Central and Southwest Florida (see tornado entries)._x000D_ _x000D_ Damage in Levy county was confined to roofs and toppled trees, mainly in the Cedar Key area, where a total of $100,000 dollars was estimated._x000D_ _x000D_ Damage in Citrus county was confined to a few downed trees, power lines and snapped branches from Sulphur Springs south to Ozello mounting to less than $25,000 dollars._x000D_ _x000D_ Damage in Hernando county was confined to ten homes that suffered floodwater damage along the coast along with a few toppled trees and downed power lines. Damage in Hernando county was estimated at $100,000 dollars._x000D_ _x000D_ Damage in Pasco county was confined to 15 roof damaged villas, downed trees and damaged vehicles in the New Port Colony Villas subdivsion in New Port Richey estimated at $250,000 dollars._x000D_ _x000D_ In Pinellas county, 51 single-family homes, 32 mobile homes, 27 multi-family homes and 24 businesses sustained minor wind or water damage. Estimated cost of the damage in Pinellas county was nearly $500,000 dollars._x000D_ _x000D_ In Hillsborough county, 40 homes in low lying coastal areas from Ruskin to Gibsonton to Riverview, incurred flooding from storm surge. Also, several homes were damaged from wind toppled trees and large branches throughout Hillsborough county. Estimated cost of the damage in Hillsborough county was near $500,000 dollars._x000D_ _x000D_ In Manatee county, 25 homes and businesses were flooded in Bradenton Beach and several homes incurred minor to moderate roof damage in Anna Maria. At Coquina Beach in Manatee county, 60 mph wind gusts, associated with an outer feeder band of Gordon, toppled life guard towers and destroyed an anemometer. Property damage from Hurricane Gordon was estimated at nearly $500,000 dollars in Manatee county._x000D_ _x000D_ In Sarasota county, eight foot high waves, caused nearly $600,000 in property damage to the Venice Municipal Fishing Pier. The hurricane induced waves ripped a 20 foot section and three 50 foot concrete pilings from the northern section of the pier._x000D_ _x000D_ In Lee county, tropical storm force winds caused roof, awning and lanai damage to nine homes, toppled several large trees and branches, and downed power lines across Cape Coral and Ft. Myers. Also, tornadoes, associated with outer feeder bands of Hurricane Gordon, caused significant damage on Sanibel Island of extreme western Lee county (see Lee county tornado entries)._x000D_ _x000D_ Max Wind Gust: 68 mph - Cedar Key, Levy Co. 2153 EST 09/17_x000D_ Lowest Pressure: 994.2 mb - Cedar Key, Levy Co. 2200 EST 09/17_x000D_ Max Rainfall: 6.39 in - Page Field, Ft. Myers, Lee Co. 0000-2400 EST 09/17 | AR53: 136
A54: 5157578 | B54: HARDEE (ZONE) | C54: =_xlfn.XLOOKUP(B54,Match!$A$2:$A$111,Match!$B$2:$B$111) -> Hardee, FL | D54: =_xlfn.XLOOKUP(C54,Validation!$B$2:$B$68,Validation!$A$2:$A$68) -> 12049 | F54: 36786 | G54: 500 | H54: Hurricane (Typhoon) | K54: 0 | L54: 0 | M54: 20000 | N54: 0 | O54: FL | P54: EST | R54: 1104015 | S54: Z | T54: 56 | U54: TBW | V54: 0 | W54: 0 | X54: AWOS | Y54: ASOS | Z54: MESONET | AA54: ETC | AJ54: 36786 | AK54: 1600 | AQ54: Hurricane Gordon moved northeast across the eastern Gulf of Mexico and brought mainly 30 to 40 mph sustained winds and 50 to nearly 70 mph tropical storm force wind gusts to mainly coastal areas of Southwest and West Central Florida throughout the daylight hours of the 17th. Gordon's ill-defined center made landfall near the Suwannee River around midnight of the 18th. Official, maximum sustained winds of 53 mph, with gusts as high as 68 mph, were observed at the C-MAN automated weather sensor at Cedar Key in Levy county prior to landfall near the mouth of the Suwannee River during the late evening of the 17th._x000D_ _x000D_ Hurricane Gordon produced maximum storm tides above mean sea level of 2 to 4 feet from Lee north to Manatee county, 4 to 5.5 feet along the Pinellas and Hillsborough county coastlines, and 2 to 4 feet from Pasco north to Levy county on the 17th._x000D_ _x000D_ Coastal flooding from storm surge was minimal from Lee county north to the Tampa metropolitan area. Near downtown Tampa, a foot of water covered the south and northern lanes of Bayshore Boulevard during midday on the 17th. Coastal flood waters between one and two feet covered coastal roads along Longboat Key in Manatee county and Siesta and Casey Keys in Sarasota county. In Pinellas county, nearly a foot of water covered coastal roads from St. Pete Beach to Clearwater. The Courtney Campbell Parkway, seperating Pinellas and Hillsborough counties, was closed, due to storm surge flooding, from nearly 5 to 9 pm on the 17th._x000D_ _x000D_ Beach erosion was minor from Lee north to Charlotte, moderate to severe along Sarasota and Manatee counties, minor to moderate over Manatee, Pinellas, Pasco and Hernando counties. At Bradenton Beach in Manatee county, nearly 100 feet of pristine beach, five to six feet in depth, was stripped away by wave action from Hurricane Gordon. In Sarasota county, storm surge and wave action from Gordon caused nearly 1.1 million dollars in beach erosion while in Manatee county, beach erosion was estimated at 500 thousand dollars._x000D_ _x000D_ Inland flooding from rainfall occurred over low-lying and urban areas in mainly Lee, Charlotte, Sarasota, Manatee, Hardee, DeSoto, Highlands and southern Polk counties (see flood entries)._x000D_ _x000D_ Eastern rain bands of Hurricane Gordon spawned at least five known tornadoes, two F1's and three F0's over Central and Southwest Florida (see tornado entries)._x000D_ _x000D_ Damage in Levy county was confined to roofs and toppled trees, mainly in the Cedar Key area, where a total of $100,000 dollars was estimated._x000D_ _x000D_ Damage in Citrus county was confined to a few downed trees, power lines and snapped branches from Sulphur Springs south to Ozello mounting to less than $25,000 dollars._x000D_ _x000D_ Damage in Hernando county was confined to ten homes that suffered floodwater damage along the coast along with a few toppled trees and downed power lines. Damage in Hernando county was estimated at $100,000 dollars._x000D_ _x000D_ Damage in Pasco county was confined to 15 roof damaged villas, downed trees and damaged vehicles in the New Port Colony Villas subdivsion in New Port Richey estimated at $250,000 dollars._x000D_ _x000D_ In Pinellas county, 51 single-family homes, 32 mobile homes, 27 multi-family homes and 24 businesses sustained minor wind or water damage. Estimated cost of the damage in Pinellas county was nearly $500,000 dollars._x000D_ _x000D_ In Hillsborough county, 40 homes in low lying coastal areas from Ruskin to Gibsonton to Riverview, incurred flooding from storm surge. Also, several homes were damaged from wind toppled trees and large branches throughout Hillsborough county. Estimated cost of the damage in Hillsborough county was near $500,000 dollars._x000D_ _x000D_ In Manatee county, 25 homes and businesses were flooded in Bradenton Beach and several homes incurred minor to moderate roof damage in Anna Maria. At Coquina Beach in Manatee county, 60 mph wind gusts, associated with an outer feeder band of Gordon, toppled life guard towers and destroyed an anemometer. Property damage from Hurricane Gordon was estimated at nearly $500,000 dollars in Manatee county._x000D_ _x000D_ In Sarasota county, eight foot high waves, caused nearly $600,000 in property damage to the Venice Municipal Fishing Pier. The hurricane induced waves ripped a 20 foot section and three 50 foot concrete pilings from the northern section of the pier._x000D_ _x000D_ In Lee county, tropical storm force winds caused roof, awning and lanai damage to nine homes, toppled several large trees and branches, and downed power lines across Cape Coral and Ft. Myers. Also, tornadoes, associated with outer feeder bands of Hurricane Gordon, caused significant damage on Sanibel Island of extreme western Lee county (see Lee county tornado entries)._x000D_ _x000D_ Max Wind Gust: 68 mph - Cedar Key, Levy Co. 2153 EST 09/17_x000D_ Lowest Pressure: 994.2 mb - Cedar Key, Levy Co. 2200 EST 09/17_x000D_ Max Rainfall: 6.39 in - Page Field, Ft. Myers, Lee Co. 0000-2400 EST 09/17 | AR54: 137
A55: 5157577 | B55: DE SOTO (ZONE) | C55: =_xlfn.XLOOKUP(B55,Match!$A$2:$A$111,Match!$B$2:$B$111) -> DeSoto, FL | D55: =_xlfn.XLOOKUP(C55,Validation!$B$2:$B$68,Validation!$A$2:$A$68) -> 12027 | F55: 36786 | G55: 500 | H55: Hurricane (Typhoon) | K55: 0 | L55: 0 | M55: 20000 | N55: 0 | O55: FL | P55: EST | R55: 1104015 | S55: Z | T55: 61 | U55: TBW | V55: 0 | W55: 0 | X55: AWOS | Y55: ASOS | Z55: MESONET | AA55: ETC | AJ55: 36786 | AK55: 1600 | AQ55: Hurricane Gordon moved northeast across the eastern Gulf of Mexico and brought mainly 30 to 40 mph sustained winds and 50 to nearly 70 mph tropical storm force wind gusts to mainly coastal areas of Southwest and West Central Florida throughout the daylight hours of the 17th. Gordon's ill-defined center made landfall near the Suwannee River around midnight of the 18th. Official, maximum sustained winds of 53 mph, with gusts as high as 68 mph, were observed at the C-MAN automated weather sensor at Cedar Key in Levy county prior to landfall near the mouth of the Suwannee River during the late evening of the 17th._x000D_ _x000D_ Hurricane Gordon produced maximum storm tides above mean sea level of 2 to 4 feet from Lee north to Manatee county, 4 to 5.5 feet along the Pinellas and Hillsborough county coastlines, and 2 to 4 feet from Pasco north to Levy county on the 17th._x000D_ _x000D_ Coastal flooding from storm surge was minimal from Lee county north to the Tampa metropolitan area. Near downtown Tampa, a foot of water covered the south and northern lanes of Bayshore Boulevard during midday on the 17th. Coastal flood waters between one and two feet covered coastal roads along Longboat Key in Manatee county and Siesta and Casey Keys in Sarasota county. In Pinellas county, nearly a foot of water covered coastal roads from St. Pete Beach to Clearwater. The Courtney Campbell Parkway, seperating Pinellas and Hillsborough counties, was closed, due to storm surge flooding, from nearly 5 to 9 pm on the 17th._x000D_ _x000D_ Beach erosion was minor from Lee north to Charlotte, moderate to severe along Sarasota and Manatee counties, minor to moderate over Manatee, Pinellas, Pasco and Hernando counties. At Bradenton Beach in Manatee county, nearly 100 feet of pristine beach, five to six feet in depth, was stripped away by wave action from Hurricane Gordon. In Sarasota county, storm surge and wave action from Gordon caused nearly 1.1 million dollars in beach erosion while in Manatee county, beach erosion was estimated at 500 thousand dollars._x000D_ _x000D_ Inland flooding from rainfall occurred over low-lying and urban areas in mainly Lee, Charlotte, Sarasota, Manatee, Hardee, DeSoto, Highlands and southern Polk counties (see flood entries)._x000D_ _x000D_ Eastern rain bands of Hurricane Gordon spawned at least five known tornadoes, two F1's and three F0's over Central and Southwest Florida (see tornado entries)._x000D_ _x000D_ Damage in Levy county was confined to roofs and toppled trees, mainly in the Cedar Key area, where a total of $100,000 dollars was estimated._x000D_ _x000D_ Damage in Citrus county was confined to a few downed trees, power lines and snapped branches from Sulphur Springs south to Ozello mounting to less than $25,000 dollars._x000D_ _x000D_ Damage in Hernando county was confined to ten homes that suffered floodwater damage along the coast along with a few toppled trees and downed power lines. Damage in Hernando county was estimated at $100,000 dollars._x000D_ _x000D_ Damage in Pasco county was confined to 15 roof damaged villas, downed trees and damaged vehicles in the New Port Colony Villas subdivsion in New Port Richey estimated at $250,000 dollars._x000D_ _x000D_ In Pinellas county, 51 single-family homes, 32 mobile homes, 27 multi-family homes and 24 businesses sustained minor wind or water damage. Estimated cost of the damage in Pinellas county was nearly $500,000 dollars._x000D_ _x000D_ In Hillsborough county, 40 homes in low lying coastal areas from Ruskin to Gibsonton to Riverview, incurred flooding from storm surge. Also, several homes were damaged from wind toppled trees and large branches throughout Hillsborough county. Estimated cost of the damage in Hillsborough county was near $500,000 dollars._x000D_ _x000D_ In Manatee county, 25 homes and businesses were flooded in Bradenton Beach and several homes incurred minor to moderate roof damage in Anna Maria. At Coquina Beach in Manatee county, 60 mph wind gusts, associated with an outer feeder band of Gordon, toppled life guard towers and destroyed an anemometer. Property damage from Hurricane Gordon was estimated at nearly $500,000 dollars in Manatee county._x000D_ _x000D_ In Sarasota county, eight foot high waves, caused nearly $600,000 in property damage to the Venice Municipal Fishing Pier. The hurricane induced waves ripped a 20 foot section and three 50 foot concrete pilings from the northern section of the pier._x000D_ _x000D_ In Lee county, tropical storm force winds caused roof, awning and lanai damage to nine homes, toppled several large trees and branches, and downed power lines across Cape Coral and Ft. Myers. Also, tornadoes, associated with outer feeder bands of Hurricane Gordon, caused significant damage on Sanibel Island of extreme western Lee county (see Lee county tornado entries)._x000D_ _x000D_ Max Wind Gust: 68 mph - Cedar Key, Levy Co. 2153 EST 09/17_x000D_ Lowest Pressure: 994.2 mb - Cedar Key, Levy Co. 2200 EST 09/17_x000D_ Max Rainfall: 6.39 in - Page Field, Ft. Myers, Lee Co. 0000-2400 EST 09/17 | AR55: 138
A56: 5157576 | B56: CITRUS (ZONE) | C56: =_xlfn.XLOOKUP(B56,Match!$A$2:$A$111,Match!$B$2:$B$111) -> Citrus, FL | D56: =_xlfn.XLOOKUP(C56,Validation!$B$2:$B$68,Validation!$A$2:$A$68) -> 12017 | F56: 36786 | G56: 500 | H56: Hurricane (Typhoon) | K56: 0 | L56: 0 | M56: 25000 | N56: 0 | O56: FL | P56: EST | R56: 1104015 | S56: Z | T56: 42 | U56: TBW | V56: 0 | W56: 0 | X56: AWOS | Y56: ASOS | Z56: MESONET | AA56: ETC | AJ56: 36787 | AK56: 400 | AQ56: Hurricane Gordon moved northeast across the eastern Gulf of Mexico and brought mainly 30 to 40 mph sustained winds and 50 to nearly 70 mph tropical storm force wind gusts to mainly coastal areas of Southwest and West Central Florida throughout the daylight hours of the 17th. Gordon's ill-defined center made landfall near the Suwannee River around midnight of the 18th. Official, maximum sustained winds of 53 mph, with gusts as high as 68 mph, were observed at the C-MAN automated weather sensor at Cedar Key in Levy county prior to landfall near the mouth of the Suwannee River during the late evening of the 17th._x000D_ _x000D_ Hurricane Gordon produced maximum storm tides above mean sea level of 2 to 4 feet from Lee north to Manatee county, 4 to 5.5 feet along the Pinellas and Hillsborough county coastlines, and 2 to 4 feet from Pasco north to Levy county on the 17th._x000D_ _x000D_ Coastal flooding from storm surge was minimal from Lee county north to the Tampa metropolitan area. Near downtown Tampa, a foot of water covered the south and northern lanes of Bayshore Boulevard during midday on the 17th. Coastal flood waters between one and two feet covered coastal roads along Longboat Key in Manatee county and Siesta and Casey Keys in Sarasota county. In Pinellas county, nearly a foot of water covered coastal roads from St. Pete Beach to Clearwater. The Courtney Campbell Parkway, seperating Pinellas and Hillsborough counties, was closed, due to storm surge flooding, from nearly 5 to 9 pm on the 17th._x000D_ _x000D_ Beach erosion was minor from Lee north to Charlotte, moderate to severe along Sarasota and Manatee counties, minor to moderate over Manatee, Pinellas, Pasco and Hernando counties. At Bradenton Beach in Manatee county, nearly 100 feet of pristine beach, five to six feet in depth, was stripped away by wave action from Hurricane Gordon. In Sarasota county, storm surge and wave action from Gordon caused nearly 1.1 million dollars in beach erosion while in Manatee county, beach erosion was estimated at 500 thousand dollars._x000D_ _x000D_ Inland flooding from rainfall occurred over low-lying and urban areas in mainly Lee, Charlotte, Sarasota, Manatee, Hardee, DeSoto, Highlands and southern Polk counties (see flood entries)._x000D_ _x000D_ Eastern rain bands of Hurricane Gordon spawned at least five known tornadoes, two F1's and three F0's over Central and Southwest Florida (see tornado entries)._x000D_ _x000D_ Damage in Levy county was confined to roofs and toppled trees, mainly in the Cedar Key area, where a total of $100,000 dollars was estimated._x000D_ _x000D_ Damage in Citrus county was confined to a few downed trees, power lines and snapped branches from Sulphur Springs south to Ozello mounting to less than $25,000 dollars._x000D_ _x000D_ Damage in Hernando county was confined to ten homes that suffered floodwater damage along the coast along with a few toppled trees and downed power lines. Damage in Hernando county was estimated at $100,000 dollars._x000D_ _x000D_ Damage in Pasco county was confined to 15 roof damaged villas, downed trees and damaged vehicles in the New Port Colony Villas subdivsion in New Port Richey estimated at $250,000 dollars._x000D_ _x000D_ In Pinellas county, 51 single-family homes, 32 mobile homes, 27 multi-family homes and 24 businesses sustained minor wind or water damage. Estimated cost of the damage in Pinellas county was nearly $500,000 dollars._x000D_ _x000D_ In Hillsborough county, 40 homes in low lying coastal areas from Ruskin to Gibsonton to Riverview, incurred flooding from storm surge. Also, several homes were damaged from wind toppled trees and large branches throughout Hillsborough county. Estimated cost of the damage in Hillsborough county was near $500,000 dollars._x000D_ _x000D_ In Manatee county, 25 homes and businesses were flooded in Bradenton Beach and several homes incurred minor to moderate roof damage in Anna Maria. At Coquina Beach in Manatee county, 60 mph wind gusts, associated with an outer feeder band of Gordon, toppled life guard towers and destroyed an anemometer. Property damage from Hurricane Gordon was estimated at nearly $500,000 dollars in Manatee county._x000D_ _x000D_ In Sarasota county, eight foot high waves, caused nearly $600,000 in property damage to the Venice Municipal Fishing Pier. The hurricane induced waves ripped a 20 foot section and three 50 foot concrete pilings from the northern section of the pier._x000D_ _x000D_ In Lee county, tropical storm force winds caused roof, awning and lanai damage to nine homes, toppled several large trees and branches, and downed power lines across Cape Coral and Ft. Myers. Also, tornadoes, associated with outer feeder bands of Hurricane Gordon, caused significant damage on Sanibel Island of extreme western Lee county (see Lee county tornado entries)._x000D_ _x000D_ Max Wind Gust: 68 mph - Cedar Key, Levy Co. 2153 EST 09/17_x000D_ Lowest Pressure: 994.2 mb - Cedar Key, Levy Co. 2200 EST 09/17_x000D_ Max Rainfall: 6.39 in - Page Field, Ft. Myers, Lee Co. 0000-2400 EST 09/17 | AR56: 139
... A59: 5157587 | B59: SARASOTA (ZONE) | C59: =_xlfn.XLOOKUP(B59,Match!$A$2:$A$111,Match!$B$2:$B$111) -> Sarasota, FL | D59: =_xlfn.XLOOKUP(C59,Validation!$B$2:$B$68,Validation!$A$2:$A$68) -> 12115 | F59: 36786 | G59: 500 | H59: Hurricane (Typhoon) | K59: 0 | L59: 0 | M59: 1800000 | N59: 0 | O59: FL | P59: EST | R59: 1104015 | S59: Z | T59: 60 | U59: TBW | V59: 0 | W59: 0 | X59: AWOS | Y59: ASOS | Z59: MESONET | AA59: ETC | AJ59: 36786 | AK59: 1600 | AQ59: Hurricane Gordon moved northeast across the eastern Gulf of Mexico and brought mainly 30 to 40 mph sustained winds and 50 to nearly 70 mph tropical storm force wind gusts to mainly coastal areas of Southwest and West Central Florida throughout the daylight hours of the 17th. Gordon's ill-defined center made landfall near the Suwannee River around midnight of the 18th. Official, maximum sustained winds of 53 mph, with gusts as high as 68 mph, were observed at the C-MAN automated weather sensor at Cedar Key in Levy county prior to landfall near the mouth of the Suwannee River during the late evening of the 17th._x000D_ _x000D_ Hurricane Gordon produced maximum storm tides above mean sea level of 2 to 4 feet from Lee north to Manatee county, 4 to 5.5 feet along the Pinellas and Hillsborough county coastlines, and 2 to 4 feet from Pasco north to Levy county on the 17th._x000D_ _x000D_ Coastal flooding from storm surge was minimal from Lee county north to the Tampa metropolitan area. Near downtown Tampa, a foot of water covered the south and northern lanes of Bayshore Boulevard during midday on the 17th. Coastal flood waters between one and two feet covered coastal roads along Longboat Key in Manatee county and Siesta and Casey Keys in Sarasota county. In Pinellas county, nearly a foot of water covered coastal roads from St. Pete Beach to Clearwater. The Courtney Campbell Parkway, seperating Pinellas and Hillsborough counties, was closed, due to storm surge flooding, from nearly 5 to 9 pm on the 17th._x000D_ _x000D_ Beach erosion was minor from Lee north to Charlotte, moderate to severe along Sarasota and Manatee counties, minor to moderate over Manatee, Pinellas, Pasco and Hernando counties. At Bradenton Beach in Manatee county, nearly 100 feet of pristine beach, five to six feet in depth, was stripped away by wave action from Hurricane Gordon. In Sarasota county, storm surge and wave action from Gordon caused nearly 1.1 million dollars in beach erosion while in Manatee county, beach erosion was estimated at 500 thousand dollars._x000D_ _x000D_ Inland flooding from rainfall occurred over low-lying and urban areas in mainly Lee, Charlotte, Sarasota, Manatee, Hardee, DeSoto, Highlands and southern Polk counties (see flood entries)._x000D_ _x000D_ Eastern rain bands of Hurricane Gordon spawned at least five known tornadoes, two F1's and three F0's over Central and Southwest Florida (see tornado entries)._x000D_ _x000D_ Damage in Levy county was confined to roofs and toppled trees, mainly in the Cedar Key area, where a total of $100,000 dollars was estimated._x000D_ _x000D_ Damage in Citrus county was confined to a few downed trees, power lines and snapped branches from Sulphur Springs south to Ozello mounting to less than $25,000 dollars._x000D_ _x000D_ Damage in Hernando county was confined to ten homes that suffered floodwater damage along the coast along with a few toppled trees and downed power lines. Damage in Hernando county was estimated at $100,000 dollars._x000D_ _x000D_ Damage in Pasco county was confined to 15 roof damaged villas, downed trees and damaged vehicles in the New Port Colony Villas subdivsion in New Port Richey estimated at $250,000 dollars._x000D_ _x000D_ In Pinellas county, 51 single-family homes, 32 mobile homes, 27 multi-family homes and 24 businesses sustained minor wind or water damage. Estimated cost of the damage in Pinellas county was nearly $500,000 dollars._x000D_ _x000D_ In Hillsborough county, 40 homes in low lying coastal areas from Ruskin to Gibsonton to Riverview, incurred flooding from storm surge. Also, several homes were damaged from wind toppled trees and large branches throughout Hillsborough county. Estimated cost of the damage in Hillsborough county was near $500,000 dollars._x000D_ _x000D_ In Manatee county, 25 homes and businesses were flooded in Bradenton Beach and several homes incurred minor to moderate roof damage in Anna Maria. At Coquina Beach in Manatee county, 60 mph wind gusts, associated with an outer feeder band of Gordon, toppled life guard towers and destroyed an anemometer. Property damage from Hurricane Gordon was estimated at nearly $500,000 dollars in Manatee county._x000D_ _x000D_ In Sarasota county, eight foot high waves, caused nearly $600,000 in property damage to the Venice Municipal Fishing Pier. The hurricane induced waves ripped a 20 foot section and three 50 foot concrete pilings from the northern section of the pier._x000D_ _x000D_ In Lee county, tropical storm force winds caused roof, awning and lanai damage to nine homes, toppled several large trees and branches, and downed power lines across Cape Coral and Ft. Myers. Also, tornadoes, associated with outer feeder bands of Hurricane Gordon, caused significant damage on Sanibel Island of extreme western Lee county (see Lee county tornado entries)._x000D_ _x000D_ Max Wind Gust: 68 mph - Cedar Key, Levy Co. 2153 EST 09/17_x000D_ Lowest Pressure: 994.2 mb - Cedar Key, Levy Co. 2200 EST 09/17_x000D_ Max Rainfall: 6.39 in - Page Field, Ft. Myers, Lee Co. 0000-2400 EST 09/17 | AR59: 142
A60: 5158515 | B60: DIXIE (ZONE) | C60: =_xlfn.XLOOKUP(B60,Match!$A$2:$A$111,Match!$B$2:$B$111) -> Dixie, FL | D60: =_xlfn.XLOOKUP(C60,Validation!$B$2:$B$68,Validation!$A$2:$A$68) -> 12029 | F60: 36786 | G60: 800 | H60: Hurricane (Typhoon) | K60: 0 | L60: 0 | M60: 0 | N60: 0 | O60: FL | P60: EST | R60: 1103646 | S60: Z | T60: 34 | U60: TAE | V60: 0 | W60: 0 | X60: EMERGENCY MANAGER | AG60: 36787 | AH60: 800 | AO60: 143
A61: 5158516 | B61: FRANKLIN (ZONE) | C61: =_xlfn.XLOOKUP(B61,Match!$A$2:$A$111,Match!$B$2:$B$111) -> Franklin, FL | D61: =_xlfn.XLOOKUP(C61,Validation!$B$2:$B$68,Validation!$A$2:$A$68) -> 12037 | F61: 36786 | G61: 800 | H61: Hurricane (Typhoon) | K61: 0 | L61: 0 | M61: 0 | N61: 0 | O61: FL | P61: EST | R61: 1103646 | S61: Z | T61: 15 | U61: TAE | V61: 0 | W61: 0 | X61: EMERGENCY MANAGER | AG61: 36787 | AH61: 800 | AM61: Hurricane Gordon, a minimal Category 1 storm, weakened to a tropical storm just prior to landfall near Cedar Key, Florida during the late evening hours of Sunday, September, 17, 2000. Heavy rainfall associated with Gordon's outer bands began to affect mainly eastern portions of the Florida Big Bend as early as Sunday morning. Storm total rainfall varied from 0.71 inches at Tallahassee to 4.83 inches at Cross City, Florida. The highest sustained wind recorded was 33 mph with a peak gust of 42 mph at Cross City. The lowest sea-level pressure recorded was 997 mb at Cross City. There were no reports of beach erosion, flooding or tornadoes. | AO61: 144
A62: 5158517 | B62: GADSDEN (ZONE) | C62: =_xlfn.XLOOKUP(B62,Match!$A$2:$A$111,Match!$B$2:$B$111) -> Gadsden, FL | D62: =_xlfn.XLOOKUP(C62,Validation!$B$2:$B$68,Validation!$A$2:$A$68) -> 12039 | F62: 36786 | G62: 800 | H62: Hurricane (Typhoon) | K62: 0 | L62: 0 | M62: 0 | N62: 0 | O62: FL | P62: EST | R62: 1103646 | S62: Z | T62: 16 | U62: TAE | V62: 0 | W62: 0 | X62: EMERGENCY MANAGER | AG62: 36787 | AH62: 800 | AO62: 145
A63: 5158518 | B63: JEFFERSON (ZONE) | C63: =_xlfn.XLOOKUP(B63,Match!$A$2:$A$111,Match!$B$2:$B$111) -> Jefferson, FL | D63: =_xlfn.XLOOKUP(C63,Validation!$B$2:$B$68,Validation!$A$2:$A$68) -> 12065 | F63: 36786 | G63: 800 | H63: Hurricane (Typhoon) | K63: 0 | L63: 0 | M63: 0 | N63: 0 | O63: FL | P63: EST | R63: 1103646 | S63: Z | T63: 18 | U63: TAE | V63: 0 | W63: 0 | X63: EMERGENCY MANAGER | AG63: 36787 | AH63: 800 | AO63: 146
A64: 5158519 | B64: LAFAYETTE (ZONE) | C64: =_xlfn.XLOOKUP(B64,Match!$A$2:$A$111,Match!$B$2:$B$111) -> Lafayette, FL | D64: =_xlfn.XLOOKUP(C64,Validation!$B$2:$B$68,Validation!$A$2:$A$68) -> 12067 | F64: 36786 | G64: 800 | H64: Hurricane (Typhoon) | K64: 0 | L64: 0 | M64: 0 | N64: 0 | O64: FL | P64: EST | R64: 1103646 | S64: Z | T64: 29 | U64: TAE | V64: 0 | W64: 0 | X64: EMERGENCY MANAGER | AG64: 36787 | AH64: 800 | AO64: 147
A65: 5158520 | B65: LEON (ZONE) | C65: =_xlfn.XLOOKUP(B65,Match!$A$2:$A$111,Match!$B$2:$B$111) -> Leon, FL | D65: =_xlfn.XLOOKUP(C65,Validation!$B$2:$B$68,Validation!$A$2:$A$68) -> 12073 | F65: 36786 | G65: 800 | H65: Hurricane (Typhoon) | K65: 0 | L65: 0 | M65: 0 | N65: 0 | O65: FL | P65: EST | R65: 1103646 | S65: Z | T65: 17 | U65: TAE | V65: 0 | W65: 0 | X65: EMERGENCY MANAGER | AG65: 36787 | AH65: 800 | AO65: 148
A66: 5158521 | B66: LIBERTY (ZONE) | C66: =_xlfn.XLOOKUP(B66,Match!$A$2:$A$111,Match!$B$2:$B$111) -> Liberty, FL | D66: =_xlfn.XLOOKUP(C66,Validation!$B$2:$B$68,Validation!$A$2:$A$68) -> 12077 | F66: 36786 | G66: 800 | H66: Hurricane (Typhoon) | K66: 0 | L66: 0 | M66: 0 | N66: 0 | O66: FL | P66: EST | R66: 1103646 | S66: Z | T66: 26 | U66: TAE | V66: 0 | W66: 0 | X66: EMERGENCY MANAGER | AG66: 36787 | AH66: 800 | AO66: 149
A67: 5158868 | B67: MADISON (ZONE) | C67: =_xlfn.XLOOKUP(B67,Match!$A$2:$A$111,Match!$B$2:$B$111) -> Madison, FL | D67: =_xlfn.XLOOKUP(C67,Validation!$B$2:$B$68,Validation!$A$2:$A$68) -> 12079 | F67: 36786 | G67: 800 | H67: Hurricane (Typhoon) | K67: 0 | L67: 0 | M67: 0 | N67: 0 | O67: FL | P67: EST | R67: 1103646 | S67: Z | T67: 19 | U67: TAE | V67: 0 | W67: 0 | X67: EMERGENCY MANAGER | AG67: 36787 | AH67: 800 | AO67: 150
A68: 5158869 | B68: TAYLOR (ZONE) | C68: =_xlfn.XLOOKUP(B68,Match!$A$2:$A$111,Match!$B$2:$B$111) -> Taylor, FL | D68: =_xlfn.XLOOKUP(C68,Validation!$B$2:$B$68,Validation!$A$2:$A$68) -> 12123 | F68: 36786 | G68: 800 | H68: Hurricane (Typhoon) | K68: 0 | L68: 0 | M68: 0 | N68: 0 | O68: FL | P68: EST | R68: 1103646 | S68: Z | T68: 28 | U68: TAE | V68: 0 | W68: 0 | X68: EMERGENCY MANAGER | AG68: 36787 | AH68: 800 | AO68: 151
A69: 5158870 | B69: WAKULLA (ZONE) | C69: =_xlfn.XLOOKUP(B69,Match!$A$2:$A$111,Match!$B$2:$B$111) -> Wakulla, FL | D69: =_xlfn.XLOOKUP(C69,Validation!$B$2:$B$68,Validation!$A$2:$A$68) -> 12129 | F69: 36786 | G69: 800 | H69: Hurricane (Typhoon) | K69: 0 | L69: 0 | M69: 0 | N69: 0 | O69: FL | P69: EST | R69: 1103646 | S69: Z | T69: 27 | U69: TAE | V69: 0 | W69: 0 | X69: EMERGENCY MANAGER | AG69: 36787 | AH69: 800 | AO69: 152
A70: 5272138 | B70: MONROE/UPPER KEYS (ZONE) | C70: =_xlfn.XLOOKUP(B70,Match!$A$2:$A$111,Match!$B$2:$B$111) -> Monroe, FL | D70: =_xlfn.XLOOKUP(C70,Validation!$B$2:$B$68,Validation!$A$2:$A$68) -> 12087 | F70: 37199 | G70: 1900 | H70: Hurricane (Typhoon) | K70: 0 | L70: 0 | M70: 0 | N70: 0 | O70: FL | P70: EST | R70: 1124515 | S70: Z | T70: 76 | U70: EYW | V70: 0 | W70: 0 | X70: COASTAL OBSERVING STATION | AG70: 37199 | AH70: 1901 | AN70: Hurricane Michelle passed about 60 miles south of the Florida Keys on the 4th and 5th. Only minimal damage occurred in the Keys. The listings are for sustained and maximum wind gusts observed over coastal observing stations. The 3 events listed are the only observations of sustained winds greater than 33 knots._x000D_ _x000D_ Location maximum sustained (direction) maximum gust (direction) time_x000D_ Sombrero Key C-MAN station: 43 knots (060) 50 knots (060) 0300 EST (5th)_x000D_ (Middle Keys)_x000D_ Sand Key C-MAN station 42 knots (050) 47 knots (050) 0000 EST (5th)_x000D_ (Lower Keys)_x000D_ Molasses Reef C-MAN station: 39 knots (060) 49 knots (060) 1900 EST (4th) _x000D_ (Upper Keys) | AO70: 153
A71: 5272137 | B71: MONROE/LOWER KEYS (ZONE) | C71: =_xlfn.XLOOKUP(B71,Match!$A$2:$A$111,Match!$B$2:$B$111) -> Monroe, FL | D71: =_xlfn.XLOOKUP(C71,Validation!$B$2:$B$68,Validation!$A$2:$A$68) -> 12087 | F71: 37200 | G71: 0 | H71: Hurricane (Typhoon) | K71: 0 | L71: 0 | M71: 0 | N71: 0 | O71: FL | P71: EST | R71: 1124515 | S71: Z | T71: 78 | U71: EYW | V71: 0 | W71: 0 | X71: COASTAL OBSERVING STATION | AG71: 37200 | AH71: 1 | AN71: Hurricane Michelle passed about 60 miles south of the Florida Keys on the 4th and 5th. Only minimal damage occurred in the Keys. The listings are for sustained and maximum wind gusts observed over coastal observing stations. The 3 events listed are the only observations of sustained winds greater than 33 knots._x000D_ _x000D_ Location maximum sustained (direction) maximum gust (direction) time_x000D_ Sombrero Key C-MAN station: 43 knots (060) 50 knots (060) 0300 EST (5th)_x000D_ (Middle Keys)_x000D_ Sand Key C-MAN station 42 knots (050) 47 knots (050) 0000 EST (5th)_x000D_ (Lower Keys)_x000D_ Molasses Reef C-MAN station: 39 knots (060) 49 knots (060) 1900 EST (4th) _x000D_ (Upper Keys) | AO71: 154
A72: 5272141 | B72: COASTAL DADE (ZONE) | C72: =_xlfn.XLOOKUP(B72,Match!$A$2:$A$111,Match!$B$2:$B$111) -> Miami-Dade, FL | D72: =_xlfn.XLOOKUP(C72,Validation!$B$2:$B$68,Validation!$A$2:$A$68) -> 12086 | F72: 37200 | G72: 200 | H72: Hurricane (Typhoon) | K72: 0 | L72: 0 | M72: 10000 | N72: 0 | O72: FL | P72: EST | R72: 1124518 | S72: Z | T72: 74 | U72: MFL | V72: 0 | W72: 0 | X72: NEWSPAPER | AG72: 37200 | AH72: 1200 | AN72: Hurricane Michelle after forming into a depression in the southwest Caribbean Sea on October 29 drifted north and became a tropical storm on October 31 and a hurricane on November 2. It turned northeast and made landfall along the south shore of Cuba as a category 4 hurricane on the Saffir-Simpson Hurricane Scale. Michelle weakened as it moved across Cuba and into the central Bahamas. The center reached its closest approach to southeast Florida, about 170 miles southeast of Miami, around 4 am November 5. Tropical storm warnings were issued for southeast Florida at 10 pm, November 3. The minimum pressure and maximum winds along the southeast Florida coast occurred at Miami Beach with a barometer reading of 1001.2 mb and sustained winds of 37 knots with gusts of 44 knots. Fowey Rocks Light, just south of Key Biscayne, reported a peak gust of 53 knots. Storm surge was estimated to be 1-2 feet while rainfall amounts of 1 to 2 inches were widespread across the southeast Florida mainland. Two brief tornadoes were spawned by Michelle causing minor damage. | AO72: 155
A73: 5272136 | B73: MONROE/MIDDLE KEYS (ZONE) | C73: =_xlfn.XLOOKUP(B73,Match!$A$2:$A$111,Match!$B$2:$B$111) -> Monroe, FL | D73: =_xlfn.XLOOKUP(C73,Validation!$B$2:$B$68,Validation!$A$2:$A$68) -> 12087 | F73: 37200 | G73: 300 | H73: Hurricane (Typhoon) | K73: 0 | L73: 0 | M73: 0 | N73: 0 | O73: FL | P73: EST | R73: 1124515 | S73: Z | T73: 77 | U73: EYW | V73: 0 | W73: 0 | X73: COASTAL OBSERVING STATION | AG73: 37200 | AH73: 301 | AN73: Hurricane Michelle passed about 60 miles south of the Florida Keys on the 4th and 5th. Only minimal damage occurred in the Keys. The listings are for sustained and maximum wind gusts observed over coastal observing stations. The 3 events listed are the only observations of sustained winds greater than 33 knots._x000D_ _x000D_ Location maximum sustained (direction) maximum gust (direction) time_x000D_ Sombrero Key C-MAN station: 43 knots (060) 50 knots (060) 0300 EST (5th)_x000D_ (Middle Keys)_x000D_ Sand Key C-MAN station 42 knots (050) 47 knots (050) 0000 EST (5th)_x000D_ (Lower Keys)_x000D_ Molasses Reef C-MAN station: 39 knots (060) 49 knots (060) 1900 EST (4th) _x000D_ (Upper Keys) | AO73: 156
A74: 5272142 | B74: COASTAL BROWARD (ZONE) | C74: =_xlfn.XLOOKUP(B74,Match!$A$2:$A$111,Match!$B$2:$B$111) -> Broward, FL | D74: =_xlfn.XLOOKUP(C74,Validation!$B$2:$B$68,Validation!$A$2:$A$68) -> 12011 | F74: 37200 | G74: 300 | H74: Hurricane (Typhoon) | K74: 0 | L74: 0 | M74: 30000 | N74: 0 | O74: FL | P74: EST | R74: 1124518 | S74: Z | T74: 72 | U74: MFL | V74: 0 | W74: 0 | X74: NEWSPAPER | AG74: 37200 | AH74: 1200 | AN74: Hurricane Michelle after forming into a depression in the southwest Caribbean Sea on October 29 drifted north and became a tropical storm on October 31 and a hurricane on November 2. It turned northeast and made landfall along the south shore of Cuba as a category 4 hurricane on the Saffir-Simpson Hurricane Scale. Michelle weakened as it moved across Cuba and into the central Bahamas. The center reached its closest approach to southeast Florida, about 170 miles southeast of Miami, around 4 am November 5. Tropical storm warnings were issued for southeast Florida at 10 pm, November 3. The minimum pressure and maximum winds along the southeast Florida coast occurred at Miami Beach with a barometer reading of 1001.2 mb and sustained winds of 37 knots with gusts of 44 knots. Fowey Rocks Light, just south of Key Biscayne, reported a peak gust of 53 knots. Storm surge was estimated to be 1-2 feet while rainfall amounts of 1 to 2 inches were widespread across the southeast Florida mainland. Two brief tornadoes were spawned by Michelle causing minor damage. | AO74: 157
A75: 5272143 | B75: COASTAL PALM BEACH (ZONE) | C75: =_xlfn.XLOOKUP(B75,Match!$A$2:$A$111,Match!$B$2:$B$111) -> Palm Beach, FL | D75: =_xlfn.XLOOKUP(C75,Validation!$B$2:$B$68,Validation!$A$2:$A$68) -> 12099 | F75: 37200 | G75: 400 | H75: Hurricane (Typhoon) | K75: 0 | L75: 0 | M75: 10000 | N75: 0 | O75: FL | P75: EST | R75: 1124518 | S75: Z | T75: 68 | U75: MFL | V75: 0 | W75: 0 | X75: NEWSPAPER | AG75: 37200 | AH75: 1200 | AN75: Hurricane Michelle after forming into a depression in the southwest Caribbean Sea on October 29 drifted north and became a tropical storm on October 31 and a hurricane on November 2. It turned northeast and made landfall along the south shore of Cuba as a category 4 hurricane on the Saffir-Simpson Hurricane Scale. Michelle weakened as it moved across Cuba and into the central Bahamas. The center reached its closest approach to southeast Florida, about 170 miles southeast of Miami, around 4 am November 5. Tropical storm warnings were issued for southeast Florida at 10 pm, November 3. The minimum pressure and maximum winds along the southeast Florida coast occurred at Miami Beach with a barometer reading of 1001.2 mb and sustained winds of 37 knots with gusts of 44 knots. Fowey Rocks Light, just south of Key Biscayne, reported a peak gust of 53 knots. Storm surge was estimated to be 1-2 feet while rainfall amounts of 1 to 2 inches were widespread across the southeast Florida mainland. Two brief tornadoes were spawned by Michelle causing minor damage. | AO75: 158
A76: 5421070 | B76: MONROE/LOWER KEYS (ZONE) | C76: =_xlfn.XLOOKUP(B76,Match!$A$2:$A$111,Match!$B$2:$B$111) -> Monroe, FL | D76: =_xlfn.XLOOKUP(C76,Validation!$B$2:$B$68,Validation!$A$2:$A$68) -> 12087 | F76: 38210 | G76: 400 | H76: Hurricane (Typhoon) | K76: 0 | L76: 0 | M76: 150000 | N76: 0 | O76: FL | P76: EST | R76: 1179334 | S76: Z | T76: 78 | U76: EYW | V76: 0 | W76: 0 | X76: NWS STORM SURVEY | AG76: 38212 | AH76: 1600 | AN76: Hurricane Charley moved north from western Cuba, passing directly over Dry Tortugas National Park around 0700 EST on August 13, 2004. During the evening of August 12, a strong convective band moved north through the Florida Straits, the Keys east of the Seven Mile Bridge, and into Florida Bay. Peak wind gusts to 56 knots (64 mph) were recorded at Sombrero Key Light, 53 knots (61 mph) at Long Key and 47 knots (54 mph) at Molasses Reef C-MAN stations during this convective band, along with reported wind gust to 45 knots (52 mph) from a spotter on Duck Key. Damage along the island chain from Marathon through Ocean Reef was limited to downed tree limbs, power lines and unreinforced signs, and almost entirely from the convective band. Beginning around 0330 EST, strong gradient winds began in the Lower Keys and Dry Tortugas. Peak wind gusts of 54 knots (62 mph) were recorded at Sand Key C-MAN station, with gusts to 50 knots (58 mph) at Key West International Airport. Peak wind measurements of 40 to 45 knots (46 to 52 mph) were measured along the island chain from Boca Chica Key through Summerland Key. Wind damage including a few uprooted and snapped trees, large tree limbs, power lines, fences and unreinforced signs. A sailboat broke loose from moorings around 0730 EST on August 13, striking a phase of a 115 kilovolt transmission line serving the lower Keys, causing a widespread power outage west of Marathon through Key West._x000D_ _x000D_ Maximum storm surge was estimated to near 6 feet at Dry Tortugas/Garden Key by National Park Service personnel, who rode out the hurricane at the fort. Wave action produced extensive flooding of the park grounds outside of the Fort Jefferson walls. Approximately 1000 feet of brickwork was lost on the outer moat wall, which was completely submerged at the time of high tide. Numerous finger docks and the deck of the main dock were destroyed. Scaffolding used during the Fort's multi-year renovation project was also damaged and found floating in the moat. The Dry Tortugas C-MAN station, which included instrumentation less than 15 feet above mean sea level, was also destroyed, likely from the combination of wave action and elevated tide levels. Maximum storm surge was estimated at one foot above normal at Key West. Wave action produced minor coastal flooding along the oceanfront. _x000D_ _x000D_ An estimated 11,000 visitors evacuated the Keys, causing an estimated tourism loss of 5.3 million dollars. | AO76: 159
A77: 5421072 | B77: MONROE/UPPER KEYS (ZONE) | C77: =_xlfn.XLOOKUP(B77,Match!$A$2:$A$111,Match!$B$2:$B$111) -> Monroe, FL | D77: =_xlfn.XLOOKUP(C77,Validation!$B$2:$B$68,Validation!$A$2:$A$68) -> 12087 | F77: 38210 | G77: 400 | H77: Hurricane (Typhoon) | K77: 0 | L77: 0 | M77: 5000 | N77: 0 | O77: FL | P77: EST | R77: 1179334 | S77: Z | T77: 76 | U77: EYW | V77: 0 | W77: 0 | X77: NWS STORM SURVEY | AG77: 38212 | AH77: 1600 | AN77: Hurricane Charley moved north from western Cuba, passing directly over Dry Tortugas National Park around 0700 EST on August 13, 2004. During the evening of August 12, a strong convective band moved north through the Florida Straits, the Keys east of the Seven Mile Bridge, and into Florida Bay. Peak wind gusts to 56 knots (64 mph) were recorded at Sombrero Key Light, 53 knots (61 mph) at Long Key and 47 knots (54 mph) at Molasses Reef C-MAN stations during this convective band, along with reported wind gust to 45 knots (52 mph) from a spotter on Duck Key. Damage along the island chain from Marathon through Ocean Reef was limited to downed tree limbs, power lines and unreinforced signs, and almost entirely from the convective band. Beginning around 0330 EST, strong gradient winds began in the Lower Keys and Dry Tortugas. Peak wind gusts of 54 knots (62 mph) were recorded at Sand Key C-MAN station, with gusts to 50 knots (58 mph) at Key West International Airport. Peak wind measurements of 40 to 45 knots (46 to 52 mph) were measured along the island chain from Boca Chica Key through Summerland Key. Wind damage including a few uprooted and snapped trees, large tree limbs, power lines, fences and unreinforced signs. A sailboat broke loose from moorings around 0730 EST on August 13, striking a phase of a 115 kilovolt transmission line serving the lower Keys, causing a widespread power outage west of Marathon through Key West._x000D_ _x000D_ Maximum storm surge was estimated to near 6 feet at Dry Tortugas/Garden Key by National Park Service personnel, who rode out the hurricane at the fort. Wave action produced extensive flooding of the park grounds outside of the Fort Jefferson walls. Approximately 1000 feet of brickwork was lost on the outer moat wall, which was completely submerged at the time of high tide. Numerous finger docks and the deck of the main dock were destroyed. Scaffolding used during the Fort's multi-year renovation project was also damaged and found floating in the moat. The Dry Tortugas C-MAN station, which included instrumentation less than 15 feet above mean sea level, was also destroyed, likely from the combination of wave action and elevated tide levels. Maximum storm surge was estimated at one foot above normal at Key West. Wave action produced minor coastal flooding along the oceanfront. _x000D_ _x000D_ An estimated 11,000 visitors evacuated the Keys, causing an estimated tourism loss of 5.3 million dollars. | AO77: 160
A78: 5421071 | B78: MONROE/MIDDLE KEYS (ZONE) | C78: =_xlfn.XLOOKUP(B78,Match!$A$2:$A$111,Match!$B$2:$B$111) -> Monroe, FL | D78: =_xlfn.XLOOKUP(C78,Validation!$B$2:$B$68,Validation!$A$2:$A$68) -> 12087 | F78: 38210 | G78: 400 | H78: Hurricane (Typhoon) | K78: 0 | L78: 0 | M78: 5000 | N78: 0 | O78: FL | P78: EST | R78: 1179334 | S78: Z | T78: 77 | U78: EYW | V78: 0 | W78: 0 | X78: NWS STORM SURVEY | AG78: 38212 | AH78: 1600 | AN78: Hurricane Charley moved north from western Cuba, passing directly over Dry Tortugas National Park around 0700 EST on August 13, 2004. During the evening of August 12, a strong convective band moved north through the Florida Straits, the Keys east of the Seven Mile Bridge, and into Florida Bay. Peak wind gusts to 56 knots (64 mph) were recorded at Sombrero Key Light, 53 knots (61 mph) at Long Key and 47 knots (54 mph) at Molasses Reef C-MAN stations during this convective band, along with reported wind gust to 45 knots (52 mph) from a spotter on Duck Key. Damage along the island chain from Marathon through Ocean Reef was limited to downed tree limbs, power lines and unreinforced signs, and almost entirely from the convective band. Beginning around 0330 EST, strong gradient winds began in the Lower Keys and Dry Tortugas. Peak wind gusts of 54 knots (62 mph) were recorded at Sand Key C-MAN station, with gusts to 50 knots (58 mph) at Key West International Airport. Peak wind measurements of 40 to 45 knots (46 to 52 mph) were measured along the island chain from Boca Chica Key through Summerland Key. Wind damage including a few uprooted and snapped trees, large tree limbs, power lines, fences and unreinforced signs. A sailboat broke loose from moorings around 0730 EST on August 13, striking a phase of a 115 kilovolt transmission line serving the lower Keys, causing a widespread power outage west of Marathon through Key West._x000D_ _x000D_ Maximum storm surge was estimated to near 6 feet at Dry Tortugas/Garden Key by National Park Service personnel, who rode out the hurricane at the fort. Wave action produced extensive flooding of the park grounds outside of the Fort Jefferson walls. Approximately 1000 feet of brickwork was lost on the outer moat wall, which was completely submerged at the time of high tide. Numerous finger docks and the deck of the main dock were destroyed. Scaffolding used during the Fort's multi-year renovation project was also damaged and found floating in the moat. The Dry Tortugas C-MAN station, which included instrumentation less than 15 feet above mean sea level, was also destroyed, likely from the combination of wave action and elevated tide levels. Maximum storm surge was estimated at one foot above normal at Key West. Wave action produced minor coastal flooding along the oceanfront. _x000D_ _x000D_ An estimated 11,000 visitors evacuated the Keys, causing an estimated tourism loss of 5.3 million dollars. | AO78: 161
A79: 5413247 | B79: COASTAL COLLIER (ZONE) | C79: =_xlfn.XLOOKUP(B79,Match!$A$2:$A$111,Match!$B$2:$B$111) -> Collier, FL | D79: =_xlfn.XLOOKUP(C79,Validation!$B$2:$B$68,Validation!$A$2:$A$68) -> 12021 | F79: 38212 | G79: 0 | H79: Hurricane (Typhoon) | K79: 0 | L79: 0 | M79: 2500000 | N79: 0 | O79: FL | P79: EST | R79: 1175921 | S79: Z | T79: 69 | U79: MFL | V79: 0 | W79: 0 | X79: EMERGENCY MANAGER | AG79: 38212 | AH79: 2200 | AN79: On August 12, Hurricane Charley, after moving through the northwest Caribbean Sea, turned north and accelerated cross the western end of Cuba, and just west of the lower Florida Keys. Early on August 13, the hurricane intensified to Category 4 status and turned to a north northeast direction before making landfall near Port Charlotte around 3 PM EDT. The first outer rainband, with wind gusts estimated up to 60 mph, impacted the south Florida Peninsula between midnight and 2 AM EDT _x000D_ _x000D_ In Collier County, a peak wind gust of 84 mph was measured at 2:50 PM EDT on the top of a condominium at Vanderbilt Beach before the equipment failed. The Naples ASOS equipment failed well before the maximum winds or minimum pressure occurred. Wind gusts at La Belle were estimated at 80 mph._x000D_ _x000D_ Rainfall in most locations in Collier County was around two inches with an unofficial amount of 7.5 inches reported in North Naples. Radar rainfall estimates of locally 8 to 10 inches were made in North Naples. Flooding was mostly minimal. _x000D_ _x000D_ The highest Storm Tide along the southwest Florida Coast was estimated at three feet near Wiggins Pass with heights of one to two feet from Naples to Marco Island to Everglades City. Tidal flooding was minimal. Lake Okeechobee levels increased up to three feet above normal along the north and northeast shores._x000D_ _x000D_ A long-track tornado moved through the open country of the Everglades in eastern Hendry County before doing minor damage to buildings in Clewiston._x000D_ _x000D_ Hurricane wind damage was greatest in North Naples and Vanderbilt Beach with numerous power poles, trees and signs blown down, and a few roofs damaged. Damage also occurred to screened porches throughout the Naples-Marco Island metropolitan areas. Damage occurred to Gulf-side structures along most of the coastline but beach erosion was mostly minor. Four persons in Naples suffered minor injuries when their vehicle was touched by a downed power line during the storm. Three persons in Collier County died from indirect causes after the hurricane. An estimated 130,000 customers in Collier County lost power. About 2,500 people took refuge in six shelters._x000D_ _x000D_ Damage in Hendry and Glades counties consisted mainly of downed trees, power lines and signs, with minor roof damage to several homes. An estimated 1000 customers lost electricity in Glades County. | AO79: 162
A80: 5413248 | B80: HENDRY (ZONE) | C80: =_xlfn.XLOOKUP(B80,Match!$A$2:$A$111,Match!$B$2:$B$111) -> Hendry, FL | D80: =_xlfn.XLOOKUP(C80,Validation!$B$2:$B$68,Validation!$A$2:$A$68) -> 12051 | F80: 38212 | G80: 100 | H80: Hurricane (Typhoon) | K80: 0 | L80: 0 | M80: 50000 | N80: 0 | O80: FL | P80: EST | R80: 1175921 | S80: Z | T80: 66 | U80: MFL | V80: 0 | W80: 0 | X80: EMERGENCY MANAGER | AG80: 38212 | AH80: 2300 | AN80: On August 12, Hurricane Charley, after moving through the northwest Caribbean Sea, turned north and accelerated cross the western end of Cuba, and just west of the lower Florida Keys. Early on August 13, the hurricane intensified to Category 4 status and turned to a north northeast direction before making landfall near Port Charlotte around 3 PM EDT. The first outer rainband, with wind gusts estimated up to 60 mph, impacted the south Florida Peninsula between midnight and 2 AM EDT _x000D_ _x000D_ In Collier County, a peak wind gust of 84 mph was measured at 2:50 PM EDT on the top of a condominium at Vanderbilt Beach before the equipment failed. The Naples ASOS equipment failed well before the maximum winds or minimum pressure occurred. Wind gusts at La Belle were estimated at 80 mph._x000D_ _x000D_ Rainfall in most locations in Collier County was around two inches with an unofficial amount of 7.5 inches reported in North Naples. Radar rainfall estimates of locally 8 to 10 inches were made in North Naples. Flooding was mostly minimal. _x000D_ _x000D_ The highest Storm Tide along the southwest Florida Coast was estimated at three feet near Wiggins Pass with heights of one to two feet from Naples to Marco Island to Everglades City. Tidal flooding was minimal. Lake Okeechobee levels increased up to three feet above normal along the north and northeast shores._x000D_ _x000D_ A long-track tornado moved through the open country of the Everglades in eastern Hendry County before doing minor damage to buildings in Clewiston._x000D_ _x000D_ Hurricane wind damage was greatest in North Naples and Vanderbilt Beach with numerous power poles, trees and signs blown down, and a few roofs damaged. Damage also occurred to screened porches throughout the Naples-Marco Island metropolitan areas. Damage occurred to Gulf-side structures along most of the coastline but beach erosion was mostly minor. Four persons in Naples suffered minor injuries when their vehicle was touched by a downed power line during the storm. Three persons in Collier County died from indirect causes after the hurricane. An estimated 130,000 customers in Collier County lost power. About 2,500 people took refuge in six shelters._x000D_ _x000D_ Damage in Hendry and Glades counties consisted mainly of downed trees, power lines and signs, with minor roof damage to several homes. An estimated 1000 customers lost electricity in Glades County. | AO80: 163
A81: 5413249 | B81: GLADES (ZONE) | C81: =_xlfn.XLOOKUP(B81,Match!$A$2:$A$111,Match!$B$2:$B$111) -> Glades, FL | D81: =_xlfn.XLOOKUP(C81,Validation!$B$2:$B$68,Validation!$A$2:$A$68) -> 12043 | F81: 38212 | G81: 200 | H81: Hurricane (Typhoon) | K81: 0 | L81: 0 | M81: 25000 | N81: 0 | O81: FL | P81: EST | R81: 1175921 | S81: Z | T81: 63 | U81: MFL | V81: 0 | W81: 0 | X81: EMERGENCY MANAGER | AG81: 38212 | AH81: 2330 | AN81: On August 12, Hurricane Charley, after moving through the northwest Caribbean Sea, turned north and accelerated cross the western end of Cuba, and just west of the lower Florida Keys. Early on August 13, the hurricane intensified to Category 4 status and turned to a north northeast direction before making landfall near Port Charlotte around 3 PM EDT. The first outer rainband, with wind gusts estimated up to 60 mph, impacted the south Florida Peninsula between midnight and 2 AM EDT _x000D_ _x000D_ In Collier County, a peak wind gust of 84 mph was measured at 2:50 PM EDT on the top of a condominium at Vanderbilt Beach before the equipment failed. The Naples ASOS equipment failed well before the maximum winds or minimum pressure occurred. Wind gusts at La Belle were estimated at 80 mph._x000D_ _x000D_ Rainfall in most locations in Collier County was around two inches with an unofficial amount of 7.5 inches reported in North Naples. Radar rainfall estimates of locally 8 to 10 inches were made in North Naples. Flooding was mostly minimal. _x000D_ _x000D_ The highest Storm Tide along the southwest Florida Coast was estimated at three feet near Wiggins Pass with heights of one to two feet from Naples to Marco Island to Everglades City. Tidal flooding was minimal. Lake Okeechobee levels increased up to three feet above normal along the north and northeast shores._x000D_ _x000D_ A long-track tornado moved through the open country of the Everglades in eastern Hendry County before doing minor damage to buildings in Clewiston._x000D_ _x000D_ Hurricane wind damage was greatest in North Naples and Vanderbilt Beach with numerous power poles, trees and signs blown down, and a few roofs damaged. Damage also occurred to screened porches throughout the Naples-Marco Island metropolitan areas. Damage occurred to Gulf-side structures along most of the coastline but beach erosion was mostly minor. Four persons in Naples suffered minor injuries when their vehicle was touched by a downed power line during the storm. Three persons in Collier County died from indirect causes after the hurricane. An estimated 130,000 customers in Collier County lost power. About 2,500 people took refuge in six shelters._x000D_ _x000D_ Damage in Hendry and Glades counties consisted mainly of downed trees, power lines and signs, with minor roof damage to several homes. An estimated 1000 customers lost electricity in Glades County. | AO81: 164
... A150: 5452811 | B150: COASTAL BROWARD (ZONE) | C150: =_xlfn.XLOOKUP(B150,Match!$A$2:$A$111,Match!$B$2:$B$111) -> Broward, FL | D150: =_xlfn.XLOOKUP(C150,Validation!$B$2:$B$68,Validation!$A$2:$A$68) -> 12011 | F150: 38541 | G150: 1600 | H150: Hurricane (Typhoon) | K150: 1 | L150: 0 | M150: 0 | N150: 0 | O150: FL | P150: EST | R150: 1190954 | S150: Z | T150: 72 | U150: MFL | V150: 0 | W150: 0 | X150: NEWSPAPER | AG150: 38543 | AH150: 1200 | AN150: As Hurricane Dennis moved through the northwest Caribbean Sea and southeast Gulf of Mexico the outer fringes affected south Florida. Several strong squalls moved across the area...mainly from Friday afternoon through Saturday afternoon. Overall damage across south Florida was minor and consisted mostly of uprooted trees or tree limbs blow down causing some damage to structure roofs...vehicles and power lines. FP&L estimated power outages to 463,000 customers. There was one known direct death...a man who drowned on Thursday afternoon in a likely rip current off of Hollywood Beach. An indirect death occurred in Fort Lauderdale when a man was electrocuted after stepping on a downed power line._x000D_ _x000D_ Peak wind gusts at land locations included 69 mph at Miami Beach...68 mph at Flamingo...67 mph at Opa Locka Airport...64 mph at Tamiami Airport...58 mph at North Perry Airport...54 mph at Naples Airport...53 mph at Virginia Key...51 mph at Miami International Airport...50 mph at Pompano Beach Airport and 47 mph at For Lauderdale-Hollywood International Airport. Over water, a peak gust of 84 mph was measured at the C-MAN station at Fowey Rocks Light._x000D_ _x000D_ Mostly minor coastal flooding was observed. Along the southwest Florida coast the maximum storm surge was 2.6 feet with a maximum storm tide of 4.2 feet measured at Naples Pier. Along the southeast Florida Coast the maximum surge was less than one foot._x000D_ _x000D_ Rainfall flooding was mostly minor with official rainfall amounts for the 72 hour period from Friday through Sunday ranging from one to nearly seven inches with an average of two to four inches across much of south Florida. The peak amount was 6.89 inches in Perrine with 5.03 inches in Hollywood and 4.36 inches at Fort Lauderdale. | AO150: 233
A151: 5474035 | B151: MONROE/MIDDLE KEYS (ZONE) | C151: =_xlfn.XLOOKUP(B151,Match!$A$2:$A$111,Match!$B$2:$B$111) -> Monroe, FL | D151: =_xlfn.XLOOKUP(C151,Validation!$B$2:$B$68,Validation!$A$2:$A$68) -> 12087 | F151: 38541 | G151: 2000 | H151: Hurricane (Typhoon) | K151: 0 | L151: 0 | M151: 6800000 | N151: 0 | O151: FL | P151: EST | R151: 1198862 | S151: Z | T151: 77 | U151: EYW | V151: 0 | W151: 0 | X151: NWS STORM SURVEY | AG151: 38542 | AH151: 2200 | AM151: Hurricane Dennis passed within 75 miles southwest of Key West as a category 2 hurricane. Over the Monroe County Lower Keys, maximum winds were sustained at 53 knots (61 mph) with gusts to 64 knots (74 mph) at Key West and 51 knots (59 mph) gusting to 68 knots (78 mph) at Sand Key. Unofficial wind gusts to 93 knots (107 mph) were reported at Cudjoe Key. Maximum storm tides were estimated to 4.5 feet above mean sea level on the Atlantic shore of Key West near the International Airport. One fatality occurred aboard a vessel moored at Stock Island due to drowning. No injuries were reported. Property damage estimated at $6.8M due to wind damage mainly to roofing, electrical equipment, landscaping and mobile homes, with estimated $100K due to combined wind and rain damages to the Key West Airport. Minimum pressure reported was 998.8 mb at Sand Key. | AO151: 234
A152: 5474034 | B152: MONROE/LOWER KEYS (ZONE) | C152: =_xlfn.XLOOKUP(B152,Match!$A$2:$A$111,Match!$B$2:$B$111) -> Monroe, FL | D152: =_xlfn.XLOOKUP(C152,Validation!$B$2:$B$68,Validation!$A$2:$A$68) -> 12087 | F152: 38541 | G152: 2000 | H152: Hurricane (Typhoon) | K152: 1 | L152: 0 | M152: 250000 | N152: 0 | O152: FL | P152: EST | R152: 1198862 | S152: Z | T152: 78 | U152: EYW | V152: 0 | W152: 0 | X152: NWS STORM SURVEY | AG152: 38542 | AH152: 2200 | AM152: Hurricane Dennis passed within 75 miles southwest of Key West as a category 2 hurricane. In the Monroe County Middle Keys, maximum rainfall was 2.00 inches at Curry Hammock State Park, east of Marathon. Maximum winds were 64 knots (74 mph) gusting to 76 knots (87 mph) at Sombrero Key Light. Maximum storm tides were estimated at 2 to 3 feet above mean sea level, producing minor flooding under elevated homes at Marathon. Minimum pressure reported was 1005.5 mb at Sombrero Key Light. No fatalities or injuries were reported. Damage was estimated at $250K from wind damage to commercial signs, landscaping and electrical equipment. | AO152: 235
A153: 5474033 | B153: MONROE/UPPER KEYS (ZONE) | C153: =_xlfn.XLOOKUP(B153,Match!$A$2:$A$111,Match!$B$2:$B$111) -> Monroe, FL | D153: =_xlfn.XLOOKUP(C153,Validation!$B$2:$B$68,Validation!$A$2:$A$68) -> 12087 | F153: 38541 | G153: 2000 | H153: Hurricane (Typhoon) | K153: 0 | L153: 0 | M153: 100000 | N153: 0 | O153: FL | P153: EST | R153: 1198862 | S153: Z | T153: 76 | U153: EYW | V153: 0 | W153: 0 | X153: NWS STORM SURVEY | AG153: 38542 | AH153: 2200 | AM153: Hurricane Dennis passed within 75 miles southwest of Key West as a category 2 hurricane. In the Monroe County Upper Keys, the maximum rainfall was 1.55 inches at Tavernier. Maximum Storm Tides were estimated at 2 to 3 feet above mean sea level, overtopping bulkheads and producing minor street flooding. Maximum winds were recorded at 51 knots (59 mph) gusting to 59 knots (68 mph) at Carysfort Reef Light. Minimum pressure reported was 1007.6 mb at Molasses Reef Light. No deaths or injuries were reported in the Upper Keys. Damage was estimated at $100K mostly to landscaping and electric utility equipment. | AO153: 236
A154: 5463843 | B154: INLAND SANTA ROSA (ZONE) | C154: =_xlfn.XLOOKUP(B154,Match!$A$2:$A$111,Match!$B$2:$B$111) -> Santa Rosa, FL | D154: =_xlfn.XLOOKUP(C154,Validation!$B$2:$B$68,Validation!$A$2:$A$68) -> 12113 | F154: 38542 | G154: 300 | H154: Hurricane (Typhoon) | K154: 0 | L154: 0 | M154: 0 | N154: 0 | O154: FL | P154: CST | R154: 1194650 | S154: Z | T154: 3 | U154: MOB | V154: 0 | W154: 0 | X154: EMERGENCY MANAGER | AG154: 38543 | AH154: 2100 | AN154: For the second time in less than a week, and the third time in two months, the area was threatened by a tropical event. Major Hurricane Dennis impacted portions of the area during the day and evening of July 10th. The storm made landfall around 130 PM CST as a category three hurricane near Navarre Beach in Santa Rosa county. Dennis then moved north northwest across Santa Rosa and northeast Escambia county in Florida. The weakening storm then moved across the west part of Escambia, the south part of Monroe, the east part of Clarke and the northeast part of Choctaw counties in Alabama. Dennis had a very small eye and winds around the eyewall of the storm caused significant damage as the storm moved north. An aerial survey of the damage showed a five to ten mile wide area of destruction, with most of the damage east of the eye of the storm. As Dennis moved north into Alabama the damage diminished and was confined to a smaller area. A lot of the damage looked like a giant tornado, except the trees were all facing in the same general direction. Coastal counties across the area from Mobile to Destin were put under a Hurricane Watch at 300 PM CST on July 8, then a Hurricane Warning at 300 AM CST on July 9. An Inland Hurricane Warning was issued for most of the inland counties in Alabama at 436 PM CST on July 9. Parts of southeast Mississippi were added to the warning during the early morning hours of July 10. Most of the warnings were dropped at 900 PM CST on July 10 as Dennis weakened as it moved inland._x000D_ Some of the wind reports from across northwest Florida on July 10 were as follows: Pensacola Regional Airport, sustained wind of 66 knots with peak gust of 81 knots. Pensacola Naval Air Station, sustained wind of 39 knots, peak gust 50 knots. Pensacola (WEAR-TV), peak gust 46 knots. Valpariaso (Eglin Air Force Base), sustained winds of 48 knots, peak gust of 72 knots. Destin airport, sustained winds of 49 knots, peak gust 64 knots. Crestview, sustained wind of 37 knots, peak gust 50 knots. Navarre, peak gust of 105 knots. Pensacola (near airport), peak gust 83 knots. Destin (near airport), peak gust 70 knots. Pace, peak gust 92 knots. Pensacola (southeast of airport), peak gust 88 knots. Some of the wind reports across southwest Alabama on July 10 were as follows: Mobile Regional Airport, sustained wind of 32 knots, peak gust of 42 knots. Dauphin Island, sustained wind at 42 knots, gust to 57 knots. Mobile Bay (USS Alabama), peak gust 67 knots. _x000D_ Some of the lowest sea level pressures recorded with Dennis on July 10 were as follows: Pensacola Regional Airport, 956.6 MB. Valpariaso (Eglin Air Force Base), 986.1 MB. Pensacola Naval Air Station, 976.6 MB. Mobile Bay (USS Alabama), 987.8 MB. Mobile Regional Airport, 990.5 MB. _x000D_ The highest 48 hour rainfall totals associated with Hurricane Dennis: In Florida: Pensacola (WEAR) 7.67 inches. Pace, 6.90 inches. Milton, 7.01 inches. Munson, 6.93 inches. Niceville, 5.15 inches. In Alabama: Bay Minette, 4.65 inches. Butler 4.36 inches._x000D_ The highest storm tides from Dennis occurred at: Pensacola with 5.50 feet. Santa Rosa Sound with 5.00 feet. Destin with 4.60 feet. Perdido Pass with 4.10 feet. Pace with 3.5 feet. A storm survey measured 6-6.5 feet on Navarre Beach. Since the eye of Dennis was very small, the highest surge values were near and just to the right of the eye of the storm. Some higher surge values occurred well east of Destin before Dennis moved ashore._x000D_ Major beach erosion occurred from Pensacola Beach to east of Destin. Minor beach erosion occurred from Dauphin Island to Orange Beach. Major flash flooding occurred along and east of the center of Dennis during the afternoon and evening of July 10 across northwest Florida and southwest Alabama. As Dennis moved inland, tornado like damage occurred near the eyewall of storm. Almost every structure located on Navarre Beach suffered some kind of damage. The structures that were located on the beach front all suffered damage. The Air Force bases at Eglin and Hurlburt reported over a half billion dollars in damage from Dennis. Almost 200 homes in northwest Florida reported major damage. Part of U. S. Highway 98 between Fort Walton Beach and Destin in Okaloosa county were again washed out by high water. The west bound lanes were damaged by the surge but the east bound lanes were okay. It was also estimated that most of this years cotton crop in northwest Florida was damaged._x000D_ No direct deaths were reported with Dennis, but three indirect deaths were reported. Two died from Carbon Monoxide poisoning in Escambia county Florida and one from electrocution in Escambia county Alabama. All of the deaths were related to the improper use of emergency generators. | AO154: 237
A155: 5463842 | B155: COASTAL SANTA ROSA (ZONE) | C155: =_xlfn.XLOOKUP(B155,Match!$A$2:$A$111,Match!$B$2:$B$111) -> Santa Rosa, FL | D155: =_xlfn.XLOOKUP(C155,Validation!$B$2:$B$68,Validation!$A$2:$A$68) -> #N/A | F155: 38542 | G155: 300 | H155: Hurricane (Typhoon) | K155: 0 | L155: 0 | M155: 0 | N155: 0 | O155: FL | P155: CST | R155: 1194650 | S155: Z | T155: 4 | U155: MOB | V155: 0 | W155: 0 | X155: EMERGENCY MANAGER | AG155: 38543 | AH155: 2100 | AN155: For the second time in less than a week, and the third time in two months, the area was threatened by a tropical event. Major Hurricane Dennis impacted portions of the area during the day and evening of July 10th. The storm made landfall around 130 PM CST as a category three hurricane near Navarre Beach in Santa Rosa county. Dennis then moved north northwest across Santa Rosa and northeast Escambia county in Florida. The weakening storm then moved across the west part of Escambia, the south part of Monroe, the east part of Clarke and the northeast part of Choctaw counties in Alabama. Dennis had a very small eye and winds around the eyewall of the storm caused significant damage as the storm moved north. An aerial survey of the damage showed a five to ten mile wide area of destruction, with most of the damage east of the eye of the storm. As Dennis moved north into Alabama the damage diminished and was confined to a smaller area. A lot of the damage looked like a giant tornado, except the trees were all facing in the same general direction. Coastal counties across the area from Mobile to Destin were put under a Hurricane Watch at 300 PM CST on July 8, then a Hurricane Warning at 300 AM CST on July 9. An Inland Hurricane Warning was issued for most of the inland counties in Alabama at 436 PM CST on July 9. Parts of southeast Mississippi were added to the warning during the early morning hours of July 10. Most of the warnings were dropped at 900 PM CST on July 10 as Dennis weakened as it moved inland._x000D_ Some of the wind reports from across northwest Florida on July 10 were as follows: Pensacola Regional Airport, sustained wind of 66 knots with peak gust of 81 knots. Pensacola Naval Air Station, sustained wind of 39 knots, peak gust 50 knots. Pensacola (WEAR-TV), peak gust 46 knots. Valpariaso (Eglin Air Force Base), sustained winds of 48 knots, peak gust of 72 knots. Destin airport, sustained winds of 49 knots, peak gust 64 knots. Crestview, sustained wind of 37 knots, peak gust 50 knots. Navarre, peak gust of 105 knots. Pensacola (near airport), peak gust 83 knots. Destin (near airport), peak gust 70 knots. Pace, peak gust 92 knots. Pensacola (southeast of airport), peak gust 88 knots. Some of the wind reports across southwest Alabama on July 10 were as follows: Mobile Regional Airport, sustained wind of 32 knots, peak gust of 42 knots. Dauphin Island, sustained wind at 42 knots, gust to 57 knots. Mobile Bay (USS Alabama), peak gust 67 knots. _x000D_ Some of the lowest sea level pressures recorded with Dennis on July 10 were as follows: Pensacola Regional Airport, 956.6 MB. Valpariaso (Eglin Air Force Base), 986.1 MB. Pensacola Naval Air Station, 976.6 MB. Mobile Bay (USS Alabama), 987.8 MB. Mobile Regional Airport, 990.5 MB. _x000D_ The highest 48 hour rainfall totals associated with Hurricane Dennis: In Florida: Pensacola (WEAR) 7.67 inches. Pace, 6.90 inches. Milton, 7.01 inches. Munson, 6.93 inches. Niceville, 5.15 inches. In Alabama: Bay Minette, 4.65 inches. Butler 4.36 inches._x000D_ The highest storm tides from Dennis occurred at: Pensacola with 5.50 feet. Santa Rosa Sound with 5.00 feet. Destin with 4.60 feet. Perdido Pass with 4.10 feet. Pace with 3.5 feet. A storm survey measured 6-6.5 feet on Navarre Beach. Since the eye of Dennis was very small, the highest surge values were near and just to the right of the eye of the storm. Some higher surge values occurred well east of Destin before Dennis moved ashore._x000D_ Major beach erosion occurred from Pensacola Beach to east of Destin. Minor beach erosion occurred from Dauphin Island to Orange Beach. Major flash flooding occurred along and east of the center of Dennis during the afternoon and evening of July 10 across northwest Florida and southwest Alabama. As Dennis moved inland, tornado like damage occurred near the eyewall of storm. Almost every structure located on Navarre Beach suffered some kind of damage. The structures that were located on the beach front all suffered damage. The Air Force bases at Eglin and Hurlburt reported over a half billion dollars in damage from Dennis. Almost 200 homes in northwest Florida reported major damage. Part of U. S. Highway 98 between Fort Walton Beach and Destin in Okaloosa county were again washed out by high water. The west bound lanes were damaged by the surge but the east bound lanes were okay. It was also estimated that most of this years cotton crop in northwest Florida was damaged._x000D_ No direct deaths were reported with Dennis, but three indirect deaths were reported. Two died from Carbon Monoxide poisoning in Escambia county Florida and one from electrocution in Escambia county Alabama. All of the deaths were related to the improper use of emergency generators. | AO155: 238
A156: 5463841 | B156: INLAND OKALOOSA (ZONE) | C156: =_xlfn.XLOOKUP(B156,Match!$A$2:$A$111,Match!$B$2:$B$111) -> Okaloosa, FL | D156: =_xlfn.XLOOKUP(C156,Validation!$B$2:$B$68,Validation!$A$2:$A$68) -> 12091 | F156: 38542 | G156: 300 | H156: Hurricane (Typhoon) | K156: 0 | L156: 0 | M156: 0 | N156: 0 | O156: FL | P156: CST | R156: 1194650 | S156: Z | T156: 5 | U156: MOB | V156: 0 | W156: 0 | X156: EMERGENCY MANAGER | AG156: 38543 | AH156: 2100 | AN156: For the second time in less than a week, and the third time in two months, the area was threatened by a tropical event. Major Hurricane Dennis impacted portions of the area during the day and evening of July 10th. The storm made landfall around 130 PM CST as a category three hurricane near Navarre Beach in Santa Rosa county. Dennis then moved north northwest across Santa Rosa and northeast Escambia county in Florida. The weakening storm then moved across the west part of Escambia, the south part of Monroe, the east part of Clarke and the northeast part of Choctaw counties in Alabama. Dennis had a very small eye and winds around the eyewall of the storm caused significant damage as the storm moved north. An aerial survey of the damage showed a five to ten mile wide area of destruction, with most of the damage east of the eye of the storm. As Dennis moved north into Alabama the damage diminished and was confined to a smaller area. A lot of the damage looked like a giant tornado, except the trees were all facing in the same general direction. Coastal counties across the area from Mobile to Destin were put under a Hurricane Watch at 300 PM CST on July 8, then a Hurricane Warning at 300 AM CST on July 9. An Inland Hurricane Warning was issued for most of the inland counties in Alabama at 436 PM CST on July 9. Parts of southeast Mississippi were added to the warning during the early morning hours of July 10. Most of the warnings were dropped at 900 PM CST on July 10 as Dennis weakened as it moved inland._x000D_ Some of the wind reports from across northwest Florida on July 10 were as follows: Pensacola Regional Airport, sustained wind of 66 knots with peak gust of 81 knots. Pensacola Naval Air Station, sustained wind of 39 knots, peak gust 50 knots. Pensacola (WEAR-TV), peak gust 46 knots. Valpariaso (Eglin Air Force Base), sustained winds of 48 knots, peak gust of 72 knots. Destin airport, sustained winds of 49 knots, peak gust 64 knots. Crestview, sustained wind of 37 knots, peak gust 50 knots. Navarre, peak gust of 105 knots. Pensacola (near airport), peak gust 83 knots. Destin (near airport), peak gust 70 knots. Pace, peak gust 92 knots. Pensacola (southeast of airport), peak gust 88 knots. Some of the wind reports across southwest Alabama on July 10 were as follows: Mobile Regional Airport, sustained wind of 32 knots, peak gust of 42 knots. Dauphin Island, sustained wind at 42 knots, gust to 57 knots. Mobile Bay (USS Alabama), peak gust 67 knots. _x000D_ Some of the lowest sea level pressures recorded with Dennis on July 10 were as follows: Pensacola Regional Airport, 956.6 MB. Valpariaso (Eglin Air Force Base), 986.1 MB. Pensacola Naval Air Station, 976.6 MB. Mobile Bay (USS Alabama), 987.8 MB. Mobile Regional Airport, 990.5 MB. _x000D_ The highest 48 hour rainfall totals associated with Hurricane Dennis: In Florida: Pensacola (WEAR) 7.67 inches. Pace, 6.90 inches. Milton, 7.01 inches. Munson, 6.93 inches. Niceville, 5.15 inches. In Alabama: Bay Minette, 4.65 inches. Butler 4.36 inches._x000D_ The highest storm tides from Dennis occurred at: Pensacola with 5.50 feet. Santa Rosa Sound with 5.00 feet. Destin with 4.60 feet. Perdido Pass with 4.10 feet. Pace with 3.5 feet. A storm survey measured 6-6.5 feet on Navarre Beach. Since the eye of Dennis was very small, the highest surge values were near and just to the right of the eye of the storm. Some higher surge values occurred well east of Destin before Dennis moved ashore._x000D_ Major beach erosion occurred from Pensacola Beach to east of Destin. Minor beach erosion occurred from Dauphin Island to Orange Beach. Major flash flooding occurred along and east of the center of Dennis during the afternoon and evening of July 10 across northwest Florida and southwest Alabama. As Dennis moved inland, tornado like damage occurred near the eyewall of storm. Almost every structure located on Navarre Beach suffered some kind of damage. The structures that were located on the beach front all suffered damage. The Air Force bases at Eglin and Hurlburt reported over a half billion dollars in damage from Dennis. Almost 200 homes in northwest Florida reported major damage. Part of U. S. Highway 98 between Fort Walton Beach and Destin in Okaloosa county were again washed out by high water. The west bound lanes were damaged by the surge but the east bound lanes were okay. It was also estimated that most of this years cotton crop in northwest Florida was damaged._x000D_ No direct deaths were reported with Dennis, but three indirect deaths were reported. Two died from Carbon Monoxide poisoning in Escambia county Florida and one from electrocution in Escambia county Alabama. All of the deaths were related to the improper use of emergency generators. | AO156: 239
A157: 5463840 | B157: COASTAL OKALOOSA (ZONE) | C157: =_xlfn.XLOOKUP(B157,Match!$A$2:$A$111,Match!$B$2:$B$111) -> Okaloosa, FL | D157: =_xlfn.XLOOKUP(C157,Validation!$B$2:$B$68,Validation!$A$2:$A$68) -> 12091 | F157: 38542 | G157: 300 | H157: Hurricane (Typhoon) | K157: 0 | L157: 0 | M157: 0 | N157: 0 | O157: FL | P157: CST | R157: 1194650 | S157: Z | T157: 6 | U157: MOB | V157: 0 | W157: 0 | X157: EMERGENCY MANAGER | AG157: 38543 | AH157: 2100 | AN157: For the second time in less than a week, and the third time in two months, the area was threatened by a tropical event. Major Hurricane Dennis impacted portions of the area during the day and evening of July 10th. The storm made landfall around 130 PM CST as a category three hurricane near Navarre Beach in Santa Rosa county. Dennis then moved north northwest across Santa Rosa and northeast Escambia county in Florida. The weakening storm then moved across the west part of Escambia, the south part of Monroe, the east part of Clarke and the northeast part of Choctaw counties in Alabama. Dennis had a very small eye and winds around the eyewall of the storm caused significant damage as the storm moved north. An aerial survey of the damage showed a five to ten mile wide area of destruction, with most of the damage east of the eye of the storm. As Dennis moved north into Alabama the damage diminished and was confined to a smaller area. A lot of the damage looked like a giant tornado, except the trees were all facing in the same general direction. Coastal counties across the area from Mobile to Destin were put under a Hurricane Watch at 300 PM CST on July 8, then a Hurricane Warning at 300 AM CST on July 9. An Inland Hurricane Warning was issued for most of the inland counties in Alabama at 436 PM CST on July 9. Parts of southeast Mississippi were added to the warning during the early morning hours of July 10. Most of the warnings were dropped at 900 PM CST on July 10 as Dennis weakened as it moved inland._x000D_ Some of the wind reports from across northwest Florida on July 10 were as follows: Pensacola Regional Airport, sustained wind of 66 knots with peak gust of 81 knots. Pensacola Naval Air Station, sustained wind of 39 knots, peak gust 50 knots. Pensacola (WEAR-TV), peak gust 46 knots. Valpariaso (Eglin Air Force Base), sustained winds of 48 knots, peak gust of 72 knots. Destin airport, sustained winds of 49 knots, peak gust 64 knots. Crestview, sustained wind of 37 knots, peak gust 50 knots. Navarre, peak gust of 105 knots. Pensacola (near airport), peak gust 83 knots. Destin (near airport), peak gust 70 knots. Pace, peak gust 92 knots. Pensacola (southeast of airport), peak gust 88 knots. Some of the wind reports across southwest Alabama on July 10 were as follows: Mobile Regional Airport, sustained wind of 32 knots, peak gust of 42 knots. Dauphin Island, sustained wind at 42 knots, gust to 57 knots. Mobile Bay (USS Alabama), peak gust 67 knots. _x000D_ Some of the lowest sea level pressures recorded with Dennis on July 10 were as follows: Pensacola Regional Airport, 956.6 MB. Valpariaso (Eglin Air Force Base), 986.1 MB. Pensacola Naval Air Station, 976.6 MB. Mobile Bay (USS Alabama), 987.8 MB. Mobile Regional Airport, 990.5 MB. _x000D_ The highest 48 hour rainfall totals associated with Hurricane Dennis: In Florida: Pensacola (WEAR) 7.67 inches. Pace, 6.90 inches. Milton, 7.01 inches. Munson, 6.93 inches. Niceville, 5.15 inches. In Alabama: Bay Minette, 4.65 inches. Butler 4.36 inches._x000D_ The highest storm tides from Dennis occurred at: Pensacola with 5.50 feet. Santa Rosa Sound with 5.00 feet. Destin with 4.60 feet. Perdido Pass with 4.10 feet. Pace with 3.5 feet. A storm survey measured 6-6.5 feet on Navarre Beach. Since the eye of Dennis was very small, the highest surge values were near and just to the right of the eye of the storm. Some higher surge values occurred well east of Destin before Dennis moved ashore._x000D_ Major beach erosion occurred from Pensacola Beach to east of Destin. Minor beach erosion occurred from Dauphin Island to Orange Beach. Major flash flooding occurred along and east of the center of Dennis during the afternoon and evening of July 10 across northwest Florida and southwest Alabama. As Dennis moved inland, tornado like damage occurred near the eyewall of storm. Almost every structure located on Navarre Beach suffered some kind of damage. The structures that were located on the beach front all suffered damage. The Air Force bases at Eglin and Hurlburt reported over a half billion dollars in damage from Dennis. Almost 200 homes in northwest Florida reported major damage. Part of U. S. Highway 98 between Fort Walton Beach and Destin in Okaloosa county were again washed out by high water. The west bound lanes were damaged by the surge but the east bound lanes were okay. It was also estimated that most of this years cotton crop in northwest Florida was damaged._x000D_ No direct deaths were reported with Dennis, but three indirect deaths were reported. Two died from Carbon Monoxide poisoning in Escambia county Florida and one from electrocution in Escambia county Alabama. All of the deaths were related to the improper use of emergency generators. | AO157: 240
A158: 5463839 | B158: INLAND ESCAMBIA (ZONE) | C158: =_xlfn.XLOOKUP(B158,Match!$A$2:$A$111,Match!$B$2:$B$111) -> Escambia, FL | D158: =_xlfn.XLOOKUP(C158,Validation!$B$2:$B$68,Validation!$A$2:$A$68) -> 12033 | F158: 38542 | G158: 300 | H158: Hurricane (Typhoon) | K158: 0 | L158: 0 | M158: 0 | N158: 0 | O158: FL | P158: CST | R158: 1194650 | S158: Z | T158: 1 | U158: MOB | V158: 0 | W158: 0 | X158: EMERGENCY MANAGER | AG158: 38543 | AH158: 2100 | AN158: For the second time in less than a week, and the third time in two months, the area was threatened by a tropical event. Major Hurricane Dennis impacted portions of the area during the day and evening of July 10th. The storm made landfall around 130 PM CST as a category three hurricane near Navarre Beach in Santa Rosa county. Dennis then moved north northwest across Santa Rosa and northeast Escambia county in Florida. The weakening storm then moved across the west part of Escambia, the south part of Monroe, the east part of Clarke and the northeast part of Choctaw counties in Alabama. Dennis had a very small eye and winds around the eyewall of the storm caused significant damage as the storm moved north. An aerial survey of the damage showed a five to ten mile wide area of destruction, with most of the damage east of the eye of the storm. As Dennis moved north into Alabama the damage diminished and was confined to a smaller area. A lot of the damage looked like a giant tornado, except the trees were all facing in the same general direction. Coastal counties across the area from Mobile to Destin were put under a Hurricane Watch at 300 PM CST on July 8, then a Hurricane Warning at 300 AM CST on July 9. An Inland Hurricane Warning was issued for most of the inland counties in Alabama at 436 PM CST on July 9. Parts of southeast Mississippi were added to the warning during the early morning hours of July 10. Most of the warnings were dropped at 900 PM CST on July 10 as Dennis weakened as it moved inland._x000D_ Some of the wind reports from across northwest Florida on July 10 were as follows: Pensacola Regional Airport, sustained wind of 66 knots with peak gust of 81 knots. Pensacola Naval Air Station, sustained wind of 39 knots, peak gust 50 knots. Pensacola (WEAR-TV), peak gust 46 knots. Valpariaso (Eglin Air Force Base), sustained winds of 48 knots, peak gust of 72 knots. Destin airport, sustained winds of 49 knots, peak gust 64 knots. Crestview, sustained wind of 37 knots, peak gust 50 knots. Navarre, peak gust of 105 knots. Pensacola (near airport), peak gust 83 knots. Destin (near airport), peak gust 70 knots. Pace, peak gust 92 knots. Pensacola (southeast of airport), peak gust 88 knots. Some of the wind reports across southwest Alabama on July 10 were as follows: Mobile Regional Airport, sustained wind of 32 knots, peak gust of 42 knots. Dauphin Island, sustained wind at 42 knots, gust to 57 knots. Mobile Bay (USS Alabama), peak gust 67 knots. _x000D_ Some of the lowest sea level pressures recorded with Dennis on July 10 were as follows: Pensacola Regional Airport, 956.6 MB. Valpariaso (Eglin Air Force Base), 986.1 MB. Pensacola Naval Air Station, 976.6 MB. Mobile Bay (USS Alabama), 987.8 MB. Mobile Regional Airport, 990.5 MB. _x000D_ The highest 48 hour rainfall totals associated with Hurricane Dennis: In Florida: Pensacola (WEAR) 7.67 inches. Pace, 6.90 inches. Milton, 7.01 inches. Munson, 6.93 inches. Niceville, 5.15 inches. In Alabama: Bay Minette, 4.65 inches. Butler 4.36 inches._x000D_ The highest storm tides from Dennis occurred at: Pensacola with 5.50 feet. Santa Rosa Sound with 5.00 feet. Destin with 4.60 feet. Perdido Pass with 4.10 feet. Pace with 3.5 feet. A storm survey measured 6-6.5 feet on Navarre Beach. Since the eye of Dennis was very small, the highest surge values were near and just to the right of the eye of the storm. Some higher surge values occurred well east of Destin before Dennis moved ashore._x000D_ Major beach erosion occurred from Pensacola Beach to east of Destin. Minor beach erosion occurred from Dauphin Island to Orange Beach. Major flash flooding occurred along and east of the center of Dennis during the afternoon and evening of July 10 across northwest Florida and southwest Alabama. As Dennis moved inland, tornado like damage occurred near the eyewall of storm. Almost every structure located on Navarre Beach suffered some kind of damage. The structures that were located on the beach front all suffered damage. The Air Force bases at Eglin and Hurlburt reported over a half billion dollars in damage from Dennis. Almost 200 homes in northwest Florida reported major damage. Part of U. S. Highway 98 between Fort Walton Beach and Destin in Okaloosa county were again washed out by high water. The west bound lanes were damaged by the surge but the east bound lanes were okay. It was also estimated that most of this years cotton crop in northwest Florida was damaged._x000D_ No direct deaths were reported with Dennis, but three indirect deaths were reported. Two died from Carbon Monoxide poisoning in Escambia county Florida and one from electrocution in Escambia county Alabama. All of the deaths were related to the improper use of emergency generators. | AO158: 241
A159: 5463838 | B159: COASTAL ESCAMBIA (ZONE) | C159: =_xlfn.XLOOKUP(B159,Match!$A$2:$A$111,Match!$B$2:$B$111) -> Escambia, FL | D159: =_xlfn.XLOOKUP(C159,Validation!$B$2:$B$68,Validation!$A$2:$A$68) -> 12033 | F159: 38542 | G159: 300 | H159: Hurricane (Typhoon) | K159: 0 | L159: 0 | M159: 1500000000 | N159: 300000 | O159: FL | P159: CST | R159: 1194650 | S159: Z | T159: 2 | U159: MOB | V159: 0 | W159: 0 | X159: EMERGENCY MANAGER | AG159: 38543 | AH159: 2100 | AN159: For the second time in less than a week, and the third time in two months, the area was threatened by a tropical event. Major Hurricane Dennis impacted portions of the area during the day and evening of July 10th. The storm made landfall around 130 PM CST as a category three hurricane near Navarre Beach in Santa Rosa county. Dennis then moved north northwest across Santa Rosa and northeast Escambia county in Florida. The weakening storm then moved across the west part of Escambia, the south part of Monroe, the east part of Clarke and the northeast part of Choctaw counties in Alabama. Dennis had a very small eye and winds around the eyewall of the storm caused significant damage as the storm moved north. An aerial survey of the damage showed a five to ten mile wide area of destruction, with most of the damage east of the eye of the storm. As Dennis moved north into Alabama the damage diminished and was confined to a smaller area. A lot of the damage looked like a giant tornado, except the trees were all facing in the same general direction. Coastal counties across the area from Mobile to Destin were put under a Hurricane Watch at 300 PM CST on July 8, then a Hurricane Warning at 300 AM CST on July 9. An Inland Hurricane Warning was issued for most of the inland counties in Alabama at 436 PM CST on July 9. Parts of southeast Mississippi were added to the warning during the early morning hours of July 10. Most of the warnings were dropped at 900 PM CST on July 10 as Dennis weakened as it moved inland._x000D_ Some of the wind reports from across northwest Florida on July 10 were as follows: Pensacola Regional Airport, sustained wind of 66 knots with peak gust of 81 knots. Pensacola Naval Air Station, sustained wind of 39 knots, peak gust 50 knots. Pensacola (WEAR-TV), peak gust 46 knots. Valpariaso (Eglin Air Force Base), sustained winds of 48 knots, peak gust of 72 knots. Destin airport, sustained winds of 49 knots, peak gust 64 knots. Crestview, sustained wind of 37 knots, peak gust 50 knots. Navarre, peak gust of 105 knots. Pensacola (near airport), peak gust 83 knots. Destin (near airport), peak gust 70 knots. Pace, peak gust 92 knots. Pensacola (southeast of airport), peak gust 88 knots. Some of the wind reports across southwest Alabama on July 10 were as follows: Mobile Regional Airport, sustained wind of 32 knots, peak gust of 42 knots. Dauphin Island, sustained wind at 42 knots, gust to 57 knots. Mobile Bay (USS Alabama), peak gust 67 knots. _x000D_ Some of the lowest sea level pressures recorded with Dennis on July 10 were as follows: Pensacola Regional Airport, 956.6 MB. Valpariaso (Eglin Air Force Base), 986.1 MB. Pensacola Naval Air Station, 976.6 MB. Mobile Bay (USS Alabama), 987.8 MB. Mobile Regional Airport, 990.5 MB. _x000D_ The highest 48 hour rainfall totals associated with Hurricane Dennis: In Florida: Pensacola (WEAR) 7.67 inches. Pace, 6.90 inches. Milton, 7.01 inches. Munson, 6.93 inches. Niceville, 5.15 inches. In Alabama: Bay Minette, 4.65 inches. Butler 4.36 inches._x000D_ The highest storm tides from Dennis occurred at: Pensacola with 5.50 feet. Santa Rosa Sound with 5.00 feet. Destin with 4.60 feet. Perdido Pass with 4.10 feet. Pace with 3.5 feet. A storm survey measured 6-6.5 feet on Navarre Beach. Since the eye of Dennis was very small, the highest surge values were near and just to the right of the eye of the storm. Some higher surge values occurred well east of Destin before Dennis moved ashore._x000D_ Major beach erosion occurred from Pensacola Beach to east of Destin. Minor beach erosion occurred from Dauphin Island to Orange Beach. Major flash flooding occurred along and east of the center of Dennis during the afternoon and evening of July 10 across northwest Florida and southwest Alabama. As Dennis moved inland, tornado like damage occurred near the eyewall of storm. Almost every structure located on Navarre Beach suffered some kind of damage. The structures that were located on the beach front all suffered damage. The Air Force bases at Eglin and Hurlburt reported over a half billion dollars in damage from Dennis. Almost 200 homes in northwest Florida reported major damage. Part of U. S. Highway 98 between Fort Walton Beach and Destin in Okaloosa county were again washed out by high water. The west bound lanes were damaged by the surge but the east bound lanes were okay. It was also estimated that most of this years cotton crop in northwest Florida was damaged._x000D_ No direct deaths were reported with Dennis, but three indirect deaths were reported. Two died from Carbon Monoxide poisoning in Escambia county Florida and one from electrocution in Escambia county Alabama. All of the deaths were related to the improper use of emergency generators. | AO159: 242
A160: 5463445 | B160: TAYLOR (ZONE) | C160: =_xlfn.XLOOKUP(B160,Match!$A$2:$A$111,Match!$B$2:$B$111) -> Taylor, FL | D160: =_xlfn.XLOOKUP(C160,Validation!$B$2:$B$68,Validation!$A$2:$A$68) -> 12123 | F160: 38542 | G160: 1800 | H160: Hurricane (Typhoon) | K160: 0 | L160: 0 | M160: 4000000 | N160: 0 | O160: FL | P160: EST | R160: 1195140 | S160: Z | T160: 28 | U160: TAE | V160: 0 | W160: 0 | X160: EMERGENCY MANAGER | AG160: 38544 | AH160: 1200 | AN160: Dennis, a Category 3 hurricane, moved inland just east of Gulf Breeze, FL, early Sunday afternoon, July 10. The peak wind gust and lowest sea-level pressure recorded were 67 knots and 979 mb, respectively, at Buoy 42039 located 80 miles south of Panama City, FL. Rainfall totals ranged from 3 to 4 inches in the eastern Florida Panhandle to 6 to 10 inches in the Florida Big Bend. Flooding was reported in southern Leon County where several areas were under 3 to 4 feet of water. Maximum coastal storm surge heights ranged from 4 to 8 feet in Walton, Bay, Gulf, Taylor and Dixie counties to 8 to 12 feet in Franklin, Wakulla and Jefferson counties. Moderate to severe beach erosion was observed along the beaches of Walton, Bay, Gulf, Franklin and Wakulla counties. Across coastal Walton County, all public dunes and walkovers were damaged. At St George Island, five miles of road and numerous structures were damaged or destroyed by Dennis' storm surge. Dennis' deluge caused several rivers and creeks in the Florida Panhandle and Big Bend to exceed their flood stages, including the Ocklockonee, Aucilla, St Marks rivers, and Spring Creek. An interesting aspect to the flooding is the remarkable surge up to 8 feet that propagated up the rivers. This surge was evident from the mouth of the Suwannee River to as far west as the Choctawhatchee River. The worst property damage occurred along the coast from Walton to Wakulla County, where more than a 1,000 homes and businesses were affected. Also, there were numerous reports of downed trees and power lines across the Florida Panhandle and Big Bend, leaving about 75,000 customers without power. Bay, Dixie, Franklin, Gulf, Taylor, Wakulla and Walton counties were declared federal disaster areas. | AO160: 243
A161: 5463442 | B161: LEON (ZONE) | C161: =_xlfn.XLOOKUP(B161,Match!$A$2:$A$111,Match!$B$2:$B$111) -> Leon, FL | D161: =_xlfn.XLOOKUP(C161,Validation!$B$2:$B$68,Validation!$A$2:$A$68) -> 12073 | F161: 38542 | G161: 1800 | H161: Hurricane (Typhoon) | K161: 0 | L161: 0 | M161: 2000000 | N161: 0 | O161: FL | P161: EST | R161: 1195140 | S161: Z | T161: 17 | U161: TAE | V161: 0 | W161: 0 | X161: EMERGENCY MANAGER | AG161: 38544 | AH161: 1200 | AN161: Dennis, a Category 3 hurricane, moved inland just east of Gulf Breeze, FL, early Sunday afternoon, July 10. The peak wind gust and lowest sea-level pressure recorded were 67 knots and 979 mb, respectively, at Buoy 42039 located 80 miles south of Panama City, FL. Rainfall totals ranged from 3 to 4 inches in the eastern Florida Panhandle to 6 to 10 inches in the Florida Big Bend. Flooding was reported in southern Leon County where several areas were under 3 to 4 feet of water. Maximum coastal storm surge heights ranged from 4 to 8 feet in Walton, Bay, Gulf, Taylor and Dixie counties to 8 to 12 feet in Franklin, Wakulla and Jefferson counties. Moderate to severe beach erosion was observed along the beaches of Walton, Bay, Gulf, Franklin and Wakulla counties. Across coastal Walton County, all public dunes and walkovers were damaged. At St George Island, five miles of road and numerous structures were damaged or destroyed by Dennis' storm surge. Dennis' deluge caused several rivers and creeks in the Florida Panhandle and Big Bend to exceed their flood stages, including the Ocklockonee, Aucilla, St Marks rivers, and Spring Creek. An interesting aspect to the flooding is the remarkable surge up to 8 feet that propagated up the rivers. This surge was evident from the mouth of the Suwannee River to as far west as the Choctawhatchee River. The worst property damage occurred along the coast from Walton to Wakulla County, where more than a 1,000 homes and businesses were affected. Also, there were numerous reports of downed trees and power lines across the Florida Panhandle and Big Bend, leaving about 75,000 customers without power. Bay, Dixie, Franklin, Gulf, Taylor, Wakulla and Walton counties were declared federal disaster areas. | AO161: 244
A162: 5463441 | B162: LAFAYETTE (ZONE) | C162: =_xlfn.XLOOKUP(B162,Match!$A$2:$A$111,Match!$B$2:$B$111) -> Lafayette, FL | D162: =_xlfn.XLOOKUP(C162,Validation!$B$2:$B$68,Validation!$A$2:$A$68) -> 12067 | F162: 38542 | G162: 1800 | H162: Hurricane (Typhoon) | K162: 0 | L162: 0 | M162: 200000 | N162: 0 | O162: FL | P162: EST | R162: 1195140 | S162: Z | T162: 29 | U162: TAE | V162: 0 | W162: 0 | X162: EMERGENCY MANAGER | AG162: 38544 | AH162: 1200 | AN162: Dennis, a Category 3 hurricane, moved inland just east of Gulf Breeze, FL, early Sunday afternoon, July 10. The peak wind gust and lowest sea-level pressure recorded were 67 knots and 979 mb, respectively, at Buoy 42039 located 80 miles south of Panama City, FL. Rainfall totals ranged from 3 to 4 inches in the eastern Florida Panhandle to 6 to 10 inches in the Florida Big Bend. Flooding was reported in southern Leon County where several areas were under 3 to 4 feet of water. Maximum coastal storm surge heights ranged from 4 to 8 feet in Walton, Bay, Gulf, Taylor and Dixie counties to 8 to 12 feet in Franklin, Wakulla and Jefferson counties. Moderate to severe beach erosion was observed along the beaches of Walton, Bay, Gulf, Franklin and Wakulla counties. Across coastal Walton County, all public dunes and walkovers were damaged. At St George Island, five miles of road and numerous structures were damaged or destroyed by Dennis' storm surge. Dennis' deluge caused several rivers and creeks in the Florida Panhandle and Big Bend to exceed their flood stages, including the Ocklockonee, Aucilla, St Marks rivers, and Spring Creek. An interesting aspect to the flooding is the remarkable surge up to 8 feet that propagated up the rivers. This surge was evident from the mouth of the Suwannee River to as far west as the Choctawhatchee River. The worst property damage occurred along the coast from Walton to Wakulla County, where more than a 1,000 homes and businesses were affected. Also, there were numerous reports of downed trees and power lines across the Florida Panhandle and Big Bend, leaving about 75,000 customers without power. Bay, Dixie, Franklin, Gulf, Taylor, Wakulla and Walton counties were declared federal disaster areas. | AO162: 245
A163: 5463440 | B163: JEFFERSON (ZONE) | C163: =_xlfn.XLOOKUP(B163,Match!$A$2:$A$111,Match!$B$2:$B$111) -> Jefferson, FL | D163: =_xlfn.XLOOKUP(C163,Validation!$B$2:$B$68,Validation!$A$2:$A$68) -> 12065 | F163: 38542 | G163: 1800 | H163: Hurricane (Typhoon) | K163: 0 | L163: 0 | M163: 200000 | N163: 0 | O163: FL | P163: EST | R163: 1195140 | S163: Z | T163: 18 | U163: TAE | V163: 0 | W163: 0 | X163: EMERGENCY MANAGER | AG163: 38543 | AH163: 1200 | AN163: Dennis, a Category 3 hurricane, moved inland just east of Gulf Breeze, FL, early Sunday afternoon, July 10. The peak wind gust and lowest sea-level pressure recorded were 67 knots and 979 mb, respectively, at Buoy 42039 located 80 miles south of Panama City, FL. Rainfall totals ranged from 3 to 4 inches in the eastern Florida Panhandle to 6 to 10 inches in the Florida Big Bend. Flooding was reported in southern Leon County where several areas were under 3 to 4 feet of water. Maximum coastal storm surge heights ranged from 4 to 8 feet in Walton, Bay, Gulf, Taylor and Dixie counties to 8 to 12 feet in Franklin, Wakulla and Jefferson counties. Moderate to severe beach erosion was observed along the beaches of Walton, Bay, Gulf, Franklin and Wakulla counties. Across coastal Walton County, all public dunes and walkovers were damaged. At St George Island, five miles of road and numerous structures were damaged or destroyed by Dennis' storm surge. Dennis' deluge caused several rivers and creeks in the Florida Panhandle and Big Bend to exceed their flood stages, including the Ocklockonee, Aucilla, St Marks rivers, and Spring Creek. An interesting aspect to the flooding is the remarkable surge up to 8 feet that propagated up the rivers. This surge was evident from the mouth of the Suwannee River to as far west as the Choctawhatchee River. The worst property damage occurred along the coast from Walton to Wakulla County, where more than a 1,000 homes and businesses were affected. Also, there were numerous reports of downed trees and power lines across the Florida Panhandle and Big Bend, leaving about 75,000 customers without power. Bay, Dixie, Franklin, Gulf, Taylor, Wakulla and Walton counties were declared federal disaster areas. | AO163: 246
A164: 5463430 | B164: BAY (ZONE) | C164: =_xlfn.XLOOKUP(B164,Match!$A$2:$A$111,Match!$B$2:$B$111) -> Bay, FL | D164: =_xlfn.XLOOKUP(C164,Validation!$B$2:$B$68,Validation!$A$2:$A$68) -> 12005 | F164: 38542 | G164: 1800 | H164: Hurricane (Typhoon) | K164: 0 | L164: 0 | M164: 10000000 | N164: 0 | O164: FL | P164: EST | R164: 1195140 | S164: Z | T164: 12 | U164: TAE | V164: 0 | W164: 0 | X164: EMERGENCY MANAGER | AG164: 38544 | AH164: 1200 | AN164: Dennis, a Category 3 hurricane, moved inland just east of Gulf Breeze, FL, early Sunday afternoon, July 10. The peak wind gust and lowest sea-level pressure recorded were 67 knots and 979 mb, respectively, at Buoy 42039 located 80 miles south of Panama City, FL. Rainfall totals ranged from 3 to 4 inches in the eastern Florida Panhandle to 6 to 10 inches in the Florida Big Bend. Flooding was reported in southern Leon County where several areas were under 3 to 4 feet of water. Maximum coastal storm surge heights ranged from 4 to 8 feet in Walton, Bay, Gulf, Taylor and Dixie counties to 8 to 12 feet in Franklin, Wakulla and Jefferson counties. Moderate to severe beach erosion was observed along the beaches of Walton, Bay, Gulf, Franklin and Wakulla counties. Across coastal Walton County, all public dunes and walkovers were damaged. At St George Island, five miles of road and numerous structures were damaged or destroyed by Dennis' storm surge. Dennis' deluge caused several rivers and creeks in the Florida Panhandle and Big Bend to exceed their flood stages, including the Ocklockonee, Aucilla, St Marks rivers, and Spring Creek. An interesting aspect to the flooding is the remarkable surge up to 8 feet that propagated up the rivers. This surge was evident from the mouth of the Suwannee River to as far west as the Choctawhatchee River. The worst property damage occurred along the coast from Walton to Wakulla County, where more than a 1,000 homes and businesses were affected. Also, there were numerous reports of downed trees and power lines across the Florida Panhandle and Big Bend, leaving about 75,000 customers without power. Bay, Dixie, Franklin, Gulf, Taylor, Wakulla and Walton counties were declared federal disaster areas. | AO164: 247
A165: 5463444 | B165: MADISON (ZONE) | C165: =_xlfn.XLOOKUP(B165,Match!$A$2:$A$111,Match!$B$2:$B$111) -> Madison, FL | D165: =_xlfn.XLOOKUP(C165,Validation!$B$2:$B$68,Validation!$A$2:$A$68) -> 12079 | F165: 38542 | G165: 1800 | H165: Hurricane (Typhoon) | K165: 0 | L165: 0 | M165: 200000 | N165: 0 | O165: FL | P165: EST | R165: 1195140 | S165: Z | T165: 19 | U165: TAE | V165: 0 | W165: 0 | X165: EMERGENCY MANAGER | AG165: 38544 | AH165: 1200 | AN165: Dennis, a Category 3 hurricane, moved inland just east of Gulf Breeze, FL, early Sunday afternoon, July 10. The peak wind gust and lowest sea-level pressure recorded were 67 knots and 979 mb, respectively, at Buoy 42039 located 80 miles south of Panama City, FL. Rainfall totals ranged from 3 to 4 inches in the eastern Florida Panhandle to 6 to 10 inches in the Florida Big Bend. Flooding was reported in southern Leon County where several areas were under 3 to 4 feet of water. Maximum coastal storm surge heights ranged from 4 to 8 feet in Walton, Bay, Gulf, Taylor and Dixie counties to 8 to 12 feet in Franklin, Wakulla and Jefferson counties. Moderate to severe beach erosion was observed along the beaches of Walton, Bay, Gulf, Franklin and Wakulla counties. Across coastal Walton County, all public dunes and walkovers were damaged. At St George Island, five miles of road and numerous structures were damaged or destroyed by Dennis' storm surge. Dennis' deluge caused several rivers and creeks in the Florida Panhandle and Big Bend to exceed their flood stages, including the Ocklockonee, Aucilla, St Marks rivers, and Spring Creek. An interesting aspect to the flooding is the remarkable surge up to 8 feet that propagated up the rivers. This surge was evident from the mouth of the Suwannee River to as far west as the Choctawhatchee River. The worst property damage occurred along the coast from Walton to Wakulla County, where more than a 1,000 homes and businesses were affected. Also, there were numerous reports of downed trees and power lines across the Florida Panhandle and Big Bend, leaving about 75,000 customers without power. Bay, Dixie, Franklin, Gulf, Taylor, Wakulla and Walton counties were declared federal disaster areas. | AO165: 248
... A186: 5470156 | B186: COASTAL BROWARD (ZONE) | C186: =_xlfn.XLOOKUP(B186,Match!$A$2:$A$111,Match!$B$2:$B$111) -> Broward, FL | D186: =_xlfn.XLOOKUP(C186,Validation!$B$2:$B$68,Validation!$A$2:$A$68) -> 12011 | F186: 38589 | G186: 1200 | H186: Hurricane (Typhoon) | K186: 0 | L186: 0 | M186: 36000000 | N186: 0 | O186: FL | P186: EST | R186: 1196431 | S186: Z | T186: 72 | U186: MFL | V186: 0 | W186: 0 | X186: NEWSPAPER | AG186: 38590 | AH186: 800 | AN186: A tropical wave that moved across the Atlantic from near the west coast of Africa eventually spawned the tropical cyclone that became hurricane Katrina. The tropical wave became a tropical depression near the central Bahamas late on August 22. The depression moved slowly northwest and became tropical storm Katrina on August 24 near the northwest Bahama Islands then turned west and intensified to a hurricane on August 25, a few hours before making landfall on the southeast Florida Coast._x000D_ _x000D_ The center of the ragged 25-mile-wide eye of Katrina made landfall around 6:30 PM EDT, Thursday, August 25 near the Broward/Miami-Dade County border then moved toward the southwest across central and southwest Miami-Dade County, passing directly over the National Weather Service (NWS) Office in Sweetwater. Katrina briefly weakened to a tropical storm before exiting the Florida peninsula into the Gulf of Mexico early on August 26 just north of Cape Sable in mainland Monroe County then quickly regained hurricane strength in the southeast Gulf of Mexico. The distribution of winds and rain near the center of Katrina while passing across the south Florida peninsula were asymmetrical with the strongest winds and heaviest rain located to the south and east of the center._x000D_ _x000D_ Measurements from reconnaissance aircraft and Miami Doppler Weather Radar estimated maximum sustained winds in Katrina to be 80 mph. The maximum reported sustained surface wind over the south Florida peninsula was 72 mph measured atop a building at the University of Miami's Rosenstiel School of Marine and Atmospheric Science (RSMAS) on Virginia Key. This wind value was determined by adjusting the actual wind speed to the standard anemometer height of 10 meters. This same site recorded an unadjusted peak wind speed of 94 mph. The anemometer atop the Miami Weather Forecast Office in Sweetwater measured a sustained wind of 69 mph. Maximum sustained winds measured at the NWS Automated Surface Observing System (ASOS) sites included 60 mph at Fort Lauderdale-Hollywood International Airport, 50 mph at Tamiami Airport in West Kendall and 48 mph at Miami International Airport._x000D_ _x000D_ The maximum ASOS-measured peak wind gusts included 82 mph at Fort Lauderdale-Hollywood International Airport, 78 mph at Miami International Airport and 76 mph at Tamiami Airport in West Kendall. Other unofficial peak wind gust measurements included 97 mph at Homestead General Airport, 92 mph at Port Everglades, 87 mph at the Miami Weather Forecast Office in Sweetwater, 77 mph at Marco Island, 76 mph at the Atlantic Oceanographic and Meteorological Laboratory (AOML) on Virginia Key, and 64 mph at Boca Raton Airport. The minimum pressure measured over the south Florida peninsula was 983.1 millibars at the NWS site in Sweetwater._x000D_ _x000D_ Rainfall amounts were excessive across portions of south Miami-Dade County causing flooding of structures, vehicles, crop lands and nurseries. A maximum storm total amount of 16.33 inches, of which 15.10 inches fell in a 24-hour period, was measured by a cooperative observed in Perrine. Other heavy storm total amounts in south Miami-Dade County included 14.04 inches at Homestead Air Reserve Base, 12.25 inches near Florida City and 11.13 inches near Cutler Ridge. Most of the remainder of metropolitan Miami-Dade County and all of metropolitan Broward and Palm Beach counties generally received rain amounts of two to four inches. Rainfall over interior south Florida ranged from one to three inches with mostly less than one inch over coastal Collier County._x000D_ _x000D_ Mostly minor beach erosion and isolated incidence of coastal flooding were observed. The maximum storm tide was estimated at three to five feet along the southwest Florida coast in mainland Monroe County. This caused water damage to several homes, trailers and vehicles at Flamingo in Everglades National Park early on August 26. Other maximum storm tide values included 3.0 feet at Naples Pier along the southwest coast at 2.1 feet at Virginia Key on the southeast coast._x000D_ _x000D_ A total of six persons are known to have died directly as a result of the winds and water. Three of the deaths, all in Broward County, were associated with trees or tree limbs that were blown down, striking people. The other three deaths, all in Miami-Dade County, were associated with drownings, two on boats and one under unknown circumstances. In addition at least another six people died from indirect hurricane effects including three from carbon monoxide poisoning caused by generators, one in a vehicle accident, one during debris cleanup and one associated with a lack of electricity. Several people were injured, including five or six related to carbon monoxide poisoning._x000D_ _x000D_ Total damage in south Florida was estimated at around $100 million. Between 100 and 200 houses suffered significant damage, mainly in south Miami-Dade due to flooding. Wind damage was mainly to vegetation, signs, and watercraft. Winds and flooding combined caused an estimated $423 million in losses to agriculture and nurseries. | AO186: 269
A187: 5474301 | B187: MONROE/LOWER KEYS (ZONE) | C187: =_xlfn.XLOOKUP(B187,Match!$A$2:$A$111,Match!$B$2:$B$111) -> Monroe, FL | D187: =_xlfn.XLOOKUP(C187,Validation!$B$2:$B$68,Validation!$A$2:$A$68) -> 12087 | F187: 38590 | G187: 800 | H187: Hurricane (Typhoon) | K187: 0 | L187: 0 | M187: 1000000 | N187: 0 | O187: FL | P187: EST | R187: 1198872 | S187: Z | T187: 78 | U187: EYW | V187: 0 | W187: 0 | X187: NWS STORM SURVEY | AG187: 38591 | AH187: 0 | AM187: Hurricane Katrina passed 40 miles north of Key West as a category one hurricane. Katrina passed 15 miles north Dry Tortugas National Park as a category 2 hurricane. Over the Monroe County Lower Keys, maximum winds were 54 knots (62 mph) with gusts to 67 knots (77 mph) at Sand Key. Rainfall totalled 10.05 inches at Key West, resulting in extensive street flooding and some residential flooding in Key West. Lowest pressure reported was 999.3 mb at Key West, and 974.4 mb at Dry Tortugas National Park. Storm tides were estimated at 2.5 feet above mean sea level at Key West. Total property damages estimated near $1 million. Most damage caused by wind and resulting rainwater intrusion to homes and businesses. | AO187: 270
